Workbook

Sheet Resumo executivo
A1: Relatório econômico-fiscal do Brasil – 2016 × 2019 × 2022 × 2025
A2: Escopo nacional; contas públicas com prioridade à União/Governo Central. Dados acessados em 22/09/2026. Valores nominais do próprio ano; correção pelo IPCA até dez/2025.
A4: Parâmetros de cálculo | B4: 2016 | C4: 2019 | D4: 2022 | E4: 2025
A5: PIB (R$ bi, IBGE SIDRA 1846) | B5: 6269.327 | C5: 7389.131 | D5: 10079.676 | E5: 12738.566
A6: IPCA número-índice de dezembro (SIDRA 1737) | B6: 4775.7 | C6: 5320.25 | D6: 6474.09 | E6: 7403.29
A7: Fator IPCA dez/ano → dez/2025 | B7: =IPCA_DEZ_2025/IPCA_DEZ_2016 -> 1.5502 | C7: =IPCA_DEZ_2025/IPCA_DEZ_2019 -> 1.3915305 | D7: =IPCA_DEZ_2025/IPCA_DEZ_2022 -> 1.143526 | E7: =IPCA_DEZ_2025/IPCA_DEZ_2025 -> 1
A8: PTAX média anual (R$/US$, média das médias mensais – BCB SGS 3698) | B8: =AVERAGE(4.0524,3.9737,3.7039,3.5658,3.5393,3.4245,3.2756,3.2097,3.2564,3.1858,3.342,3.3523) -> 3.4901167 | C8: =AVERAGE(3.7417,3.7236,3.8465,3.8962,4.0015,3.8588,3.7793,4.02,4.1215,4.087,4.1553,4.1096) -> 3.9450833 | D8: =AVERAGE(5.5341,5.1966,4.9684,4.758,4.9551,5.0492,5.3681,5.1433,5.237,5.2503,5.2747,5.2424) -> 5.1647667 | E8: =AVERAGE(6.0218,5.7656,5.7468,5.7837,5.6674,5.5471,5.5285,5.4469,5.3674,5.3855,5.3409,5.4531) -> 5.5878917
A9: PIB em US$ bi | B9: =PIB_2016/PTAX_2016 -> 1796.3087 | C9: =PIB_2019/PTAX_2019 -> 1872.9974 | D9: =PIB_2022/PTAX_2022 -> 1951.6227 | E9: =PIB_2025/PTAX_2025 -> 2279.673
A11: Principais indicadores
A12: Indicador | B12: 2016 | C12: 2019 | D12: 2022 | E12: 2025 | F12: Var. real 2016→2019 | G12: Var. real 2019→2022 | H12: Var. real 2022→2025 | I12: Leitura
A13: PIB (R$ bi) | B13: ='PIB setorial'!F4 -> 6269.327 | C13: ='PIB setorial'!G4 -> 7389.131 | D13: ='PIB setorial'!H4 -> 10079.676 | E13: ='PIB setorial'!I4 -> 12738.566 | F13: =IFERROR((C13*FATOR_2019)/(B13*FATOR_2016)-1,"n.d.") -> 0.057979958 | G13: =IFERROR((D13*FATOR_2022)/(C13*FATOR_2019)-1,"n.d.") -> 0.12100233 | H13: =IFERROR((E13*FATOR_2025)/(D13*FATOR_2022)-1,"n.d.") -> 0.10516708 | I13: Recessão 2015–16, pandemia em 2020 e recuperação desde 2021.
A14: Participação da agropecuária no PIB | B14: ='PIB setorial'!F22 -> 0.048913384 | C14: ='PIB setorial'!G22 -> 0.042050141 | D14: ='PIB setorial'!H22 -> 0.05767477 | E14: ='PIB setorial'!I22 -> 0.060862188 | F14: =IFERROR((C14-B14)*100,"n.d.") -> -0.68632432 | G14: =IFERROR((D14-C14)*100,"n.d.") -> 1.562463 | H14: =IFERROR((E14-D14)*100,"n.d.") -> 0.31874176 | I14: Ganho contínuo de peso relativo.
A15: Participação da indústria no PIB | B15: ='PIB setorial'!F23 -> 0.18354761 | C15: ='PIB setorial'!G23 -> 0.18754628 | D15: ='PIB setorial'!H23 -> 0.22819454 | E15: ='PIB setorial'!I23 -> 0.20149945 | F15: =IFERROR((C15-B15)*100,"n.d.") -> 0.39986637 | G15: =IFERROR((D15-C15)*100,"n.d.") -> 4.0648261 | H15: =IFERROR((E15-D15)*100,"n.d.") -> -2.6695091 | I15: Salto em 2022 puxado pela extrativa (petróleo).
A16: Participação dos serviços financeiros no PIB | B16: ='PIB setorial'!F25 -> 0.067875388 | C16: ='PIB setorial'!G25 -> 0.062293117 | D16: ='PIB setorial'!H25 -> 0.060455911 | E16: ='PIB setorial'!I25 -> 0.073027765 | F16: =IFERROR((C16-B16)*100,"n.d.") -> -0.55822708 | G16: =IFERROR((D16-C16)*100,"n.d.") -> -0.18372053 | H16: =IFERROR((E16-D16)*100,"n.d.") -> 1.2571853
A17: Participação dos serviços não financeiros no PIB | B17: ='PIB setorial'!F26 -> 0.56416151 | C17: ='PIB setorial'!G26 -> 0.56838538 | D17: ='PIB setorial'!H26 -> 0.52041643 | E17: ='PIB setorial'!I26 -> 0.52436051 | F17: =IFERROR((C17-B17)*100,"n.d.") -> 0.42238637 | G17: =IFERROR((D17-C17)*100,"n.d.") -> -4.7968946 | H17: =IFERROR((E17-D17)*100,"n.d.") -> 0.39440827 | I17: Perde participação ao longo do período.
A18: Receita líquida do Governo Central (R$ bi) | B18: ='Receitas públicas'!F16 -> 1089.15 | C18: ='Receitas públicas'!G16 -> 1347.277 | D18: ='Receitas públicas'!H16 -> 1856.102 | E18: ='Receitas públicas'!I16 -> 2332.558 | F18: =IFERROR((C18*FATOR_2019)/(B18*FATOR_2016)-1,"n.d.") -> 0.11038656 | G18: =IFERROR((D18*FATOR_2022)/(C18*FATOR_2019)-1,"n.d.") -> 0.13213509 | H18: =IFERROR((E18*FATOR_2025)/(D18*FATOR_2022)-1,"n.d.") -> 0.098966828
A19: Despesa primária do Governo Central (R$ bi) | B19: ='Despesas públicas'!F4 -> 1250.426 | C19: ='Despesas públicas'!G4 -> 1442.34 | D19: ='Despesas públicas'!H4 -> 1809.693 | E19: ='Despesas públicas'!I4 -> 2394.25 | F19: =IFERROR((C19*FATOR_2019)/(B19*FATOR_2016)-1,"n.d.") -> 0.03541547 | G19: =IFERROR((D19*FATOR_2022)/(C19*FATOR_2019)-1,"n.d.") -> 0.031075735 | H19: =IFERROR((E19*FATOR_2025)/(D19*FATOR_2022)-1,"n.d.") -> 0.15696058 | I19: Teto de gastos (2017–2022) × arcabouço (2024–).
A20: Resultado primário do Governo Central (R$ bi) | B20: ='Despesas públicas'!F12 -> -161.276 | C20: ='Despesas públicas'!G12 -> -95.065 | D20: ='Despesas públicas'!H12 -> 46.408 | E20: ='Despesas públicas'!I12 -> -61.69 | F20: =IFERROR((C20*FATOR_2019)/(B20*FATOR_2016)-1,"n.d.") -> -0.47087789 | G20: =IFERROR((D20*FATOR_2022)/(C20*FATOR_2019)-1,"n.d.") -> -1.4011673 | H20: =IFERROR((E20*FATOR_2025)/(D20*FATOR_2022)-1,"n.d.") -> -2.1624543 | I20: Déficit em 2016 e 2019, superávit em 2022, déficit em 2025.
A21: Juros nominais – setor público consolidado (R$ bi) | B21: ='Dívida e juros'!F11 -> 407.024 | C21: ='Dívida e juros'!G11 -> 367.282 | D21: ='Dívida e juros'!H11 -> 586.4 | E21: ='Dívida e juros'!I11 -> 1007.6 | F21: =IFERROR((C21*FATOR_2019)/(B21*FATOR_2016)-1,"n.d.") -> -0.19000074 | G21: =IFERROR((D21*FATOR_2022)/(C21*FATOR_2019)-1,"n.d.") -> 0.31204166 | H21: =IFERROR((E21*FATOR_2025)/(D21*FATOR_2022)-1,"n.d.") -> 0.50261655 | I21: Selic: 14,25% (2016) → 4,5% (2019) → 13,75% (2022) → 15% (2025).
A22: Dívida Bruta do Governo Geral (% PIB, BCB) | B22: ='Dívida e juros'!F7 -> 0.6984 | C22: ='Dívida e juros'!G7 -> 0.7444 | D22: ='Dívida e juros'!H7 -> 0.7168 | E22: ='Dívida e juros'!I7 -> 0.7864 | F22: =IFERROR((C22-B22)*100,"n.d.") -> 4.6 | G22: =IFERROR((D22-C22)*100,"n.d.") -> -2.76 | H22: =IFERROR((E22-D22)*100,"n.d.") -> 6.96
A23: Dívida Líquida do Setor Público (% PIB, BCB) | B23: ='Dívida e juros'!F9 -> 0.4614 | C23: ='Dívida e juros'!G9 -> 0.547 | D23: ='Dívida e juros'!H9 -> 0.5613 | E23: ='Dívida e juros'!I9 -> 0.6524 | F23: =IFERROR((C23-B23)*100,"n.d.") -> 8.56 | G23: =IFERROR((D23-C23)*100,"n.d.") -> 1.43 | H23: =IFERROR((E23-D23)*100,"n.d.") -> 9.11
A24: Investimentos federais pagos – RTN (R$ bi) | B24: ='LOA e execução orçamentária'!F14 -> 48.051 | C24: ='LOA e execução orçamentária'!G14 -> 37.82 | D24: ='LOA e execução orçamentária'!H14 -> 40.639 | E24: ='LOA e execução orçamentária'!I14 -> 69.923 | F24: =IFERROR((C24*FATOR_2019)/(B24*FATOR_2016)-1,"n.d.") -> -0.2934806 | G24: =IFERROR((D24*FATOR_2022)/(C24*FATOR_2019)-1,"n.d.") -> -0.11697135 | H24: =IFERROR((E24*FATOR_2025)/(D24*FATOR_2022)-1,"n.d.") -> 0.50463448 | I24: Mínimo em 2022.
A25: Desembolsos do BNDES (R$ bi) | B25: ='BNDES, Plano Safra e P&D'!F4 -> 88.3 | C25: ='BNDES, Plano Safra e P&D'!G4 -> 55.314 | D25: ='BNDES, Plano Safra e P&D'!H4 -> 97.5 | E25: ='BNDES, Plano Safra e P&D'!I4 -> 169.7 | F25: =IFERROR((C25*FATOR_2019)/(B25*FATOR_2016)-1,"n.d.") -> -0.4376854 | G25: =IFERROR((D25*FATOR_2022)/(C25*FATOR_2019)-1,"n.d.") -> 0.44851454 | H25: =IFERROR((E25*FATOR_2025)/(D25*FATOR_2022)-1,"n.d.") -> 0.52205798
A26: Plano Safra (R$ bi, ciclo) | B26: ='BNDES, Plano Safra e P&D'!F7 -> 232.88 | C26: ='BNDES, Plano Safra e P&D'!G7 -> 225.59 | D26: ='BNDES, Plano Safra e P&D'!H7 -> 340.88 | E26: ='BNDES, Plano Safra e P&D'!I7 -> 605.2 | F26: =IFERROR((C26*FATOR_2019)/(B26*FATOR_2016)-1,"n.d.") -> -0.13045383 | G26: =IFERROR((D26*FATOR_2022)/(C26*FATOR_2019)-1,"n.d.") -> 0.24175233 | H26: =IFERROR((E26*FATOR_2025)/(D26*FATOR_2022)-1,"n.d.") -> 0.55257064 | I26: Ciclos agrícolas, não anos civis.
A27: Saldo de empregos formais (pessoas) | B27: =Emprego!F7 -> -1321994 | C27: =Emprego!G7 -> 644079 | D27: =Emprego!H7 -> 2037982 | E27: =Emprego!I7 -> 1279498 | F27: =IFERROR(C27/B27-1,"n.d.") -> -1.4872027 | G27: =IFERROR(D27/C27-1,"n.d.") -> 2.1641802 | H27: =IFERROR(E27/D27-1,"n.d.") -> -0.37217404 | I27: Quebra Caged/Novo Caged em 2020.
A28: Bolsa Família / Auxílio Brasil pago (R$ bi) | B28: ='Políticas afirmativas e apoio'!F7 -> 27.49159 | C28: ='Políticas afirmativas e apoio'!G7 -> 32.48162 | D28: ='Políticas afirmativas e apoio'!H7 -> 113.02915 | E28: ='Políticas afirmativas e apoio'!I7 -> 171.82365 | F28: =IFERROR((C28*FATOR_2019)/(B28*FATOR_2016)-1,"n.d.") -> 0.060578503 | G28: =IFERROR((D28*FATOR_2022)/(C28*FATOR_2019)-1,"n.d.") -> 1.8596053 | H28: =IFERROR((E28*FATOR_2025)/(D28*FATOR_2022)-1,"n.d.") -> 0.32937176 | I28: Auxílio Brasil em 2022; novo Bolsa Família em 2025.
A29: Taxa média de desocupação | B29: =Emprego!F8 -> 0.115 | C29: =Emprego!G8 -> 0.119 | D29: =Emprego!H8 -> 0.093 | E29: =Emprego!I8 -> 0.056 | F29: =IFERROR((C29-B29)*100,"n.d.") -> 0.4 | G29: =IFERROR((D29-C29)*100,"n.d.") -> -2.6 | H29: =IFERROR((E29-D29)*100,"n.d.") -> -3.7
A30: Exportações (US$ bi) | B30: ='Comércio exterior'!F4 -> 179.52613 | C30: ='Comércio exterior'!G4 -> 221.12681 | D30: ='Comércio exterior'!H4 -> 334.13604 | E30: ='Comércio exterior'!I4 -> 348.27846 | F30: =IFERROR(C30/B30-1,"n.d.") -> 0.23172492 | G30: =IFERROR(D30/C30-1,"n.d.") -> 0.51106074 | H30: =IFERROR(E30/D30-1,"n.d.") -> 0.042325349
A31: Saldo comercial (US$ bi) | B31: ='Comércio exterior'!F6 -> 40.204772 | C31: ='Comércio exterior'!G6 -> 35.19884 | D31: ='Comércio exterior'!H6 -> 61.525351 | E31: ='Comércio exterior'!I6 -> 68.070029 | F31: =IFERROR(C31/B31-1,"n.d.") -> -0.12451088 | G31: =IFERROR(D31/C31-1,"n.d.") -> 0.7479369 | H31: =IFERROR(E31/D31-1,"n.d.") -> 0.10637367
A32: Para % e taxas, as colunas de variação trazem diferença em p.p.; para US$ e pessoas, variação nominal.
A34: Legenda de cores (classificação do dado)
A35: OFICIAL | B35: Dado oficial publicado (IBGE, BCB, Tesouro, RFB, MTE, MDIC, BNDES, MAPA/MDA, Siconfi, Portal da Transparência, Casa Civil)
A36: ESTIMADO | B36: Estimativa/projeção oficial ou cálculo próprio a partir de dados oficiais (soma, diferença, % aplicado ao PIB)
A37: APROXIMAÇÃO | B37: Aproximação: período, conceito ou recorte diferente do solicitado (explicado na observação)
A38: IMPRENSA/SETORIAL | B38: Cifra obtida via imprensa ou entidade setorial (Abdib, Inesc etc.), sem acesso direto à base oficial
A39: NÃO LOCALIZADO | B39: Não localizado após busca — tentativas registradas na aba 'Fontes e metodologia'
A41: Síntese das principais diferenças 2016 × 2019 × 2022 × 2025
A42: ■ 1. Economia e estrutura produtiva
A43: Em reais de dez/2025 (IPCA), o PIB foi de R$ 9,72 tri (2016) para R$ 10,28 tri (2019), R$ 11,53 tri (2022) e R$ 12,74 tri (2025). A agropecuária subiu de 4,9% do PIB em 2016 para 6,1% em 2025, com queda em 2019 (4,2%). A indústria teve pico em 2022 (22,8%), puxado pela extrativa (petróleo caro), e voltou a 20,2% em 2025. Os serviços não financeiros caíram de 56,4% para 52,4% do PIB; o setor financeiro recuou até 2022 (6,0%) e saltou em 2025 (7,3%). A FBCF foi de 15,5% do PIB (2016) a 17,8% (2022) e 16,8% (2025).
A44: ■ 2. Contas do Governo Central
A45: A receita líquida subiu de 17,4% do PIB (2016) para cerca de 18,3% a partir de 2019. A despesa primária caiu de 19,9% (2016) para 18,0% (2022), sob o teto de gastos, e voltou a 18,8% em 2025. O resultado primário passou de déficit de R$ 161 bi (2016, pior da série) e R$ 95 bi (2019) para superávit de R$ 46 bi em 2022 (54 bi na divulgação original), impulsionado por royalties, dividendos e receitas extraordinárias, e para déficit de R$ 62 bi em 2025. Os gastos tributários ficaram entre 4,2% e 4,6% do PIB nos quatro anos; os benefícios financeiros e creditícios caíram de 1,8% (2016) para 0,5% (2019) e voltaram a 1,2–1,4%.
A46: ■ 3. Dívida e juros
A47: Os juros do setor público foram de 6,5% do PIB (2016, Selic 14,25%) para 5,0% (2019, Selic baixa), 5,8% (2022) e 7,9% (2025, Selic 15%). A dívida bruta foi de 69,8% (2016) para 74,4% (2019), recuou a 71,7% (2022) e atingiu 78,6% (2025). A dívida líquida subiu sem interrupção: 46,1% → 54,7% → 56,1% → 65,2% do PIB. A DPF quase triplicou em termos nominais (R$ 3,1 tri → R$ 8,6 tri).
A48: ■ 4. Orçamento: prioridades e execução
A49: Em reais de 2025, saúde empenhada ficou praticamente estável entre 2016 e 2022 (R$ 165–175 bi) e saltou para R$ 239 bi em 2025; educação caiu de R$ 147 bi (2016) para R$ 135 bi (2022) e subiu para R$ 176 bi (2025). Segurança pública cresceu de forma gradual (R$ 13,7 bi → R$ 16,6 bi). O investimento federal pago (RTN) caiu de R$ 74 bi (2016, em R$ de 2025) para R$ 46 bi (2022) e se recuperou para R$ 70 bi em 2025, ainda abaixo de 2016. O programa de igualdade racial teve R$ 20 mi empenhados em 2016, R$ 12 mi em 2019, nenhum programa específico em 2022 e R$ 77 mi em 2025.
A50: ■ 5. Crédito público, emprego e setor externo
A51: Os desembolsos do BNDES, em reais de 2025, caíram de R$ 137 bi (2016) para R$ 77 bi (2019) e subiram para R$ 111 bi (2022) e R$ 170 bi (2025). O Plano Safra anunciado (reais de 2025) foi de R$ 361 bi (2016/17) a R$ 314 bi (2019/20), R$ 390 bi (2022/23) e R$ 605 bi (2025/26). O emprego formal passou de perda de 1,32 milhão de vagas (2016) a saldos de 644 mil (2019), 2,04 milhões (2022) e 1,28 milhão (2025), com quebra metodológica em 2020; a desocupação foi de 11,5% e 11,9% para 9,3% e 5,6%. As exportações quase dobraram (US$ 180 bi → US$ 348 bi), com salto em 2022; o saldo comercial foi de US$ 40 bi para US$ 68 bi; o IDP oscilou entre US$ 69 bi e US$ 78 bi.
A52: ■ 5-A. Políticas afirmativas e de apoio social (aba nova)
... A55: 2016 é o fundo da recessão (déficit recorde, desemprego alto, juros altos); 2019 mostra ajuste lento sob o teto de gastos, com investimento e crédito público no mínimo; 2022 combina superávit primário e forte arrecadação ligados a commodities, com investimento público muito baixo; 2025 traz expansão do gasto social, do BNDES e do Plano Safra, emprego recorde e a maior carga de juros e dívida do período. Ver quebras de série (Caged 2020), estimativas (estoque de emprego 2016, aprovações BNDES 2022, gastos tributários 2025) e itens não localizados na aba 'Fontes e metodologia'.

Sheet Indicadores consolidados
A1: Indicadores consolidados – Brasil 2016 × 2019 × 2022 × 2025
A2: Valores vinculados às abas temáticas (texto verde). R$ bilhões correntes salvo indicação; correção pelo IPCA até dez/2025.
A3: Código | B3: Indicador | C3: Conceito | D3: Âmbito | E3: Unidade | F3: Brasil 2016 | G3: Brasil 2019 | H3: Brasil 2022 | I3: Brasil 2025 | J3: 2016 corrigido para preços de 2025 | K3: 2019 corrigido para preços de 2025 | L3: 2022 corrigido para preços de 2025 | M3: Variação nominal 2019→2025 | N3: Variação real 2016→2025 | O3: Variação real 2019→2025 | P3: Variação real 2022→2025 | Q3: 2016 como % do PIB | R3: 2019 como % do PIB | S3: 2022 como % do PIB | T3: 2025 como % do PIB | U3: Fonte 2016 | V3: Fonte 2019 | W3: Fonte 2022 | X3: Fonte 2025 | Y3: Data de acesso | Z3: Observações metodológicas
A4: 1 | B4: PIB total do Brasil | C4: PIB a preços de mercado, valores correntes (fluxo anual) | D4: Brasil | E4: R$ bi | F4: ='PIB setorial'!F4 -> 6269.327 | G4: ='PIB setorial'!G4 -> 7389.131 | H4: ='PIB setorial'!H4 -> 10079.676 | I4: ='PIB setorial'!I4 -> 12738.566 | J4: =IFERROR(F4*FATOR_2016,"n.d.") -> 9718.7105 | K4: =IFERROR(G4*FATOR_2019,"n.d.") -> 10282.201 | L4: =IFERROR(H4*FATOR_2022,"n.d.") -> 11526.371 | M4: =IFERROR(I4/G4-1,"n.d.") -> 0.72395996 | N4: =IFERROR(I4/J4-1,"n.d.") -> 0.31072594 | O4: =IFERROR(I4/K4-1,"n.d.") -> 0.23889487 | P4: =IFERROR(I4/L4-1,"n.d.") -> 0.10516708 | Q4: =IFERROR(F4/PIB_2016,"n.d.") -> 1 | R4: =IFERROR(G4/PIB_2019,"n.d.") -> 1 | S4: =IFERROR(H4/PIB_2022,"n.d.") -> 1 | T4: =IFERROR(I4/PIB_2025,"n.d.") -> 1 | U4: IBGE/SIDRA 1846 (S01) | V4: IBGE/SIDRA 1846 (S01) | W4: IBGE/SIDRA 1846 (S01) | X4: IBGE/SIDRA 1846 (S01) | Y4: 22/09/2026 | Z4: [OFICIAL] Soma dos 4 trimestres. Divulgação original de 2025: R$ 12,7 tri (S02); Tesouro usa R$ 12.733,6 bi (série anterior).
A5: 2 | B5: PIB da agropecuária | C5: VAB – Agropecuária total | D5: Brasil | E5: R$ bi | F5: ='PIB setorial'!F7 -> 306.654 | G5: ='PIB setorial'!G7 -> 310.714 | H5: ='PIB setorial'!H7 -> 581.343 | I5: ='PIB setorial'!I7 -> 775.297 | J5: =IFERROR(F5*FATOR_2016,"n.d.") -> 475.37502 | K5: =IFERROR(G5*FATOR_2019,"n.d.") -> 432.368 | L5: =IFERROR(H5*FATOR_2022,"n.d.") -> 664.78081 | M5: =IFERROR(I5/G5-1,"n.d.") -> 1.495211 | N5: =IFERROR(I5/J5-1,"n.d.") -> 0.63091657 | O5: =IFERROR(I5/K5-1,"n.d.") -> 0.79314149 | P5: =IFERROR(I5/L5-1,"n.d.") -> 0.16624455 | Q5: =IFERROR(F5/PIB_2016,"n.d.") -> 0.048913384 | R5: =IFERROR(G5/PIB_2019,"n.d.") -> 0.042050141 | S5: =IFERROR(H5/PIB_2022,"n.d.") -> 0.05767477 | T5: =IFERROR(I5/PIB_2025,"n.d.") -> 0.060862188 | U5: IBGE/SIDRA 1846 (S01) | V5: IBGE/SIDRA 1846 (S01) | W5: IBGE/SIDRA 1846 (S01) | X5: IBGE/SIDRA 1846 (S01) | Y5: 22/09/2026 | Z5: [OFICIAL] —
A6: 3 | B6: PIB da indústria | C6: VAB – Indústria total | D6: Brasil | E6: R$ bi | F6: ='PIB setorial'!F8 -> 1150.72 | G6: ='PIB setorial'!G8 -> 1385.804 | H6: ='PIB setorial'!H8 -> 2300.127 | I6: ='PIB setorial'!I8 -> 2566.814 | J6: =IFERROR(F6*FATOR_2016,"n.d.") -> 1783.8461 | K6: =IFERROR(G6*FATOR_2019,"n.d.") -> 1928.3885 | L6: =IFERROR(H6*FATOR_2022,"n.d.") -> 2630.2549 | M6: =IFERROR(I6/G6-1,"n.d.") -> 0.85222008 | N6: =IFERROR(I6/J6-1,"n.d.") -> 0.43892121 | O6: =IFERROR(I6/K6-1,"n.d.") -> 0.33106685 | P6: =IFERROR(I6/L6-1,"n.d.") -> -0.024119693 | Q6: =IFERROR(F6/PIB_2016,"n.d.") -> 0.18354761 | R6: =IFERROR(G6/PIB_2019,"n.d.") -> 0.18754628 | S6: =IFERROR(H6/PIB_2022,"n.d.") -> 0.22819454 | T6: =IFERROR(I6/PIB_2025,"n.d.") -> 0.20149945 | U6: IBGE/SIDRA 1846 (S01) | V6: IBGE/SIDRA 1846 (S01) | W6: IBGE/SIDRA 1846 (S01) | X6: IBGE/SIDRA 1846 (S01) | Y6: 22/09/2026 | Z6: [OFICIAL] Extrativa + transformação + eletricidade/gás/água/esgoto + construção.
A7: 4 | B7: PIB dos serviços | C7: VAB – Serviços total | D7: Brasil | E7: R$ bi | F7: ='PIB setorial'!F13 -> 3962.446 | G7: ='PIB setorial'!G13 -> 4660.166 | H7: ='PIB setorial'!H13 -> 5855.005 | I7: ='PIB setorial'!I13 -> 7609.87 | J7: =IFERROR(F7*FATOR_2016,"n.d.") -> 6142.5837 | K7: =IFERROR(G7*FATOR_2019,"n.d.") -> 6484.763 | L7: =IFERROR(H7*FATOR_2022,"n.d.") -> 6695.3502 | M7: =IFERROR(I7/G7-1,"n.d.") -> 0.63296114 | N7: =IFERROR(I7/J7-1,"n.d.") -> 0.2388712 | O7: =IFERROR(I7/K7-1,"n.d.") -> 0.1735001 | P7: =IFERROR(I7/L7-1,"n.d.") -> 0.13659028 | Q7: =IFERROR(F7/PIB_2016,"n.d.") -> 0.6320369 | R7: =IFERROR(G7/PIB_2019,"n.d.") -> 0.63067849 | S7: =IFERROR(H7/PIB_2022,"n.d.") -> 0.58087234 | T7: =IFERROR(I7/PIB_2025,"n.d.") -> 0.59738828 | U7: IBGE/SIDRA 1846 (S01) | V7: IBGE/SIDRA 1846 (S01) | W7: IBGE/SIDRA 1846 (S01) | X7: IBGE/SIDRA 1846 (S01) | Y7: 22/09/2026 | Z7: [OFICIAL] —
A8: 5 | B8: PIB das atividades financeiras, de seguros e serviços relacionados | C8: VAB | D8: Brasil | E8: R$ bi | F8: ='PIB setorial'!F17 -> 425.533 | G8: ='PIB setorial'!G17 -> 460.292 | H8: ='PIB setorial'!H17 -> 609.376 | I8: ='PIB setorial'!I17 -> 930.269 | J8: =IFERROR(F8*FATOR_2016,"n.d.") -> 659.66124 | K8: =IFERROR(G8*FATOR_2019,"n.d.") -> 640.51034 | L8: =IFERROR(H8*FATOR_2022,"n.d.") -> 696.83728 | M8: =IFERROR(I8/G8-1,"n.d.") -> 1.021041 | N8: =IFERROR(I8/J8-1,"n.d.") -> 0.4102223 | O8: =IFERROR(I8/K8-1,"n.d.") -> 0.45238716 | P8: =IFERROR(I8/L8-1,"n.d.") -> 0.33498742 | Q8: =IFERROR(F8/PIB_2016,"n.d.") -> 0.067875388 | R8: =IFERROR(G8/PIB_2019,"n.d.") -> 0.062293117 | S8: =IFERROR(H8/PIB_2022,"n.d.") -> 0.060455911 | T8: =IFERROR(I8/PIB_2025,"n.d.") -> 0.073027765 | U8: IBGE/SIDRA 1846 (S01) | V8: IBGE/SIDRA 1846 (S01) | W8: IBGE/SIDRA 1846 (S01) | X8: IBGE/SIDRA 1846 (S01) | Y8: 22/09/2026 | Z8: [OFICIAL] Separadas dos demais serviços, conforme solicitado.
A9: 6 | B9: PIB dos serviços não financeiros | C9: Serviços totais − atividades financeiras (cálculo) | D9: Brasil | E9: R$ bi | F9: ='PIB setorial'!F21 -> 3536.913 | G9: ='PIB setorial'!G21 -> 4199.874 | H9: ='PIB setorial'!H21 -> 5245.629 | I9: ='PIB setorial'!I21 -> 6679.601 | J9: =IFERROR(F9*FATOR_2016,"n.d.") -> 5482.9224 | K9: =IFERROR(G9*FATOR_2019,"n.d.") -> 5844.2527 | L9: =IFERROR(H9*FATOR_2022,"n.d.") -> 5998.513 | M9: =IFERROR(I9/G9-1,"n.d.") -> 0.5904289 | N9: =IFERROR(I9/J9-1,"n.d.") -> 0.21825561 | O9: =IFERROR(I9/K9-1,"n.d.") -> 0.14293502 | P9: =IFERROR(I9/L9-1,"n.d.") -> 0.11354282 | Q9: =IFERROR(F9/PIB_2016,"n.d.") -> 0.56416151 | R9: =IFERROR(G9/PIB_2019,"n.d.") -> 0.56838538 | S9: =IFERROR(H9/PIB_2022,"n.d.") -> 0.52041643 | T9: =IFERROR(I9/PIB_2025,"n.d.") -> 0.52436051 | U9: Cálculo sobre S01 | V9: Cálculo sobre S01 | W9: Cálculo sobre S01 | X9: Cálculo sobre S01 | Y9: 22/09/2026 | Z9: [ESTIMADO] Calculado na planilha: VAB serviços − VAB financeiro (mesma fonte e conceito).
A10: 7a | B10: Participação da agropecuária no PIB | C10: VAB da atividade ÷ PIB | D10: Brasil | E10: % | F10: ='PIB setorial'!F22 -> 0.048913384 | G10: ='PIB setorial'!G22 -> 0.042050141 | H10: ='PIB setorial'!H22 -> 0.05767477 | I10: ='PIB setorial'!I22 -> 0.060862188 | J10: n.a. | K10: n.a. | L10: n.a. | M10: =IFERROR((I10-G10)*100,"n.d.") -> 1.8812047 | N10: n.a. | O10: n.a. | P10: n.a. | Q10: n.a. | R10: n.a. | S10: n.a. | T10: n.a. | U10: Cálculo sobre S01 | V10: Cálculo sobre S01 | W10: Cálculo sobre S01 | X10: Cálculo sobre S01 | Y10: 22/09/2026 | Z10: ="[ESTIMADO] "&'PIB setorial'!AB22 -> [ESTIMADO] Participação no VAB (critério IBGE): 2016: 5,66%; 2019: 4,89%; 2022: 6,65%; 2025: 7,08%.
A11: 7b | B11: Participação da indústria no PIB | C11: VAB da atividade ÷ PIB | D11: Brasil | E11: % | F11: ='PIB setorial'!F23 -> 0.18354761 | G11: ='PIB setorial'!G23 -> 0.18754628 | H11: ='PIB setorial'!H23 -> 0.22819454 | I11: ='PIB setorial'!I23 -> 0.20149945 | J11: n.a. | K11: n.a. | L11: n.a. | M11: =IFERROR((I11-G11)*100,"n.d.") -> 1.3953171 | N11: n.a. | O11: n.a. | P11: n.a. | Q11: n.a. | R11: n.a. | S11: n.a. | T11: n.a. | U11: Cálculo sobre S01 | V11: Cálculo sobre S01 | W11: Cálculo sobre S01 | X11: Cálculo sobre S01 | Y11: 22/09/2026 | Z11: ="[ESTIMADO] "&'PIB setorial'!AB23 -> [ESTIMADO] Participação no VAB (critério IBGE): 2016: 21,23%; 2019: 21,80%; 2022: 26,33%; 2025: 23,44%.
A12: 7c | B12: Participação dos serviços financeiros no PIB | C12: VAB da atividade ÷ PIB | D12: Brasil | E12: % | F12: ='PIB setorial'!F25 -> 0.067875388 | G12: ='PIB setorial'!G25 -> 0.062293117 | H12: ='PIB setorial'!H25 -> 0.060455911 | I12: ='PIB setorial'!I25 -> 0.073027765 | J12: n.a. | K12: n.a. | L12: n.a. | M12: =IFERROR((I12-G12)*100,"n.d.") -> 1.0734648 | N12: n.a. | O12: n.a. | P12: n.a. | Q12: n.a. | R12: n.a. | S12: n.a. | T12: n.a. | U12: Cálculo sobre S01 | V12: Cálculo sobre S01 | W12: Cálculo sobre S01 | X12: Cálculo sobre S01 | Y12: 22/09/2026 | Z12: ="[ESTIMADO] "&'PIB setorial'!AB25 -> [ESTIMADO] Participação no VAB (critério IBGE): 2016: 7,85%; 2019: 7,24%; 2022: 6,98%; 2025: 8,49%.
A13: 7d | B13: Participação dos serviços não financeiros no PIB | C13: VAB da atividade ÷ PIB | D13: Brasil | E13: % | F13: ='PIB setorial'!F26 -> 0.56416151 | G13: ='PIB setorial'!G26 -> 0.56838538 | H13: ='PIB setorial'!H26 -> 0.52041643 | I13: ='PIB setorial'!I26 -> 0.52436051 | J13: n.a. | K13: n.a. | L13: n.a. | M13: =IFERROR((I13-G13)*100,"n.d.") -> -4.4024863 | N13: n.a. | O13: n.a. | P13: n.a. | Q13: n.a. | R13: n.a. | S13: n.a. | T13: n.a. | U13: Cálculo sobre S01 | V13: Cálculo sobre S01 | W13: Cálculo sobre S01 | X13: Cálculo sobre S01 | Y13: 22/09/2026 | Z13: ="[ESTIMADO] "&'PIB setorial'!AB26 -> [ESTIMADO] Participação no VAB (critério IBGE): 2016: 65,26%; 2019: 66,07%; 2022: 60,04%; 2025: 60,99%.
A14: 8 | B14: Arrecadação da União | C14: Arrecadação total das receitas federais (RFB + outros órgãos), fluxo anual | D14: União | E14: R$ bi | F14: ='Receitas públicas'!F4 -> 1289 | G14: ='Receitas públicas'!G4 -> 1537 | H14: ='Receitas públicas'!H4 -> 2218 | I14: ='Receitas públicas'!I4 -> 2886 | J14: =IFERROR(F14*FATOR_2016,"n.d.") -> 1998.2078 | K14: =IFERROR(G14*FATOR_2019,"n.d.") -> 2138.7823 | L14: =IFERROR(H14*FATOR_2022,"n.d.") -> 2536.3406 | M14: =IFERROR(I14/G14-1,"n.d.") -> 0.8776838 | N14: =IFERROR(I14/J14-1,"n.d.") -> 0.44429426 | O14: =IFERROR(I14/K14-1,"n.d.") -> 0.34936592 | P14: =IFERROR(I14/L14-1,"n.d.") -> 0.1378598 | Q14: =IFERROR(F14/PIB_2016,"n.d.") -> 0.20560421 | R14: =IFERROR(G14/PIB_2019,"n.d.") -> 0.20800822 | S14: =IFERROR(H14/PIB_2022,"n.d.") -> 0.22004676 | T14: =IFERROR(I14/PIB_2025,"n.d.") -> 0.22655611 | U14: Receita Federal (S29) | V14: Receita Federal (S12) | W14: Receita Federal (S29) | X14: Receita Federal (S12) | Y14: 22/09/2026 | Z14: [OFICIAL] Valores publicados como R$ 1,537 tri (2019) e R$ 2,886 tri (2025), sem mais casas decimais. Conceito distinto da 'receita total' do RTN (caixa do Tesouro). [2016/2022] 2016: R$ 1,289 tri; 2022: R$ 2,218 tri (publicados sem mais casas).
A15: 9 | B15: Gastos da União | C15: Despesas pagas no exercício, exceto intra-orçamentárias; inclui juros e amortização | D15: União | E15: R$ bi | F15: ='Despesas públicas'!F16 -> 1875.18 | G15: ='Despesas públicas'!G16 -> 2198.25 | H15: ='Despesas públicas'!H16 -> 2603.83 | I15: ='Despesas públicas'!I16 -> 3606.51 | J15: =IFERROR(F15*FATOR_2016,"n.d.") -> 2906.904 | K15: =IFERROR(G15*FATOR_2019,"n.d.") -> 3058.9319 | L15: =IFERROR(H15*FATOR_2022,"n.d.") -> 2977.5472 | M15: =IFERROR(I15/G15-1,"n.d.") -> 0.64062777 | N15: =IFERROR(I15/J15-1,"n.d.") -> 0.24067049 | O15: =IFERROR(I15/K15-1,"n.d.") -> 0.17900959 | P15: =IFERROR(I15/L15-1,"n.d.") -> 0.2112352 | Q15: =IFERROR(F15/PIB_2016,"n.d.") -> 0.29910388 | R15: =IFERROR(G15/PIB_2019,"n.d.") -> 0.29749777 | S15: =IFERROR(H15/PIB_2022,"n.d.") -> 0.25832477 | T15: =IFERROR(I15/PIB_2025,"n.d.") -> 0.28311742 | U15: RREO Anexo 01 (S05) | V15: RREO Anexo 01 (S05) | W15: RREO Anexo 01 (S05) | X15: S05 | Y15: 22/09/2026 | Z15: [OFICIAL] Não inclui restos a pagar pagos nem refinanciamento da dívida.
A16: 10 | B16: Receita primária do Governo Central | C16: Receita total (Tesouro + Previdência + BCB), caixa | D16: Governo Central | E16: R$ bi | F16: ='Receitas públicas'!F14 -> 1315.985 | G16: ='Receitas públicas'!G14 -> 1635.608 | H16: ='Receitas públicas'!H14 -> 2313.305 | I16: ='Receitas públicas'!I14 -> 2902.275 | J16: =IFERROR(F16*FATOR_2016,"n.d.") -> 2040.0399 | K16: =IFERROR(G16*FATOR_2019,"n.d.") -> 2275.9984 | L16: =IFERROR(H16*FATOR_2022,"n.d.") -> 2645.3243 | M16: =IFERROR(I16/G16-1,"n.d.") -> 0.77443189 | N16: =IFERROR(I16/J16-1,"n.d.") -> 0.42265599 | O16: =IFERROR(I16/K16-1,"n.d.") -> 0.27516567 | P16: =IFERROR(I16/L16-1,"n.d.") -> 0.097133902 | Q16: =IFERROR(F16/PIB_2016,"n.d.") -> 0.2099085 | R16: =IFERROR(G16/PIB_2019,"n.d.") -> 0.22135323 | S16: =IFERROR(H16/PIB_2022,"n.d.") -> 0.22950192 | T16: =IFERROR(I16/PIB_2025,"n.d.") -> 0.22783373 | U16: STN – RTN tab. 2.1 (S04) | V16: S04 | W16: STN – RTN tab. 2.1 (S04) | X16: S04 | Y16: 22/09/2026 | Z16: [OFICIAL] —
A17: 10b | B17: Receita líquida do Governo Central | C17: Receita total − transferências por repartição | D17: Governo Central | E17: R$ bi | F17: ='Receitas públicas'!F16 -> 1089.15 | G17: ='Receitas públicas'!G16 -> 1347.277 | H17: ='Receitas públicas'!H16 -> 1856.102 | I17: ='Receitas públicas'!I16 -> 2332.558 | J17: =IFERROR(F17*FATOR_2016,"n.d.") -> 1688.4003 | K17: =IFERROR(G17*FATOR_2019,"n.d.") -> 1874.777 | L17: =IFERROR(H17*FATOR_2022,"n.d.") -> 2122.5008 | M17: =IFERROR(I17/G17-1,"n.d.") -> 0.73131286 | N17: =IFERROR(I17/J17-1,"n.d.") -> 0.38151954 | O17: =IFERROR(I17/K17-1,"n.d.") -> 0.24417891 | P17: =IFERROR(I17/L17-1,"n.d.") -> 0.098966828 | Q17: =IFERROR(F17/PIB_2016,"n.d.") -> 0.17372678 | R17: =IFERROR(G17/PIB_2019,"n.d.") -> 0.18233227 | S17: =IFERROR(H17/PIB_2022,"n.d.") -> 0.18414302 | T17: =IFERROR(I17/PIB_2025,"n.d.") -> 0.18310994 | U17: STN – RTN tab. 2.1 (S04) | V17: S04 | W17: STN – RTN tab. 2.1 (S04) | X17: S04 | Y17: 22/09/2026 | Z17: [OFICIAL] —
A18: 11 | B18: Despesa primária do Governo Central | C18: Despesa total primária (RTN), caixa | D18: Governo Central | E18: R$ bi | F18: ='Despesas públicas'!F4 -> 1250.426 | G18: ='Despesas públicas'!G4 -> 1442.34 | H18: ='Despesas públicas'!H4 -> 1809.693 | I18: ='Despesas públicas'!I4 -> 2394.25 | J18: =IFERROR(F18*FATOR_2016,"n.d.") -> 1938.4103 | K18: =IFERROR(G18*FATOR_2019,"n.d.") -> 2007.0601 | L18: =IFERROR(H18*FATOR_2022,"n.d.") -> 2069.4309 | M18: =IFERROR(I18/G18-1,"n.d.") -> 0.65997615 | N18: =IFERROR(I18/J18-1,"n.d.") -> 0.23516159 | O18: =IFERROR(I18/K18-1,"n.d.") -> 0.19291398 | P18: =IFERROR(I18/L18-1,"n.d.") -> 0.15696058 | Q18: =IFERROR(F18/PIB_2016,"n.d.") -> 0.19945139 | R18: =IFERROR(G18/PIB_2019,"n.d.") -> 0.19519751 | S18: =IFERROR(H18/PIB_2022,"n.d.") -> 0.17953881 | T18: =IFERROR(I18/PIB_2025,"n.d.") -> 0.18795287 | U18: STN – RTN tab. 2.1 (S04) | V18: STN – RTN tab. 2.1 (S04) | W18: STN – RTN tab. 2.1 (S04) | X18: S04 | Y18: 22/09/2026 | Z18: [OFICIAL] —
A19: 12 | B19: Despesa total do Governo Central | C19: Soma: despesa primária (caixa, STN) + juros nominais (competência, BCB) | D19: Governo Central | E19: R$ bi | F19: ='Despesas públicas'!F14 -> 1568.788 | G19: ='Despesas públicas'!G14 -> 1752.46 | H19: ='Despesas públicas'!H14 -> 2312.927 | I19: ='Despesas públicas'!I14 -> 3286.13 | J19: =IFERROR(F19*FATOR_2016,"n.d.") -> 2431.9351 | K19: =IFERROR(G19*FATOR_2019,"n.d.") -> 2438.6015 | L19: =IFERROR(H19*FATOR_2022,"n.d.") -> 2644.8921 | M19: =IFERROR(I19/G19-1,"n.d.") -> 0.87515264 | N19: =IFERROR(I19/J19-1,"n.d.") -> 0.35124082 | O19: =IFERROR(I19/K19-1,"n.d.") -> 0.34754695 | P19: =IFERROR(I19/L19-1,"n.d.") -> 0.24244389 | Q19: =IFERROR(F19/PIB_2016,"n.d.") -> 0.25023228 | R19: =IFERROR(G19/PIB_2019,"n.d.") -> 0.23716727 | S19: =IFERROR(H19/PIB_2022,"n.d.") -> 0.22946442 | T19: =IFERROR(I19/PIB_2025,"n.d.") -> 0.25796703 | U19: Cálculo S04 | V19: Cálculo S04 | W19: Cálculo S04 | X19: Cálculo S04 | Y19: 22/09/2026 | Z19: [APROXIMAÇÃO] Indicador sem publicação oficial única. Soma critérios diferentes (caixa × competência); usar apenas como ordem de grandeza. Ver também o déficit nominal oficial na linha seguinte.
A20: 13 | B20: Dívida Pública Federal | C20: Estoque em 31/dez (interna + externa) | D20: União | E20: R$ bi | F20: ='Dívida e juros'!F4 -> 3113 | G20: ='Dívida e juros'!G4 -> 4248 | H20: ='Dívida e juros'!H4 -> 5951 | I20: ='Dívida e juros'!I4 -> 8635 | J20: =IFERROR(F20*FATOR_2016,"n.d.") -> 4825.7725 | K20: =IFERROR(G20*FATOR_2019,"n.d.") -> 5911.2215 | L20: =IFERROR(H20*FATOR_2022,"n.d.") -> 6805.123 | M20: =IFERROR(I20/G20-1,"n.d.") -> 1.0327213 | N20: =IFERROR(I20/J20-1,"n.d.") -> 0.78935082 | O20: =IFERROR(I20/K20-1,"n.d.") -> 0.460781 | P20: =IFERROR(I20/L20-1,"n.d.") -> 0.26889698 | Q20: =IFERROR(F20/PIB_2016,"n.d.") -> 0.49654453 | R20: =IFERROR(G20/PIB_2019,"n.d.") -> 0.57489846 | S20: =IFERROR(H20/PIB_2022,"n.d.") -> 0.59039596 | T20: =IFERROR(I20/PIB_2025,"n.d.") -> 0.6778628 | U20: Tesouro – RMD (S30) | V20: Tesouro – RMD (S11) | W20: Tesouro – RMD (S30) | X20: S11 | Y20: 22/09/2026 | Z20: [OFICIAL] Estoque; não somar com fluxos.
A21: 14 | B21: Dívida Bruta do Governo Geral | C21: Estoque em dez (União + estados + municípios; exclui BCB e estatais) | D21: Governo Geral | E21: R$ bi | F21: ='Dívida e juros'!F6 -> 4378.4864 | G21: ='Dívida e juros'!G6 -> 5500.1042 | H21: ='Dívida e juros'!H6 -> 7224.8822 | I21: ='Dívida e juros'!I6 -> 10017.919 | J21: =IFERROR(F21*FATOR_2016,"n.d.") -> 6787.5295 | K21: =IFERROR(G21*FATOR_2019,"n.d.") -> 7653.5625 | L21: =IFERROR(H21*FATOR_2022,"n.d.") -> 8261.8404 | M21: =IFERROR(I21/G21-1,"n.d.") -> 0.82140535 | N21: =IFERROR(I21/J21-1,"n.d.") -> 0.47593011 | O21: =IFERROR(I21/K21-1,"n.d.") -> 0.30892236 | P21: =IFERROR(I21/L21-1,"n.d.") -> 0.21255297 | Q21: =IFERROR(F21/PIB_2016,"n.d.") -> 0.69839815 | R21: =IFERROR(G21/PIB_2019,"n.d.") -> 0.74435061 | S21: =IFERROR(H21/PIB_2022,"n.d.") -> 0.71677723 | T21: =IFERROR(I21/PIB_2025,"n.d.") -> 0.7864244 | U21: BCB SGS (S08) | V21: BCB SGS 13761 (S08) | W21: BCB SGS (S08) | X21: S08 | Y21: 22/09/2026 | Z21: [OFICIAL] DBGG ≠ DPF: inclui dívida de estados/municípios e operações compromissadas do BCB; exclui títulos na carteira do BCB.
A22: 15 | B22: Dívida Líquida do Setor Público | C22: Estoque em dez (setor público consolidado, inclui BCB e estatais não financeiras) | D22: Setor público consolidado | E22: R$ bi | F22: ='Dívida e juros'!F8 -> 2892.9135 | G22: ='Dívida e juros'!G8 -> 4041.7688 | H22: ='Dívida e juros'!H8 -> 5658.0169 | I22: ='Dívida e juros'!I8 -> 8311.0858 | J22: =IFERROR(F22*FATOR_2016,"n.d.") -> 4484.5944 | K22: =IFERROR(G22*FATOR_2019,"n.d.") -> 5624.2444 | L22: =IFERROR(H22*FATOR_2022,"n.d.") -> 6470.0892 | M22: =IFERROR(I22/G22-1,"n.d.") -> 1.0562992 | N22: =IFERROR(I22/J22-1,"n.d.") -> 0.85325251 | O22: =IFERROR(I22/K22-1,"n.d.") -> 0.47772485 | P22: =IFERROR(I22/L22-1,"n.d.") -> 0.2845396 | Q22: =IFERROR(F22/PIB_2016,"n.d.") -> 0.46143924 | R22: =IFERROR(G22/PIB_2019,"n.d.") -> 0.54698838 | S22: =IFERROR(H22/PIB_2022,"n.d.") -> 0.56132924 | T22: =IFERROR(I22/PIB_2025,"n.d.") -> 0.65243496 | U22: BCB SGS (S08) | V22: BCB SGS 4478 (S08) | W22: BCB SGS (S08) | X22: S08 | Y22: 22/09/2026 | Z22: [OFICIAL] —
A23: 16 | B23: Renúncias fiscais e gastos tributários | C23: 2019: benefícios tributários efetivos (OSU). 2025: última projeção oficial (DGT Bases Efetivas) | D23: União | E23: R$ bi | F23: ='Receitas públicas'!F17 -> 271 | G23: ='Receitas públicas'!G17 -> 308.4 | H23: ='Receitas públicas'!H17 -> 461.05 | I23: ='Receitas públicas'!I17 -> 587.4 | J23: =IFERROR(F23*FATOR_2016,"n.d.") -> 420.10419 | K23: =IFERROR(G23*FATOR_2019,"n.d.") -> 429.148 | L23: =IFERROR(H23*FATOR_2022,"n.d.") -> 527.22265 | M23: =IFERROR(I23/G23-1,"n.d.") -> 0.90466926 | N23: =IFERROR(I23/J23-1,"n.d.") -> 0.39822456 | O23: =IFERROR(I23/K23-1,"n.d.") -> 0.36875857 | P23: =IFERROR(I23/L23-1,"n.d.") -> 0.11414031 | Q23: =IFERROR(F23/PIB_2016,"n.d.") -> 0.04322633 | R23: =IFERROR(G23/PIB_2019,"n.d.") -> 0.041736978 | S23: =IFERROR(H23/PIB_2022,"n.d.") -> 0.045740558 | T23: =IFERROR(I23/PIB_2025,"n.d.") -> 0.046111941 | U23: Fazenda – OSU 1ª ed. (S36) | V23: OSU 4ª ed. (S13) | W23: MPO – OSU (S36) | X23: RFB via Nota Técnica PLOA 2026 (S14) | Y23: 22/09/2026 | Z23: [ESTIMADO] 2025 é projeção (não realizado): 612,8 − 25,4 = 587,4 (4,40% PIB). Estimativa do PLOA 2025 = 544,4 (612,8 − 68,4). 2019 é valor efetivo. Divergência = diferença entre estimativa ex ante e apuração ex post. [2016/2022] 2016 e 2022 são valores apurados (ex post); 2016 da 1ª edição do OSU, sujeito a revisão.
A24: 17 | B24: Benefícios financeiros e creditícios | C24: Subsídios explícitos (financeiros) + implícitos (creditícios) | D24: União | E24: R$ bi | F24: ='Receitas públicas'!F18 -> 115 | G24: ='Receitas públicas'!G18 -> 40.05 | H24: ='Receitas públicas'!H18 -> 120.43 | I24: ='Receitas públicas'!I18 -> 172.5 | J24: =IFERROR(F24*FATOR_2016,"n.d.") -> 178.273 | K24: =IFERROR(G24*FATOR_2019,"n.d.") -> 55.730795 | L24: =IFERROR(H24*FATOR_2022,"n.d.") -> 137.71483 | M24: =IFERROR(I24/G24-1,"n.d.") -> 3.3071161 | N24: =IFERROR(I24/J24-1,"n.d.") -> -0.0323829 | O24: =IFERROR(I24/K24-1,"n.d.") -> 2.0952366 | P24: =IFERROR(I24/L24-1,"n.d.") -> 0.2525884 | Q24: =IFERROR(F24/PIB_2016,"n.d.") -> 0.018343277 | R24: =IFERROR(G24/PIB_2019,"n.d.") -> 0.0054201232 | S24: =IFERROR(H24/PIB_2022,"n.d.") -> 0.011947805 | T24: =IFERROR(I24/PIB_2025,"n.d.") -> 0.013541556 | U24: Fazenda – OSU (S36) | V24: OSU 4ª ed. (S13) – 11,5% × R$ 348,3 bi | W24: MPO – OSU (S36) | X24: Estimativa do Executivo – PLOA 2026 (S14) | Y24: 22/09/2026 | Z24: [ESTIMADO] 2019: 11,5% de R$ 348,3 bi (cálculo sobre dado oficial). 2025: estimativa do Poder Executivo, não apuração. Em 2024 (realizado, OSU 9ª ed.) financeiros+creditícios = 16,9% de R$ 678 bi ≈ R$ 114,6 bi — ordem de grandeza menor que a estimativa de 2025. [2016/2022] 2016 e 2022 apurados; 2016 inflado por subsídios implícitos do BNDES/FIES.
A25: 18 | B25: Juros nominais pagos (União, orçamento) | C25: GND 2, valor pago no exercício (caixa) | D25: União | E25: R$ bi | F25: ='Dívida e juros'!F10 -> 204.89 | G25: ='Dívida e juros'!G10 -> 285.09 | H25: ='Dívida e juros'!H10 -> 247.31 | I25: ='Dívida e juros'!I10 -> 363.47 | J25: =IFERROR(F25*FATOR_2016,"n.d.") -> 317.62047 | K25: =IFERROR(G25*FATOR_2019,"n.d.") -> 396.71142 | L25: =IFERROR(H25*FATOR_2022,"n.d.") -> 282.80541 | M25: =IFERROR(I25/G25-1,"n.d.") -> 0.27493072 | N25: =IFERROR(I25/J25-1,"n.d.") -> 0.14435319 | O25: =IFERROR(I25/K25-1,"n.d.") -> -0.083792451 | P25: =IFERROR(I25/L25-1,"n.d.") -> 0.28523003 | Q25: =IFERROR(F25/PIB_2016,"n.d.") -> 0.032681339 | R25: =IFERROR(G25/PIB_2019,"n.d.") -> 0.038582345 | S25: =IFERROR(H25/PIB_2022,"n.d.") -> 0.024535511 | T25: =IFERROR(I25/PIB_2025,"n.d.") -> 0.028533039 | U25: RREO Anexo 01 (S05) | V25: RREO Anexo 01 (S05) | W25: RREO Anexo 01 (S05) | X25: S05 | Y25: 22/09/2026 | Z25: [OFICIAL] Pagamento orçamentário; difere dos juros apropriados (competência) do BCB. Não há estatística oficial de juros 'pagos' do setor público consolidado.
A26: 19 | B26: Juros nominais líquidos (setor público consolidado) | C26: Competência, líquidos de juros ativos (BCB/NFSP) | D26: Setor público consolidado | E26: R$ bi | F26: ='Dívida e juros'!F11 -> 407.024 | G26: ='Dívida e juros'!G11 -> 367.282 | H26: ='Dívida e juros'!H11 -> 586.4 | I26: ='Dívida e juros'!I11 -> 1007.6 | J26: =IFERROR(F26*FATOR_2016,"n.d.") -> 630.96859 | K26: =IFERROR(G26*FATOR_2019,"n.d.") -> 511.0841 | L26: =IFERROR(H26*FATOR_2022,"n.d.") -> 670.56362 | M26: =IFERROR(I26/G26-1,"n.d.") -> 1.7433961 | N26: =IFERROR(I26/J26-1,"n.d.") -> 0.59690991 | O26: =IFERROR(I26/K26-1,"n.d.") -> 0.97149551 | P26: =IFERROR(I26/L26-1,"n.d.") -> 0.50261655 | Q26: =IFERROR(F26/PIB_2016,"n.d.") -> 0.064923077 | R26: =IFERROR(G26/PIB_2019,"n.d.") -> 0.04970571 | S26: =IFERROR(H26/PIB_2022,"n.d.") -> 0.058176473 | T26: =IFERROR(I26/PIB_2025,"n.d.") -> 0.079098385 | U26: BCB (S31) | V26: BCB via Agência Brasil (S09) | W26: BCB (S31) | X26: BCB via Poder360 (S10) | Y26: 22/09/2026 | Z26: [OFICIAL] Governo Central (juros nominais BCB): 310,1 (2019) e 891,9 (2025) – ver aba Despesas. 2025 inclui ganho de R$ 105,9 bi com swaps cambiais (redutor).
A27: 20 | B27: Amortizações da dívida | C27: GND 6, pago no exercício | D27: União | E27: R$ bi | F27: ='Dívida e juros'!F16 -> 271.44 | G27: ='Dívida e juros'!G16 -> 275.69 | H27: ='Dívida e juros'!H16 -> 207.09 | I27: ='Dívida e juros'!I16 -> 353.98 | J27: =IFERROR(F27*FATOR_2016,"n.d.") -> 420.78628 | K27: =IFERROR(G27*FATOR_2019,"n.d.") -> 383.63104 | L27: =IFERROR(H27*FATOR_2022,"n.d.") -> 236.81279 | M27: =IFERROR(I27/G27-1,"n.d.") -> 0.28397838 | N27: =IFERROR(I27/J27-1,"n.d.") -> -0.15876535 | O27: =IFERROR(I27/K27-1,"n.d.") -> -0.077290504 | P27: =IFERROR(I27/L27-1,"n.d.") -> 0.49476723 | Q27: =IFERROR(F27/PIB_2016,"n.d.") -> 0.043296513 | R27: =IFERROR(G27/PIB_2019,"n.d.") -> 0.037310206 | S27: =IFERROR(H27/PIB_2022,"n.d.") -> 0.020545303 | T27: =IFERROR(I27/PIB_2025,"n.d.") -> 0.027788057 | U27: RREO Anexo 01 (S05) | V27: RREO Anexo 01 (S05) | W27: RREO Anexo 01 (S05) | X27: S05 | Y27: 22/09/2026 | Z27: [OFICIAL] Fluxo; não confundir com refinanciamento (rolagem com emissão de títulos).
A28: 21 | B28: Refinanciamento da dívida | C28: Amortização paga com recursos de emissão de títulos (rolagem) | D28: União | E28: R$ bi | F28: ='Dívida e juros'!F17 -> 653.82 | G28: ='Dívida e juros'!G17 -> 476.78 | H28: ='Dívida e juros'!H17 -> 1425.07 | I28: ='Dívida e juros'!I17 -> 1417.64 | J28: =IFERROR(F28*FATOR_2016,"n.d.") -> 1013.5517 | K28: =IFERROR(G28*FATOR_2019,"n.d.") -> 663.4539 | L28: =IFERROR(H28*FATOR_2022,"n.d.") -> 1629.6045 | M28: =IFERROR(I28/G28-1,"n.d.") -> 1.973363 | N28: =IFERROR(I28/J28-1,"n.d.") -> 0.39868537 | O28: =IFERROR(I28/K28-1,"n.d.") -> 1.1367574 | P28: =IFERROR(I28/L28-1,"n.d.") -> -0.13007115 | Q28: =IFERROR(F28/PIB_2016,"n.d.") -> 0.10428871 | R28: =IFERROR(G28/PIB_2019,"n.d.") -> 0.064524502 | S28: =IFERROR(H28/PIB_2022,"n.d.") -> 0.14138054 | T28: =IFERROR(I28/PIB_2025,"n.d.") -> 0.11128725 | U28: RREO Anexo 01 (S05) | V28: RREO Anexo 01 (S05) | W28: RREO Anexo 01 (S05) | X28: S05 | Y28: 22/09/2026 | Z28: [OFICIAL] Dotação inicial: 714,09 (2019) e 1.655,91 (2025).
A29: 22 | B29: Investimentos previstos na LOA | C29: Dotação inicial (LOA) – Investimentos (GND 4) | D29: União | E29: R$ bi | F29: ='LOA e execução orçamentária'!F9 -> 45.31 | G29: ='LOA e execução orçamentária'!G9 -> 36.12 | H29: ='LOA e execução orçamentária'!H9 -> 42.36 | I29: ='LOA e execução orçamentária'!I9 -> 80.28 | J29: =IFERROR(F29*FATOR_2016,"n.d.") -> 70.239561 | K29: =IFERROR(G29*FATOR_2019,"n.d.") -> 50.262081 | L29: =IFERROR(H29*FATOR_2022,"n.d.") -> 48.43976 | M29: =IFERROR(I29/G29-1,"n.d.") -> 1.2225914 | N29: =IFERROR(I29/J29-1,"n.d.") -> 0.14294565 | O29: =IFERROR(I29/K29-1,"n.d.") -> 0.59722795 | P29: =IFERROR(I29/L29-1,"n.d.") -> 0.65731623 | Q29: =IFERROR(F29/PIB_2016,"n.d.") -> 0.007227251 | R29: =IFERROR(G29/PIB_2019,"n.d.") -> 0.0048882609 | S29: =IFERROR(H29/PIB_2022,"n.d.") -> 0.004202516 | T29: =IFERROR(I29/PIB_2025,"n.d.") -> 0.0063021222 | U29: RREO Anexo 01 (S05) | V29: RREO Anexo 01 (S05) | W29: RREO Anexo 01 (S05) | X29: RREO Anexo 01 (S05) | Y29: 22/09/2026 | Z29: [OFICIAL] Exclui intra-orçamentárias.
A30: 23 | B30: Investimentos empenhados | C30: Empenhado – Investimentos (GND 4) | D30: União | E30: R$ bi | F30: ='LOA e execução orçamentária'!F11 -> 38.08 | G30: ='LOA e execução orçamentária'!G11 -> 42.44 | H30: ='LOA e execução orçamentária'!H11 -> 51.19 | I30: ='LOA e execução orçamentária'!I11 -> 72.11 | J30: =IFERROR(F30*FATOR_2016,"n.d.") -> 59.031615 | K30: =IFERROR(G30*FATOR_2019,"n.d.") -> 59.056553 | L30: =IFERROR(H30*FATOR_2022,"n.d.") -> 58.537094 | M30: =IFERROR(I30/G30-1,"n.d.") -> 0.69910462 | N30: =IFERROR(I30/J30-1,"n.d.") -> 0.22154883 | O30: =IFERROR(I30/K30-1,"n.d.") -> 0.22103299 | P30: =IFERROR(I30/L30-1,"n.d.") -> 0.23186846 | Q30: =IFERROR(F30/PIB_2016,"n.d.") -> 0.0060740172 | R30: =IFERROR(G30/PIB_2019,"n.d.") -> 0.0057435712 | S30: =IFERROR(H30/PIB_2022,"n.d.") -> 0.0050785363 | T30: =IFERROR(I30/PIB_2025,"n.d.") -> 0.0056607628 | U30: RREO Anexo 01 (S05) | V30: RREO Anexo 01 (S05) | W30: RREO Anexo 01 (S05) | X30: RREO Anexo 01 (S05) | Y30: 22/09/2026 | Z30: [OFICIAL] —
A31: 24 | B31: Investimentos pagos | C31: Pago – Investimentos (GND 4) | D31: União | E31: R$ bi | F31: ='LOA e execução orçamentária'!F13 -> 16.8 | G31: ='LOA e execução orçamentária'!G13 -> 16.37 | H31: ='LOA e execução orçamentária'!H13 -> 19.59 | I31: ='LOA e execução orçamentária'!I13 -> 37.81 | J31: =IFERROR(F31*FATOR_2016,"n.d.") -> 26.04336 | K31: =IFERROR(G31*FATOR_2019,"n.d.") -> 22.779354 | L31: =IFERROR(H31*FATOR_2022,"n.d.") -> 22.401674 | M31: =IFERROR(I31/G31-1,"n.d.") -> 1.3097129 | N31: =IFERROR(I31/J31-1,"n.d.") -> 0.45180962 | O31: =IFERROR(I31/K31-1,"n.d.") -> 0.65983637 | P31: =IFERROR(I31/L31-1,"n.d.") -> 0.68782032 | Q31: =IFERROR(F31/PIB_2016,"n.d.") -> 0.0026797135 | R31: =IFERROR(G31/PIB_2019,"n.d.") -> 0.0022154161 | S31: =IFERROR(H31/PIB_2022,"n.d.") -> 0.0019435149 | T31: =IFERROR(I31/PIB_2025,"n.d.") -> 0.002968152 | U31: RREO Anexo 01 (S05) | V31: RREO Anexo 01 (S05) | W31: RREO Anexo 01 (S05) | X31: RREO Anexo 01 (S05) | Y31: 22/09/2026 | Z31: [OFICIAL] Pago do exercício (sem RAP).
A32: 25 | B32: Saúde prevista na LOA | C32: Dotação inicial (LOA) – Saúde (função 10) | D32: União | E32: R$ bi | F32: ='Saúde, educação e previdência'!F4 -> 108.006 | G32: ='Saúde, educação e previdência'!G4 -> 120.56 | H32: ='Saúde, educação e previdência'!H4 -> 147.204 | I32: ='Saúde, educação e previdência'!I4 -> 232.87 | J32: =IFERROR(F32*FATOR_2016,"n.d.") -> 167.4309 | K32: =IFERROR(G32*FATOR_2019,"n.d.") -> 167.76291 | L32: =IFERROR(H32*FATOR_2022,"n.d.") -> 168.3316 | M32: =IFERROR(I32/G32-1,"n.d.") -> 0.93156934 | N32: =IFERROR(I32/J32-1,"n.d.") -> 0.39084245 | O32: =IFERROR(I32/K32-1,"n.d.") -> 0.38808986 | P32: =IFERROR(I32/L32-1,"n.d.") -> 0.38340042 | Q32: =IFERROR(F32/PIB_2016,"n.d.") -> 0.017227686 | R32: =IFERROR(G32/PIB_2019,"n.d.") -> 0.016315856 | S32: =IFERROR(H32/PIB_2022,"n.d.") -> 0.014604041 | T32: =IFERROR(I32/PIB_2025,"n.d.") -> 0.018280708 | U32: RREO Anexo 02 (S06) | V32: RREO Anexo 02 (S06) | W32: RREO Anexo 02 (S06) | X32: RREO Anexo 02 (S06) | Y32: 22/09/2026 | Z32: [OFICIAL] Exclui intra-orçamentárias.
A33: 26a | B33: Saúde empenhada | C33: Empenhado – Saúde (função 10) | D33: União | E33: R$ bi | F33: ='Saúde, educação e previdência'!F6 -> 106.487 | G33: ='Saúde, educação e previdência'!G6 -> 124.11 | H33: ='Saúde, educação e previdência'!H6 -> 153.231 | I33: ='Saúde, educação e previdência'!I6 -> 238.64 | J33: =IFERROR(F33*FATOR_2016,"n.d.") -> 165.07614 | K33: =IFERROR(G33*FATOR_2019,"n.d.") -> 172.70285 | L33: =IFERROR(H33*FATOR_2022,"n.d.") -> 175.22363 | M33: =IFERROR(I33/G33-1,"n.d.") -> 0.92281041 | N33: =IFERROR(I33/J33-1,"n.d.") -> 0.4456359 | O33: =IFERROR(I33/K33-1,"n.d.") -> 0.3817954 | P33: =IFERROR(I33/L33-1,"n.d.") -> 0.36191679 | Q33: =IFERROR(F33/PIB_2016,"n.d.") -> 0.016985396 | R33: =IFERROR(G33/PIB_2019,"n.d.") -> 0.016796292 | S33: =IFERROR(H33/PIB_2022,"n.d.") -> 0.015201977 | T33: =IFERROR(I33/PIB_2025,"n.d.") -> 0.018733663 | U33: RREO Anexo 02 (S06) | V33: RREO Anexo 02 (S06) | W33: RREO Anexo 02 (S06) | X33: RREO Anexo 02 (S06) | Y33: 22/09/2026 | Z33: [OFICIAL] —
A34: 26b | B34: Saúde paga | C34: Pago – Saúde (função 10) | D34: União | E34: R$ bi | F34: ='Saúde, educação e previdência'!F8 -> 100.191 | G34: ='Saúde, educação e previdência'!G8 -> 114.182 | H34: ='Saúde, educação e previdência'!H8 -> 136.85 | I34: ='Saúde, educação e previdência'!I8 -> 234.28 | J34: =IFERROR(F34*FATOR_2016,"n.d.") -> 155.31609 | K34: =IFERROR(G34*FATOR_2019,"n.d.") -> 158.88773 | L34: =IFERROR(H34*FATOR_2022,"n.d.") -> 156.49153 | M34: =IFERROR(I34/G34-1,"n.d.") -> 1.051812 | N34: =IFERROR(I34/J34-1,"n.d.") -> 0.50840784 | O34: =IFERROR(I34/K34-1,"n.d.") -> 0.47450024 | P34: =IFERROR(I34/L34-1,"n.d.") -> 0.49707785 | Q34: =IFERROR(F34/PIB_2016,"n.d.") -> 0.015981141 | R34: =IFERROR(G34/PIB_2019,"n.d.") -> 0.015452697 | S34: =IFERROR(H34/PIB_2022,"n.d.") -> 0.013576825 | T34: =IFERROR(I34/PIB_2025,"n.d.") -> 0.018391395 | U34: Portal da Transparência (S07) | V34: Portal da Transparência (S07) | W34: Portal da Transparência (S07) | X34: Portal da Transparência (S07) | Y34: 22/09/2026 | Z34: [OFICIAL] Pago segundo o Portal da Transparência: inclui restos a pagar pagos no ano e classificação por função do Portal; pode divergir do RREO (critérios distintos).
A35: 27 | B35: Educação prevista na LOA | C35: Dotação inicial (LOA) – Educação (função 12) | D35: União | E35: R$ bi | F35: ='Saúde, educação e previdência'!F9 -> 91.627 | G35: ='Saúde, educação e previdência'!G9 -> 103.03 | H35: ='Saúde, educação e previdência'!H9 -> 112.505 | I35: ='Saúde, educação e previdência'!I9 -> 163.1 | J35: =IFERROR(F35*FATOR_2016,"n.d.") -> 142.04017 | K35: =IFERROR(G35*FATOR_2019,"n.d.") -> 143.36938 | L35: =IFERROR(H35*FATOR_2022,"n.d.") -> 128.65239 | M35: =IFERROR(I35/G35-1,"n.d.") -> 0.58303407 | N35: =IFERROR(I35/J35-1,"n.d.") -> 0.1482667 | O35: =IFERROR(I35/K35-1,"n.d.") -> 0.13762084 | P35: =IFERROR(I35/L35-1,"n.d.") -> 0.26775726 | Q35: =IFERROR(F35/PIB_2016,"n.d.") -> 0.014615125 | R35: =IFERROR(G35/PIB_2019,"n.d.") -> 0.013943453 | S35: =IFERROR(H35/PIB_2022,"n.d.") -> 0.011161569 | T35: =IFERROR(I35/PIB_2025,"n.d.") -> 0.012803639 | U35: RREO Anexo 02 (S06) | V35: RREO Anexo 02 (S06) | W35: RREO Anexo 02 (S06) | X35: RREO Anexo 02 (S06) | Y35: 22/09/2026 | Z35: [OFICIAL] Exclui intra-orçamentárias.
A36: 28a | B36: Educação empenhada | C36: Empenhado – Educação (função 12) | D36: União | E36: R$ bi | F36: ='Saúde, educação e previdência'!F11 -> 94.546 | G36: ='Saúde, educação e previdência'!G11 -> 101.3 | H36: ='Saúde, educação e previdência'!H11 -> 117.753 | I36: ='Saúde, educação e previdência'!I11 -> 176.01 | J36: =IFERROR(F36*FATOR_2016,"n.d.") -> 146.56521 | K36: =IFERROR(G36*FATOR_2019,"n.d.") -> 140.96204 | L36: =IFERROR(H36*FATOR_2022,"n.d.") -> 134.65361 | M36: =IFERROR(I36/G36-1,"n.d.") -> 0.73751234 | N36: =IFERROR(I36/J36-1,"n.d.") -> 0.20089893 | O36: =IFERROR(I36/K36-1,"n.d.") -> 0.24863406 | P36: =IFERROR(I36/L36-1,"n.d.") -> 0.30713166 | Q36: =IFERROR(F36/PIB_2016,"n.d.") -> 0.015080726 | R36: =IFERROR(G36/PIB_2019,"n.d.") -> 0.013709325 | S36: =IFERROR(H36/PIB_2022,"n.d.") -> 0.011682221 | T36: =IFERROR(I36/PIB_2025,"n.d.") -> 0.013817097 | U36: RREO Anexo 02 (S06) | V36: RREO Anexo 02 (S06) | W36: RREO Anexo 02 (S06) | X36: RREO Anexo 02 (S06) | Y36: 22/09/2026 | Z36: [OFICIAL] —
A37: 28b | B37: Educação paga | C37: Pago – Educação (função 12) | D37: União | E37: R$ bi | F37: ='Saúde, educação e previdência'!F13 -> 95.184 | G37: ='Saúde, educação e previdência'!G13 -> 94.474 | H37: ='Saúde, educação e previdência'!H13 -> 109.778 | I37: ='Saúde, educação e previdência'!I13 -> 174.587 | J37: =IFERROR(F37*FATOR_2016,"n.d.") -> 147.55423 | K37: =IFERROR(G37*FATOR_2019,"n.d.") -> 131.46345 | L37: =IFERROR(H37*FATOR_2022,"n.d.") -> 125.53399 | M37: =IFERROR(I37/G37-1,"n.d.") -> 0.84798992 | N37: =IFERROR(I37/J37-1,"n.d.") -> 0.18320563 | O37: =IFERROR(I37/K37-1,"n.d.") -> 0.32802692 | P37: =IFERROR(I37/L37-1,"n.d.") -> 0.39075477 | Q37: =IFERROR(F37/PIB_2016,"n.d.") -> 0.015182491 | R37: =IFERROR(G37/PIB_2019,"n.d.") -> 0.012785536 | S37: =IFERROR(H37/PIB_2022,"n.d.") -> 0.010891025 | T37: =IFERROR(I37/PIB_2025,"n.d.") -> 0.013705389 | U37: Portal da Transparência (S07) | V37: Portal da Transparência (S07) | W37: Portal da Transparência (S07) | X37: Portal da Transparência (S07) | Y37: 22/09/2026 | Z37: [OFICIAL] Pago segundo o Portal da Transparência: inclui restos a pagar pagos no ano e classificação por função do Portal; pode divergir do RREO (critérios distintos).
A38: 29 | B38: Segurança pública prevista na LOA | C38: Dotação inicial (LOA) – Segurança pública (função 06) | D38: União | E38: R$ bi | F38: ='Segurança e polít. afirmativas'!F4 -> 7.032 | G38: ='Segurança e polít. afirmativas'!G4 -> 10.37 | H38: ='Segurança e polít. afirmativas'!H4 -> 11.607 | I38: ='Segurança e polít. afirmativas'!I4 -> 15.62 | J38: =IFERROR(F38*FATOR_2016,"n.d.") -> 10.901006 | K38: =IFERROR(G38*FATOR_2019,"n.d.") -> 14.430171 | L38: =IFERROR(H38*FATOR_2022,"n.d.") -> 13.272906 | M38: =IFERROR(I38/G38-1,"n.d.") -> 0.50626808 | N38: =IFERROR(I38/J38-1,"n.d.") -> 0.43289525 | O38: =IFERROR(I38/K38-1,"n.d.") -> 0.082454255 | P38: =IFERROR(I38/L38-1,"n.d.") -> 0.17683348 | Q38: =IFERROR(F38/PIB_2016,"n.d.") -> 0.0011216515 | R38: =IFERROR(G38/PIB_2019,"n.d.") -> 0.0014034127 | S38: =IFERROR(H38/PIB_2022,"n.d.") -> 0.0011515251 | T38: =IFERROR(I38/PIB_2025,"n.d.") -> 0.0012261977 | U38: RREO Anexo 02 (S06) | V38: RREO Anexo 02 (S06) | W38: RREO Anexo 02 (S06) | X38: RREO Anexo 02 (S06) | Y38: 22/09/2026 | Z38: [OFICIAL] Exclui intra-orçamentárias.
A39: 30a | B39: Segurança pública empenhada | C39: Empenhado – Segurança pública (função 06) | D39: União | E39: R$ bi | F39: ='Segurança e polít. afirmativas'!F6 -> 8.816 | G39: ='Segurança e polít. afirmativas'!G6 -> 10.23 | H39: ='Segurança e polít. afirmativas'!H6 -> 13.057 | I39: ='Segurança e polít. afirmativas'!I6 -> 16.58 | J39: =IFERROR(F39*FATOR_2016,"n.d.") -> 13.666563 | K39: =IFERROR(G39*FATOR_2019,"n.d.") -> 14.235357 | L39: =IFERROR(H39*FATOR_2022,"n.d.") -> 14.931018 | M39: =IFERROR(I39/G39-1,"n.d.") -> 0.62072336 | N39: =IFERROR(I39/J39-1,"n.d.") -> 0.21317994 | O39: =IFERROR(I39/K39-1,"n.d.") -> 0.16470562 | P39: =IFERROR(I39/L39-1,"n.d.") -> 0.11043999 | Q39: =IFERROR(F39/PIB_2016,"n.d.") -> 0.0014062115 | R39: =IFERROR(G39/PIB_2019,"n.d.") -> 0.0013844659 | S39: =IFERROR(H39/PIB_2022,"n.d.") -> 0.0012953789 | T39: =IFERROR(I39/PIB_2025,"n.d.") -> 0.0013015594 | U39: RREO Anexo 02 (S06) | V39: RREO Anexo 02 (S06) | W39: RREO Anexo 02 (S06) | X39: RREO Anexo 02 (S06) | Y39: 22/09/2026 | Z39: [OFICIAL] —
A40: 30b | B40: Segurança pública paga | C40: Pago – Segurança pública (função 06) | D40: União | E40: R$ bi | F40: ='Segurança e polít. afirmativas'!F8 -> 8.423 | G40: ='Segurança e polít. afirmativas'!G8 -> 9.018 | H40: ='Segurança e polít. afirmativas'!H8 -> 11.729 | I40: ='Segurança e polít. afirmativas'!I8 -> 15.41 | J40: =IFERROR(F40*FATOR_2016,"n.d.") -> 13.057334 | K40: =IFERROR(G40*FATOR_2019,"n.d.") -> 12.548822 | L40: =IFERROR(H40*FATOR_2022,"n.d.") -> 13.412416 | M40: =IFERROR(I40/G40-1,"n.d.") -> 0.70880461 | N40: =IFERROR(I40/J40-1,"n.d.") -> 0.18017963 | O40: =IFERROR(I40/K40-1,"n.d.") -> 0.22800373 | P40: =IFERROR(I40/L40-1,"n.d.") -> 0.14893543 | Q40: =IFERROR(F40/PIB_2016,"n.d.") -> 0.0013435254 | R40: =IFERROR(G40/PIB_2019,"n.d.") -> 0.0012204412 | S40: =IFERROR(H40/PIB_2022,"n.d.") -> 0.0011636287 | T40: =IFERROR(I40/PIB_2025,"n.d.") -> 0.0012097123 | U40: Portal da Transparência (S07) | V40: Portal da Transparência (S07) | W40: Portal da Transparência (S07) | X40: Portal da Transparência (S07) | Y40: 22/09/2026 | Z40: [OFICIAL] Pago segundo o Portal da Transparência: inclui restos a pagar pagos no ano e classificação por função do Portal; pode divergir do RREO (critérios distintos).
A41: 31 | B41: Previdência prevista na LOA | C41: Dotação inicial (LOA) – Previdência Social (função 09) | D41: União | E41: R$ bi | F41: ='Saúde, educação e previdência'!F14 -> 570.877 | G41: ='Saúde, educação e previdência'!G14 -> 733.92 | H41: ='Saúde, educação e previdência'!H14 -> 882.003 | I41: ='Saúde, educação e previdência'!I14 -> 1085.59 | J41: =IFERROR(F41*FATOR_2016,"n.d.") -> 884.97351 | K41: =IFERROR(G41*FATOR_2019,"n.d.") -> 1021.272 | L41: =IFERROR(H41*FATOR_2022,"n.d.") -> 1008.5933 | M41: =IFERROR(I41/G41-1,"n.d.") -> 0.47916667 | N41: =IFERROR(I41/J41-1,"n.d.") -> 0.22669209 | O41: =IFERROR(I41/K41-1,"n.d.") -> 0.062978278 | P41: =IFERROR(I41/L41-1,"n.d.") -> 0.07634065 | Q41: =IFERROR(F41/PIB_2016,"n.d.") -> 0.091058737 | R41: =IFERROR(G41/PIB_2019,"n.d.") -> 0.099324264 | S41: =IFERROR(H41/PIB_2022,"n.d.") -> 0.08750311 | T41: =IFERROR(I41/PIB_2025,"n.d.") -> 0.085220738 | U41: RREO Anexo 02 (S06) | V41: RREO Anexo 02 (S06) | W41: RREO Anexo 02 (S06) | X41: RREO Anexo 02 (S06) | Y41: 22/09/2026 | Z41: [OFICIAL] Exclui intra-orçamentárias.
A42: 32a | B42: Previdência empenhada | C42: Empenhado – Previdência Social (função 09) | D42: União | E42: R$ bi | F42: ='Saúde, educação e previdência'!F16 -> 594.563 | G42: ='Saúde, educação e previdência'!G16 -> 726.13 | H42: ='Saúde, educação e previdência'!H16 -> 897.148 | I42: ='Saúde, educação e previdência'!I16 -> 1103.11 | J42: =IFERROR(F42*FATOR_2016,"n.d.") -> 921.69155 | K42: =IFERROR(G42*FATOR_2019,"n.d.") -> 1010.432 | L42: =IFERROR(H42*FATOR_2022,"n.d.") -> 1025.912 | M42: =IFERROR(I42/G42-1,"n.d.") -> 0.51916324 | N42: =IFERROR(I42/J42-1,"n.d.") -> 0.19683207 | O42: =IFERROR(I42/K42-1,"n.d.") -> 0.09172114 | P42: =IFERROR(I42/L42-1,"n.d.") -> 0.075248138 | Q42: =IFERROR(F42/PIB_2016,"n.d.") -> 0.094836814 | R42: =IFERROR(G42/PIB_2019,"n.d.") -> 0.098270013 | S42: =IFERROR(H42/PIB_2022,"n.d.") -> 0.089005639 | T42: =IFERROR(I42/PIB_2025,"n.d.") -> 0.086596089 | U42: RREO Anexo 02 (S06) | V42: RREO Anexo 02 (S06) | W42: RREO Anexo 02 (S06) | X42: RREO Anexo 02 (S06) | Y42: 22/09/2026 | Z42: [OFICIAL] —
A43: 32b | B43: Previdência paga | C43: Pago – Previdência Social (função 09) | D43: União | E43: R$ bi | F43: ='Saúde, educação e previdência'!F18 -> 568.387 | G43: ='Saúde, educação e previdência'!G18 -> 668.956 | H43: ='Saúde, educação e previdência'!H18 -> 824.009 | I43: ='Saúde, educação e previdência'!I18 -> 1126.374 | J43: =IFERROR(F43*FATOR_2016,"n.d.") -> 881.11351 | K43: =IFERROR(G43*FATOR_2019,"n.d.") -> 930.87266 | L43: =IFERROR(H43*FATOR_2022,"n.d.") -> 942.27569 | M43: =IFERROR(I43/G43-1,"n.d.") -> 0.6837789 | N43: =IFERROR(I43/J43-1,"n.d.") -> 0.27835289 | O43: =IFERROR(I43/K43-1,"n.d.") -> 0.21001943 | P43: =IFERROR(I43/L43-1,"n.d.") -> 0.19537628 | Q43: =IFERROR(F43/PIB_2016,"n.d.") -> 0.090661565 | R43: =IFERROR(G43/PIB_2019,"n.d.") -> 0.090532432 | S43: =IFERROR(H43/PIB_2022,"n.d.") -> 0.081749552 | T43: =IFERROR(I43/PIB_2025,"n.d.") -> 0.088422355 | U43: Portal da Transparência (S07) | V43: Portal da Transparência (S07) | W43: Portal da Transparência (S07) | X43: Portal da Transparência (S07) | Y43: 22/09/2026 | Z43: [OFICIAL] Pago segundo o Portal da Transparência: inclui restos a pagar pagos no ano e classificação por função do Portal; pode divergir do RREO (critérios distintos). Em 2019 o pago do Portal (668,96) fica abaixo do liquidado do RREO (725,89): o Portal reclassifica parte dos benefícios; prefira o liquidado/RTN para comparação.
A44: 33 | B44: Políticas afirmativas previstas (orçamento atualizado) | C44: Orçamento atualizado (proxy de 'previsto') | D44: União | E44: R$ mi | F44: ='Segurança e polít. afirmativas'!F9 -> 39.609 | G44: ='Segurança e polít. afirmativas'!G9 -> 12.908 | H44: ='Segurança e polít. afirmativas'!H9 -> não localizado após busca | I44: ='Segurança e polít. afirmativas'!I9 -> 78.02 | J44: =IFERROR(F44*FATOR_2016,"n.d.") -> 61.401871 | K44: =IFERROR(G44*FATOR_2019,"n.d.") -> 17.961875 | L44: =IFERROR(H44*FATOR_2022,"n.d.") -> n.d. | M44: =IFERROR(I44/G44-1,"n.d.") -> 5.0443136 | N44: =IFERROR(I44/J44-1,"n.d.") -> 0.27064533 | O44: =IFERROR(I44/K44-1,"n.d.") -> 3.3436444 | P44: =IFERROR(I44/L44-1,"n.d.") -> n.d. | Q44: =IFERROR(F44/1000/PIB_2016,"n.d.") -> 6.317903e-06 | R44: =IFERROR(G44/1000/PIB_2019,"n.d.") -> 1.7468901e-06 | S44: =IFERROR(H44/1000/PIB_2022,"n.d.") -> n.d. | T44: =IFERROR(I44/1000/PIB_2025,"n.d.") -> 6.1247082e-06 | U44: Portal – Programa 2034 (S07) | V44: Portal – Programa 2034 (S07) | W44: Sem programa específico no PPA 2020–23 | X44: Portal – Programa 5804 (S07) | Y44: 22/09/2026 | Z44: [APROXIMAÇÃO] Programa 2034 'Promoção da Igualdade Racial e Superação do Racismo' (PPA 2016–19) × 5804 'Promoção da Igualdade Étnico-Racial, Combate e Superação do Racismo' (PPA 2024–27). Programas diferentes; dotação inicial não localizada.
A45: 34a | B45: Políticas afirmativas empenhadas | C45: Empenhado – Políticas afirmativas – programa de igualdade racial | D45: União | E45: R$ mi | F45: ='Segurança e polít. afirmativas'!F10 -> 20.269 | G45: ='Segurança e polít. afirmativas'!G10 -> 12.458 | H45: ='Segurança e polít. afirmativas'!H10 -> não localizado após busca | I45: ='Segurança e polít. afirmativas'!I10 -> 77.486 | J45: =IFERROR(F45*FATOR_2016,"n.d.") -> 31.421003 | K45: =IFERROR(G45*FATOR_2019,"n.d.") -> 17.335687 | L45: =IFERROR(H45*FATOR_2022,"n.d.") -> n.d. | M45: =IFERROR(I45/G45-1,"n.d.") -> 5.2197785 | N45: =IFERROR(I45/J45-1,"n.d.") -> 1.4660575 | O45: =IFERROR(I45/K45-1,"n.d.") -> 3.4697393 | P45: =IFERROR(I45/L45-1,"n.d.") -> n.d. | Q45: =IFERROR(F45/1000/PIB_2016,"n.d.") -> 3.2330424e-06 | R45: =IFERROR(G45/1000/PIB_2019,"n.d.") -> 1.6859899e-06 | S45: =IFERROR(H45/1000/PIB_2022,"n.d.") -> n.d. | T45: =IFERROR(I45/1000/PIB_2025,"n.d.") -> 6.0827883e-06 | U45: S07 | V45: S07 | W45: Sem programa específico no PPA 2020–23 | X45: S07 | Y45: 22/09/2026 | Z45: [APROXIMAÇÃO] Mesmo recorte da linha acima.
A46: 34b | B46: Políticas afirmativas pagas | C46: Pago no exercício (sem RAP) | D46: União | E46: R$ mi | F46: ='Segurança e polít. afirmativas'!F12 -> 8.298 | G46: ='Segurança e polít. afirmativas'!G12 -> 5.88 | H46: ='Segurança e polít. afirmativas'!H12 -> não localizado após busca | I46: ='Segurança e polít. afirmativas'!I12 -> 58.026 | J46: =IFERROR(F46*FATOR_2016,"n.d.") -> 12.863559 | K46: =IFERROR(G46*FATOR_2019,"n.d.") -> 8.1821992 | L46: =IFERROR(H46*FATOR_2022,"n.d.") -> n.d. | M46: =IFERROR(I46/G46-1,"n.d.") -> 8.8683673 | N46: =IFERROR(I46/J46-1,"n.d.") -> 3.5108821 | O46: =IFERROR(I46/K46-1,"n.d.") -> 6.0917364 | P46: =IFERROR(I46/L46-1,"n.d.") -> n.d. | Q46: =IFERROR(F46/1000/PIB_2016,"n.d.") -> 1.323587e-06 | R46: =IFERROR(G46/1000/PIB_2019,"n.d.") -> 7.957634e-07 | S46: =IFERROR(H46/1000/PIB_2022,"n.d.") -> n.d. | T46: =IFERROR(I46/1000/PIB_2025,"n.d.") -> 4.5551438e-06 | U46: S07 | V46: S07 | W46: Sem programa específico no PPA 2020–23 | X46: S07 | Y46: 22/09/2026 | Z46: [APROXIMAÇÃO] RAP pagos no ano: 9,25 (2019) e 22,73 (2025). [2016/2022] 2016: RAP pagos no ano R$ 23,83 mi.
A47: 34c | B47: Transferência de renda – Bolsa Família/Auxílio Brasil (pago) | C47: Pago no exercício (sem RAP) | D47: União | E47: R$ bi | F47: ='Políticas afirmativas e apoio'!F7 -> 27.49159 | G47: ='Políticas afirmativas e apoio'!G7 -> 32.48162 | H47: ='Políticas afirmativas e apoio'!H7 -> 113.02915 | I47: ='Políticas afirmativas e apoio'!I7 -> 171.82365 | J47: =IFERROR(F47*FATOR_2016,"n.d.") -> 42.617462 | K47: =IFERROR(G47*FATOR_2019,"n.d.") -> 45.199164 | L47: =IFERROR(H47*FATOR_2022,"n.d.") -> 129.25177 | M47: =IFERROR(I47/G47-1,"n.d.") -> 4.2898732 | N47: =IFERROR(I47/J47-1,"n.d.") -> 3.0317664 | O47: =IFERROR(I47/K47-1,"n.d.") -> 2.8014785 | P47: =IFERROR(I47/L47-1,"n.d.") -> 0.32937176 | Q47: =IFERROR(F47/PIB_2016,"n.d.") -> 0.0043850943 | R47: =IFERROR(G47/PIB_2019,"n.d.") -> 0.0043958647 | S47: =IFERROR(H47/PIB_2022,"n.d.") -> 0.01121357 | T47: =IFERROR(I47/PIB_2025,"n.d.") -> 0.013488461 | U47: Portal da Transparência – ação 8442 (S40) | V47: Portal da Transparência – ação 8442 (S40) | W47: Portal da Transparência – ação 21DP – Auxílio Brasil (S40) | X47: Portal da Transparência – ação 8442 (S40) | Y47: 22/09/2026 | Z47: [OFICIAL] 2022 = ação 21DP (Auxílio Brasil, inclui o adicional de R$ 200 aprovado pela EC 123/2022). 2025 = novo Bolsa Família (Lei 14.601/2023).
A48: 34d | B48: BPC/LOAS (pago, RTN) | C48: RTN, caixa (idosos e pessoas com deficiência de baixa renda) | D48: Governo Central | E48: R$ bi | F48: ='Políticas afirmativas e apoio'!F12 -> 48.99 | G48: ='Políticas afirmativas e apoio'!G12 -> 59.728 | H48: ='Políticas afirmativas e apoio'!H12 -> 78.827 | I48: ='Políticas afirmativas e apoio'!I12 -> 127.236 | J48: =IFERROR(F48*FATOR_2016,"n.d.") -> 75.944297 | K48: =IFERROR(G48*FATOR_2019,"n.d.") -> 83.113332 | L48: =IFERROR(H48*FATOR_2022,"n.d.") -> 90.140721 | M48: =IFERROR(I48/G48-1,"n.d.") -> 1.1302572 | N48: =IFERROR(I48/J48-1,"n.d.") -> 0.67538585 | O48: =IFERROR(I48/K48-1,"n.d.") -> 0.53087353 | P48: =IFERROR(I48/L48-1,"n.d.") -> 0.41152632 | Q48: =IFERROR(F48/PIB_2016,"n.d.") -> 0.0078142359 | R48: =IFERROR(G48/PIB_2019,"n.d.") -> 0.0080832239 | S48: =IFERROR(H48/PIB_2022,"n.d.") -> 0.0078203903 | T48: =IFERROR(I48/PIB_2025,"n.d.") -> 0.0099882514 | U48: STN – RTN tab. 2.1 (S04) | V48: STN – RTN tab. 2.1 (S04) | W48: STN – RTN tab. 2.1 (S04) | X48: STN – RTN tab. 2.1 (S04) | Y48: 22/09/2026 | Z48: [OFICIAL] Mesma série da aba 'Despesas públicas' (linha 11.3).
A49: 34e | B49: Assistência estudantil – PNAES (pago) | C49: Pago no exercício (sem RAP) | D49: União | E49: R$ mi | F49: ='Políticas afirmativas e apoio'!F16 -> 810.1 | G49: ='Políticas afirmativas e apoio'!G16 -> 867.39 | H49: ='Políticas afirmativas e apoio'!H16 -> 818.34 | I49: ='Políticas afirmativas e apoio'!I16 -> 1242.07 | J49: =IFERROR(F49*FATOR_2016,"n.d.") -> 1255.817 | K49: =IFERROR(G49*FATOR_2019,"n.d.") -> 1206.9996 | L49: =IFERROR(H49*FATOR_2022,"n.d.") -> 935.79304 | M49: =IFERROR(I49/G49-1,"n.d.") -> 0.43196255 | N49: =IFERROR(I49/J49-1,"n.d.") -> -0.010946656 | O49: =IFERROR(I49/K49-1,"n.d.") -> 0.029055836 | P49: =IFERROR(I49/L49-1,"n.d.") -> 0.32729135 | Q49: =IFERROR(F49/1000/PIB_2016,"n.d.") -> 0.00012921642 | R49: =IFERROR(G49/1000/PIB_2019,"n.d.") -> 0.00011738728 | S49: =IFERROR(H49/1000/PIB_2022,"n.d.") -> 8.1187133e-05 | T49: =IFERROR(I49/1000/PIB_2025,"n.d.") -> 9.7504696e-05 | U49: Portal da Transparência – ação 4002 (S40) | V49: Portal da Transparência – ação 4002 (S40) | W49: Portal da Transparência – ação 4002 (S40) | X49: Portal da Transparência – ação 4002 (S40) | Y49: 22/09/2026 | Z49: [OFICIAL] —
A50: 34f | B50: Políticas afirmativas e de apoio – subtotal pago | C50: Soma de PA.1 + PA.3 + PA.4 + PA.5 + PA.6 (mesma fonte e conceito) | D50: União | E50: R$ bi | F50: ='Políticas afirmativas e apoio'!F38 -> 28.801758 | G50: ='Políticas afirmativas e apoio'!G38 -> 33.90942 | H50: ='Políticas afirmativas e apoio'!H38 -> 114.40135 | I50: ='Políticas afirmativas e apoio'!I38 -> 174.1054 | J50: =IFERROR(F50*FATOR_2016,"n.d.") -> 44.648484 | K50: =IFERROR(G50*FATOR_2019,"n.d.") -> 47.185991 | L50: =IFERROR(H50*FATOR_2022,"n.d.") -> 130.82091 | M50: =IFERROR(I50/G50-1,"n.d.") -> 4.1344257 | N50: =IFERROR(I50/J50-1,"n.d.") -> 2.8994693 | O50: =IFERROR(I50/K50-1,"n.d.") -> 2.6897688 | P50: =IFERROR(I50/L50-1,"n.d.") -> 0.33086821 | Q50: =IFERROR(F50/PIB_2016,"n.d.") -> 0.0045940749 | R50: =IFERROR(G50/PIB_2019,"n.d.") -> 0.0045890944 | S50: =IFERROR(H50/PIB_2022,"n.d.") -> 0.011349705 | T50: =IFERROR(I50/PIB_2025,"n.d.") -> 0.013667582 | U50: Cálculo sobre S40 | V50: Cálculo sobre S40 | W50: Cálculo sobre S40 | X50: Cálculo sobre S40 | Y50: 22/09/2026 | Z50: [ESTIMADO] Não inclui BPC (fonte RTN, critério distinto), Auxílio Gás e Pé-de-Meia (orçamento/previsão). Para incluir o BPC, somar PA.2 só como ordem de grandeza.
A51: 34g | B51: Alimentação escolar – PNAE (repasse) | C51: Repasse do FNDE às redes estaduais, distrital e municipais | D51: União → subnacionais | E51: R$ bi | F51: ='Políticas afirmativas e apoio'!F33 -> 3.42 | G51: ='Políticas afirmativas e apoio'!G33 -> 3.95 | H51: ='Políticas afirmativas e apoio'!H33 -> 3.56 | I51: ='Políticas afirmativas e apoio'!I33 -> 5.5 | J51: =IFERROR(F51*FATOR_2016,"n.d.") -> 5.3016839 | K51: =IFERROR(G51*FATOR_2019,"n.d.") -> 5.4965454 | L51: =IFERROR(H51*FATOR_2022,"n.d.") -> 4.0709524 | M51: =IFERROR(I51/G51-1,"n.d.") -> 0.39240506 | N51: =IFERROR(I51/J51-1,"n.d.") -> 0.037406248 | O51: =IFERROR(I51/K51-1,"n.d.") -> 0.00062850948 | P51: =IFERROR(I51/L51-1,"n.d.") -> 0.35103519 | Q51: =IFERROR(F51/PIB_2016,"n.d.") -> 0.0005455131 | R51: =IFERROR(G51/PIB_2019,"n.d.") -> 0.00053456895 | S51: =IFERROR(H51/PIB_2022,"n.d.") -> 0.00035318596 | T51: =IFERROR(I51/PIB_2025,"n.d.") -> 0.00043175974 | U51: FNDE – Dados físicos e financeiros do PNAE (S45) | V51: FNDE – Dados físicos e financeiros do PNAE (S45) | W51: FNDE – Dados físicos e financeiros do PNAE (S45) | X51: Orçamento estimado – MEC/Agência Gov (S45) | Y51: 22/09/2026 | Z51: [OFICIAL] 2016–2022: valores repassados (FNDE). 2025: orçamento estimado do programa (R$ 5,5 bi), não repasse apurado; em 2023 o repasse foi R$ 5,26 bi. Exclui a rede federal (R$ 10,8 mi, 22,2 mi e 34,1 mi pagos em 2016, 2019 e 2022).
A52: 34h | B52: Fies – impacto primário | C52: RTN, linha 4.3.18 (caixa) | D52: Governo Central | E52: R$ bi | F52: ='Políticas afirmativas e apoio'!F35 -> 7.02 | G52: ='Políticas afirmativas e apoio'!G35 -> 1.942 | H52: ='Políticas afirmativas e apoio'!H35 -> 0.726 | I52: ='Políticas afirmativas e apoio'!I35 -> 2.19 | J52: =IFERROR(F52*FATOR_2016,"n.d.") -> 10.882404 | K52: =IFERROR(G52*FATOR_2019,"n.d.") -> 2.7023522 | L52: =IFERROR(H52*FATOR_2022,"n.d.") -> 0.83019985 | M52: =IFERROR(I52/G52-1,"n.d.") -> 0.1277034 | N52: =IFERROR(I52/J52-1,"n.d.") -> -0.7987577 | O52: =IFERROR(I52/K52-1,"n.d.") -> -0.1895949 | P52: =IFERROR(I52/L52-1,"n.d.") -> 1.6379191 | Q52: =IFERROR(F52/PIB_2016,"n.d.") -> 0.0011197374 | R52: =IFERROR(G52/PIB_2019,"n.d.") -> 0.00026281846 | S52: =IFERROR(H52/PIB_2022,"n.d.") -> 7.2026125e-05 | T52: =IFERROR(I52/PIB_2025,"n.d.") -> 0.00017191888 | U52: STN – RTN tab. 2.1 (S04) | V52: STN – RTN tab. 2.1 (S04) | W52: STN – RTN tab. 2.1 (S04) | X52: STN – RTN tab. 2.1 (S04) | Y52: 22/09/2026 | Z52: [OFICIAL] Não é o valor financiado: mede só o efeito primário (subsídio implícito/risco). A concessão de financiamentos (ação 00IG, inversão financeira) não pôde ser obtida no Portal (verificação humana). Nota Técnica Conof/CD 26/2021 (S46): concessão de financiamentos paga, incl. restos a pagar, em R$ de 2021 = 23,8 bi (2016) e 9,7 bi (2019).
A53: 34i | B53: ProUni – renúncia tributária | C53: Demonstrativo de Gastos Tributários – bases efetivas | D53: União | E53: R$ bi | F53: ='Políticas afirmativas e apoio'!F37 -> 2.170886 | G53: ='Políticas afirmativas e apoio'!G37 -> 2.195672 | H53: ='Políticas afirmativas e apoio'!H37 -> 2.827438 | I53: ='Políticas afirmativas e apoio'!I37 -> 3.62178 | J53: =IFERROR(F53*FATOR_2016,"n.d.") -> 3.3653074 | K53: =IFERROR(G53*FATOR_2019,"n.d.") -> 3.0553445 | L53: =IFERROR(H53*FATOR_2022,"n.d.") -> 3.2332488 | M53: =IFERROR(I53/G53-1,"n.d.") -> 0.64950867 | N53: =IFERROR(I53/J53-1,"n.d.") -> 0.076210745 | O53: =IFERROR(I53/K53-1,"n.d.") -> 0.1853917 | P53: =IFERROR(I53/L53-1,"n.d.") -> 0.12016744 | Q53: =IFERROR(F53/PIB_2016,"n.d.") -> 0.00034627098 | R53: =IFERROR(G53/PIB_2019,"n.d.") -> 0.00029714888 | S53: =IFERROR(H53/PIB_2022,"n.d.") -> 0.00028050882 | T53: =IFERROR(I53/PIB_2025,"n.d.") -> 0.00028431615 | U53: RFB – DGT Bases Efetivas 2016 (S47) | V53: RFB – DGT Bases Efetivas 2019 (S47) | W53: RFB – DGT Bases Efetivas 2022 (S47) | X53: RFB – projeção no DGT Bases Efetivas 2022 (S47) | Y53: 22/09/2026 | Z53: [OFICIAL] Renúncia (não é despesa orçamentária). 2025 é projeção da Receita Federal, não valor apurado.
A54: 35 | B54: Desembolsos anuais do BNDES | C54: Fluxo de desembolsos do Sistema BNDES | D54: BNDES (fora da LOA) | E54: R$ bi | F54: ='BNDES, Plano Safra e P&D'!F4 -> 88.3 | G54: ='BNDES, Plano Safra e P&D'!G4 -> 55.314 | H54: ='BNDES, Plano Safra e P&D'!H4 -> 97.5 | I54: ='BNDES, Plano Safra e P&D'!I4 -> 169.7 | J54: =IFERROR(F54*FATOR_2016,"n.d.") -> 136.88266 | K54: =IFERROR(G54*FATOR_2019,"n.d.") -> 76.971117 | L54: =IFERROR(H54*FATOR_2022,"n.d.") -> 111.49378 | M54: =IFERROR(I54/G54-1,"n.d.") -> 2.0679394 | N54: =IFERROR(I54/J54-1,"n.d.") -> 0.23974799 | O54: =IFERROR(I54/K54-1,"n.d.") -> 1.2047231 | P54: =IFERROR(I54/L54-1,"n.d.") -> 0.52205798 | Q54: =IFERROR(F54/PIB_2016,"n.d.") -> 0.014084446 | R54: =IFERROR(G54/PIB_2019,"n.d.") -> 0.00748586 | S54: =IFERROR(H54/PIB_2022,"n.d.") -> 0.00967293 | T54: =IFERROR(I54/PIB_2025,"n.d.") -> 0.013321751 | U54: BNDES (S32) | V54: BNDES via Estado de Minas/Agência Brasil (S20) | W54: BNDES – Relatório Anual 2022 (S32) | X54: BNDES via Agência Brasil (S20) | Y54: 22/09/2026 | Z54: [OFICIAL] Desembolsos do BNDES não são despesa da LOA (funding próprio, FAT, Tesouro).
A55: 36 | B55: Aprovações anuais do BNDES | C55: Operações de crédito aprovadas | D55: BNDES | E55: R$ bi | F55: ='BNDES, Plano Safra e P&D'!F5 -> 79.2 | G55: ='BNDES, Plano Safra e P&D'!G5 -> 63.077 | H55: ='BNDES, Plano Safra e P&D'!H5 -> 132.5 | I55: ='BNDES, Plano Safra e P&D'!I5 -> 237.9 | J55: =IFERROR(F55*FATOR_2016,"n.d.") -> 122.77584 | K55: =IFERROR(G55*FATOR_2019,"n.d.") -> 87.773568 | L55: =IFERROR(H55*FATOR_2022,"n.d.") -> 151.51719 | M55: =IFERROR(I55/G55-1,"n.d.") -> 2.7715808 | N55: =IFERROR(I55/J55-1,"n.d.") -> 0.93767768 | O55: =IFERROR(I55/K55-1,"n.d.") -> 1.7103832 | P55: =IFERROR(I55/L55-1,"n.d.") -> 0.57011887 | Q55: =IFERROR(F55/PIB_2016,"n.d.") -> 0.012632935 | R55: =IFERROR(G55/PIB_2019,"n.d.") -> 0.0085364571 | S55: =IFERROR(H55/PIB_2022,"n.d.") -> 0.013145264 | T55: =IFERROR(I55/PIB_2025,"n.d.") -> 0.018675571 | U55: BNDES via MEON (S32) | V55: S20 | W55: Estimativa a partir de variações BNDES (S32) | X55: S20 | Y55: 22/09/2026 | Z55: [OFICIAL] 2025 por setor (aprovações): infraestrutura 71,4; indústria 71,0; agropecuária 54,3; comércio e serviços 41,2. [2016/2022] 2022 é estimativa (≈ 175/1,32 ≈ 237,9/1,80).
A56: 37 | B56: P&D no orçamento federal (função C&T, empenhado) | C56: Empenhado – P&D no orçamento federal – função Ciência e Tecnologia (19) | D56: União | E56: R$ bi | F56: ='BNDES, Plano Safra e P&D'!F12 -> 6.975 | G56: ='BNDES, Plano Safra e P&D'!G12 -> 6.95 | H56: ='BNDES, Plano Safra e P&D'!H12 -> 9.273 | I56: ='BNDES, Plano Safra e P&D'!I12 -> 35.01 | J56: =IFERROR(F56*FATOR_2016,"n.d.") -> 10.812645 | K56: =IFERROR(G56*FATOR_2019,"n.d.") -> 9.6711368 | L56: =IFERROR(H56*FATOR_2022,"n.d.") -> 10.603916 | M56: =IFERROR(I56/G56-1,"n.d.") -> 4.0374101 | N56: =IFERROR(I56/J56-1,"n.d.") -> 2.2378757 | O56: =IFERROR(I56/K56-1,"n.d.") -> 2.6200501 | P56: =IFERROR(I56/L56-1,"n.d.") -> 2.3016104 | Q56: =IFERROR(F56/PIB_2016,"n.d.") -> 0.0011125596 | R56: =IFERROR(G56/PIB_2019,"n.d.") -> 0.00094057068 | S56: =IFERROR(H56/PIB_2022,"n.d.") -> 0.00091997005 | T56: =IFERROR(I56/PIB_2025,"n.d.") -> 0.002748347 | U56: RREO Anexo 02 (S06) | V56: RREO Anexo 02 (S06) | W56: RREO Anexo 02 (S06) | X56: RREO Anexo 02 (S06) | Y56: 22/09/2026 | Z56: [OFICIAL] —
A57: 38 | B57: P&D realizado (dispêndio nacional, % PIB) | C57: Governo + empresas + ESFL | D57: Brasil | E57: % | F57: ='BNDES, Plano Safra e P&D'!F15 -> 0.0119584 | G57: ='BNDES, Plano Safra e P&D'!G15 -> 0.0115115 | H57: ='BNDES, Plano Safra e P&D'!H15 -> 0.0118873 | I57: ='BNDES, Plano Safra e P&D'!I15 -> 0.011938 | J57: n.a. | K57: n.a. | L57: n.a. | M57: =IFERROR((I57-G57)*100,"n.d.") -> 0.04265 | N57: n.a. | O57: n.a. | P57: n.a. | Q57: n.a. | R57: n.a. | S57: n.a. | T57: n.a. | U57: MCTI via World Bank WDI (S22) | V57: MCTI via World Bank WDI (S22) | W57: MCTI via World Bank WDI (S22) | X57: Último dado: 2023 (S22) | Y57: 22/09/2026 | Z57: [APROXIMAÇÃO] Não há dado para 2025; a coluna 2025 traz o valor de 2023. [2016/2022] 2016 e 2022 são dados observados.
A58: 39 | B58: Valor total do Plano Safra | C58: Ciclo 2019/20 (jul/2019–jun/2020) × ciclo 2025/26 (jul/2025–jun/2026) | D58: União (crédito rural) | E58: R$ bi | F58: ='BNDES, Plano Safra e P&D'!F7 -> 232.88 | G58: ='BNDES, Plano Safra e P&D'!G7 -> 225.59 | H58: ='BNDES, Plano Safra e P&D'!H7 -> 340.88 | I58: ='BNDES, Plano Safra e P&D'!I7 -> 605.2 | J58: =IFERROR(F58*FATOR_2016,"n.d.") -> 361.01057 | K58: =IFERROR(G58*FATOR_2019,"n.d.") -> 313.91536 | L58: =IFERROR(H58*FATOR_2022,"n.d.") -> 389.80513 | M58: =IFERROR(I58/G58-1,"n.d.") -> 1.682743 | N58: =IFERROR(I58/J58-1,"n.d.") -> 0.67640521 | O58: =IFERROR(I58/K58-1,"n.d.") -> 0.92790821 | P58: =IFERROR(I58/L58-1,"n.d.") -> 0.55257064 | Q58: =IFERROR(F58/PIB_2016,"n.d.") -> 0.037145933 | R58: =IFERROR(G58/PIB_2019,"n.d.") -> 0.030529977 | S58: =IFERROR(H58/PIB_2022,"n.d.") -> 0.033818547 | T58: =IFERROR(I58/PIB_2025,"n.d.") -> 0.047509272 | U58: Cálculo: PAP + PSAF (S35) | V58: MAPA (S21) | W58: MAPA (S35) | X58: MAPA + MDA (S21) | Y58: 22/09/2026 | Z58: [APROXIMAÇÃO] Ano-safra não coincide com o ano civil. Valores anunciados (disponibilidade), não contratados. 2025/26 = empresarial 516,2 + agricultura familiar 89,0. [2016/2022] 2016/17 = PAP 202,88 (anúncio; ajustado para 185) + agricultura familiar 30,0. 2022/23 = 340,88 (inclui Pronaf).
A59: 40 | B59: Estoque de empregos formais | C59: Estoque em 31/dez (vínculos celetistas) | D59: Brasil | E59: pessoas | F59: =Emprego!F4 -> 38392395 | G59: =Emprego!G4 -> 39054507 | H59: =Emprego!H4 -> 42716337 | I59: =Emprego!I4 -> 48474348 | J59: n.a. | K59: n.a. | L59: n.a. | M59: =IFERROR(I59/G59-1,"n.d.") -> 0.24119728 | N59: n.a. | O59: n.a. | P59: n.a. | Q59: n.a. | R59: n.a. | S59: n.a. | T59: n.a. | U59: Estimativa sobre Caged (S33) | V59: Caged antigo (S16) | W59: Novo Caged (S33) | X59: Novo Caged (S15) | Y59: 22/09/2026 | Z59: [APROXIMAÇÃO] Quebra metodológica: Caged antigo (2019) × Novo Caged/eSocial (2025). 2025: 48.474.348 exclui estatutários da RAIS; 'estoque total recuperado' = 49.090.182. [2016/2022] 2016 estimado: 462.366 ÷ 1,19% − 462.366 (saldo de dezembro e variação relativa publicados).
A60: 41 | B60: Admissões formais | C60: Fluxo anual (jan–dez) | D60: Brasil | E60: pessoas | F60: =Emprego!F5 -> 14700000 | G60: =Emprego!G5 -> 16197094 | H60: =Emprego!H5 -> 22648395 | I60: =Emprego!I5 -> 26599777 | J60: n.a. | K60: n.a. | L60: n.a. | M60: =IFERROR(I60/G60-1,"n.d.") -> 0.64225614 | N60: n.a. | O60: n.a. | P60: n.a. | Q60: n.a. | R60: n.a. | S60: n.a. | T60: n.a. | U60: Caged via Agência Brasil (S33) | V60: S16 | W60: Novo Caged (S33) | X60: S15 | Y60: 22/09/2026 | Z60: [APROXIMAÇÃO] Novo Caged capta mais movimentações (temporários, intermitentes) – níveis de admissões/desligamentos não são comparáveis diretamente. [2016/2022] 2016 publicado arredondado (14,7 mi).
A61: 42 | B61: Desligamentos formais | C61: Fluxo anual (jan–dez) | D61: Brasil | E61: pessoas | F61: =Emprego!F6 -> 16100000 | G61: =Emprego!G6 -> 15553015 | H61: =Emprego!H6 -> 20610413 | I61: =Emprego!I6 -> 25320279 | J61: n.a. | K61: n.a. | L61: n.a. | M61: =IFERROR(I61/G61-1,"n.d.") -> 0.62799811 | N61: n.a. | O61: n.a. | P61: n.a. | Q61: n.a. | R61: n.a. | S61: n.a. | T61: n.a. | U61: Caged via Agência Brasil (S33) | V61: S16 | W61: Novo Caged (S33) | X61: S15 | Y61: 22/09/2026 | Z61: [APROXIMAÇÃO] Idem. [2016/2022] 2016 publicado arredondado (16,1 mi).
A62: 43 | B62: Saldo anual de empregos formais | C62: Admissões − desligamentos (saldo acumulado no ano) | D62: Brasil | E62: pessoas | F62: =Emprego!F7 -> -1321994 | G62: =Emprego!G7 -> 644079 | H62: =Emprego!H7 -> 2037982 | I62: =Emprego!I7 -> 1279498 | J62: n.a. | K62: n.a. | L62: n.a. | M62: =IFERROR(I62/G62-1,"n.d.") -> 0.98655444 | N62: n.a. | O62: n.a. | P62: n.a. | Q62: n.a. | R62: n.a. | S62: n.a. | T62: n.a. | U62: Caged (S33) | V62: S16 | W62: Novo Caged (S33) | X62: S15 | Y62: 22/09/2026 | Z62: [OFICIAL] Calculado na planilha e idêntico ao publicado (644.079 e 1.279.498). [2016/2022] 2016: saldo publicado (não calculado, pois admissões/desligamentos estão arredondados).
A63: 44 | B63: Taxa média anual de desemprego | C63: PNAD Contínua – média anual | D63: Brasil | E63: % | F63: =Emprego!F8 -> 0.115 | G63: =Emprego!G8 -> 0.119 | H63: =Emprego!H8 -> 0.093 | I63: =Emprego!I8 -> 0.056 | J63: n.a. | K63: n.a. | L63: n.a. | M63: =IFERROR((I63-G63)*100,"n.d.") -> -6.3 | N63: n.a. | O63: n.a. | P63: n.a. | Q63: n.a. | R63: n.a. | S63: n.a. | T63: n.a. | U63: IBGE (S34) | V63: IBGE (S17) | W63: IBGE (S34) | X63: IBGE (S17) | Y63: 22/09/2026 | Z63: [OFICIAL] Publicado. Série atual do SIDRA 4099 (média dos 4 trimestres, após reponderação): 12,0% (2019) e 5,9% (2025).
A64: 45 | B64: Investimentos privados/industriais (anunciados – NIB) | C64: Anúncios plurianuais | D64: Setor privado | E64: R$ bi | F64: ='Invest. privados e industriais'!F5 -> não localizado após busca | G64: ='Invest. privados e industriais'!G5 -> não localizado após busca | H64: ='Invest. privados e industriais'!H5 -> não localizado após busca | I64: ='Invest. privados e industriais'!I5 -> 2200 | J64: =IFERROR(F64*FATOR_2016,"n.d.") -> n.d. | K64: =IFERROR(G64*FATOR_2019,"n.d.") -> n.d. | L64: =IFERROR(H64*FATOR_2022,"n.d.") -> n.d. | M64: =IFERROR(I64/G64-1,"n.d.") -> n.d. | N64: =IFERROR(I64/J64-1,"n.d.") -> n.d. | O64: =IFERROR(I64/K64-1,"n.d.") -> n.d. | P64: =IFERROR(I64/L64-1,"n.d.") -> n.d. | Q64: =IFERROR(F64/PIB_2016,"n.d.") -> n.d. | R64: =IFERROR(G64/PIB_2019,"n.d.") -> n.d. | S64: =IFERROR(H64/PIB_2022,"n.d.") -> n.d. | T64: =IFERROR(I64/PIB_2025,"n.d.") -> 0.1727039 | U64: Programa inexistente | V64: Sem programa/painel equivalente em 2019 | W64: Programa inexistente | X64: MDIC (S26) | Y64: 22/09/2026 | Z64: [APROXIMAÇÃO] Anúncio ≠ contratado ≠ realizado. Valor acumulado de anúncios de 2024 até fev/2025 para vários anos; não é fluxo de 2025.
A65: 45b | B65: Investimento realizado – FBCF | C65: Contas Nacionais, valores correntes | D65: Brasil (público + privado) | E65: R$ bi | F65: ='Invest. privados e industriais'!F4 -> 973.27 | G65: ='Invest. privados e industriais'!G4 -> 1143.186 | H65: ='Invest. privados e industriais'!H4 -> 1794.223 | I65: ='Invest. privados e industriais'!I4 -> 2145.05 | J65: =IFERROR(F65*FATOR_2016,"n.d.") -> 1508.7631 | K65: =IFERROR(G65*FATOR_2019,"n.d.") -> 1590.7782 | L65: =IFERROR(H65*FATOR_2022,"n.d.") -> 2051.7406 | M65: =IFERROR(I65/G65-1,"n.d.") -> 0.87637882 | N65: =IFERROR(I65/J65-1,"n.d.") -> 0.42172748 | O65: =IFERROR(I65/K65-1,"n.d.") -> 0.34842812 | P65: =IFERROR(I65/L65-1,"n.d.") -> 0.045478175 | Q65: =IFERROR(F65/PIB_2016,"n.d.") -> 0.15524314 | R65: =IFERROR(G65/PIB_2019,"n.d.") -> 0.15471183 | S65: =IFERROR(H65/PIB_2022,"n.d.") -> 0.17800404 | T65: =IFERROR(I65/PIB_2025,"n.d.") -> 0.16839023 | U65: IBGE/SIDRA 1846 (S01) | V65: IBGE/SIDRA 1846 (S01) | W65: IBGE/SIDRA 1846 (S01) | X65: IBGE/SIDRA 1846 (S01) | Y65: 22/09/2026 | Z65: [OFICIAL] Investimento efetivamente realizado; inclui governo e estatais – o IBGE não separa FBCF privada na série trimestral.
A66: 46 | B66: Investimento estrangeiro direto | C66: Ingressos líquidos, BPM6, fluxo anual | D66: Brasil | E66: US$ bi | F66: ='Comércio exterior'!F8 -> 74.2946 | G66: ='Comércio exterior'!G8 -> 69.1744 | H66: ='Comércio exterior'!H8 -> 75.5011 | I66: ='Comércio exterior'!I8 -> 77.6761 | J66: n.a. (US$) | K66: n.a. (US$) | L66: n.a. (US$) | M66: =IFERROR(I66/G66-1,"n.d.") -> 0.1229024 | N66: n.a. | O66: n.a. | P66: n.a. | Q66: =IFERROR(F66/(PIB_2016/PTAX_2016),"n.d.") -> 0.041359594 | R66: =IFERROR(G66/(PIB_2019/PTAX_2019),"n.d.") -> 0.036932458 | S66: =IFERROR(H66/(PIB_2022/PTAX_2022),"n.d.") -> 0.038686319 | T66: =IFERROR(I66/(PIB_2025/PTAX_2025),"n.d.") -> 0.034073351 | U66: BCB SGS (S08) | V66: BCB SGS 22885 (S08) | W66: BCB SGS (S08) | X66: S08 | Y66: 22/09/2026 | Z66: [OFICIAL] 2019 divulgado originalmente: US$ 78,559 bi (S27); série atual revisada: 69,17. 2025: 3,41% do PIB segundo o BCB.
A67: 47 | B67: Exportações | C67: FOB, fluxo anual | D67: Brasil | E67: US$ bi | F67: ='Comércio exterior'!F4 -> 179.52613 | G67: ='Comércio exterior'!G4 -> 221.12681 | H67: ='Comércio exterior'!H4 -> 334.13604 | I67: ='Comércio exterior'!I4 -> 348.27846 | J67: n.a. (US$) | K67: n.a. (US$) | L67: n.a. (US$) | M67: =IFERROR(I67/G67-1,"n.d.") -> 0.57501692 | N67: n.a. | O67: n.a. | P67: n.a. | Q67: =IFERROR(F67/(PIB_2016/PTAX_2016),"n.d.") -> 0.09994169 | R67: =IFERROR(G67/(PIB_2019/PTAX_2019),"n.d.") -> 0.11806039 | S67: =IFERROR(H67/(PIB_2022/PTAX_2022),"n.d.") -> 0.17120934 | T67: =IFERROR(I67/(PIB_2025/PTAX_2025),"n.d.") -> 0.15277562 | U67: Comex Stat (S18) | V67: Comex Stat – série revisada (S18) | W67: Comex Stat (S18) | X67: Comex Stat (S18) | Y67: 22/09/2026 | Z67: [OFICIAL] Divulgação original 2019: US$ 224,01 bi. Revisão posterior da Secex (ajustes de registros, ex.: plataformas de petróleo/Repetro).
A68: 48 | B68: Importações | C68: FOB, fluxo anual | D68: Brasil | E68: US$ bi | F68: ='Comércio exterior'!F5 -> 139.32136 | G68: ='Comércio exterior'!G5 -> 185.92797 | H68: ='Comércio exterior'!H5 -> 272.61069 | I68: ='Comércio exterior'!I5 -> 280.20843 | J68: n.a. (US$) | K68: n.a. (US$) | L68: n.a. (US$) | M68: =IFERROR(I68/G68-1,"n.d.") -> 0.5070806 | N68: n.a. | O68: n.a. | P68: n.a. | Q68: =IFERROR(F68/(PIB_2016/PTAX_2016),"n.d.") -> 0.077559807 | R68: =IFERROR(G68/(PIB_2019/PTAX_2019),"n.d.") -> 0.099267603 | S68: =IFERROR(H68/(PIB_2022/PTAX_2022),"n.d.") -> 0.13968411 | T68: =IFERROR(I68/(PIB_2025/PTAX_2025),"n.d.") -> 0.12291606 | U68: Comex Stat (S18) | V68: S18 | W68: Comex Stat (S18) | X68: S18 | Y68: 22/09/2026 | Z68: [OFICIAL] Divulgação original 2019: US$ 177,34 bi; 2025 divulgado US$ 280,4 bi.
A69: 49 | B69: Saldo da balança comercial | C69: Exportações − importações | D69: Brasil | E69: US$ bi | F69: ='Comércio exterior'!F6 -> 40.204772 | G69: ='Comércio exterior'!G6 -> 35.19884 | H69: ='Comércio exterior'!H6 -> 61.525351 | I69: ='Comércio exterior'!I6 -> 68.070029 | J69: n.a. (US$) | K69: n.a. (US$) | L69: n.a. (US$) | M69: =IFERROR(I69/G69-1,"n.d.") -> 0.93387136 | N69: n.a. | O69: n.a. | P69: n.a. | Q69: =IFERROR(F69/(PIB_2016/PTAX_2016),"n.d.") -> 0.022381883 | R69: =IFERROR(G69/(PIB_2019/PTAX_2019),"n.d.") -> 0.018792786 | S69: =IFERROR(H69/(PIB_2022/PTAX_2022),"n.d.") -> 0.031525228 | T69: =IFERROR(I69/(PIB_2025/PTAX_2025),"n.d.") -> 0.029859558 | U69: Cálculo S18 | V69: Cálculo S18 | W69: Cálculo S18 | X69: Cálculo S18 | Y69: 22/09/2026 | Z69: [OFICIAL] Original 2019: US$ 46,7 bi; revisado: US$ 35,2 bi. 2025 divulgado: US$ 68,3 bi.
A70: 50 | B70: Investimentos federais em infraestrutura | C70: Soma das funções Transporte, Saneamento, Urbanismo, Habitação, Energia e Comunicações – pago total no ano (RTN) | D70: Governo Central | E70: R$ bi | F70: ='Infraestrutura federal'!F4 -> 15.874 | G70: ='Infraestrutura federal'!G4 -> 12.364 | H70: ='Infraestrutura federal'!H4 -> 13.376 | I70: ='Infraestrutura federal'!I4 -> 20.816 | J70: =IFERROR(F70*FATOR_2016,"n.d.") -> 24.607874 | K70: =IFERROR(G70*FATOR_2019,"n.d.") -> 17.204883 | L70: =IFERROR(H70*FATOR_2022,"n.d.") -> 15.295803 | M70: =IFERROR(I70/G70-1,"n.d.") -> 0.68359754 | N70: =IFERROR(I70/J70-1,"n.d.") -> -0.15409191 | O70: =IFERROR(I70/K70-1,"n.d.") -> 0.20988909 | P70: =IFERROR(I70/L70-1,"n.d.") -> 0.36089616 | Q70: =IFERROR(F70/PIB_2016,"n.d.") -> 0.0025320102 | R70: =IFERROR(G70/PIB_2019,"n.d.") -> 0.0016732685 | S70: =IFERROR(H70/PIB_2022,"n.d.") -> 0.0013270268 | T70: =IFERROR(I70/PIB_2025,"n.d.") -> 0.0016340929 | U70: Cálculo RTN tab. 2.3 (S04) | V70: Cálculo STN – RTN tab. 2.3 (S04) | W70: Cálculo RTN tab. 2.3 (S04) | X70: S04 | Y70: 22/09/2026 | Z70: [ESTIMADO] Agregação própria (mesma fonte e conceito). 2019: 7,834+1,157+3,176+0,047+0,062+0,089; 2025: 13,607+0,612+5,965+0,552+0,030+0,049. [2016/2022] 2016: 10,787+1,756+3,139+0,105+0,042+0,045; 2022: 7,147+0,342+5,622+0,025+0,056+0,184.
A71: 51 | B71: Investimentos do PAC | C71: 2025: dotação OGU do Novo PAC (100% empenhada) | D71: União | E71: R$ bi | F71: ='Infraestrutura federal'!F5 -> 42 | G71: ='Infraestrutura federal'!G5 -> não localizado após busca | H71: ='Infraestrutura federal'!H5 -> não se aplica – PAC extinto (Novo PAC só em 2023) | I71: ='Infraestrutura federal'!I5 -> 49.8 | J71: =IFERROR(F71*FATOR_2016,"n.d.") -> 65.108399 | K71: =IFERROR(G71*FATOR_2019,"n.d.") -> n.d. | L71: =IFERROR(H71*FATOR_2022,"n.d.") -> n.d. | M71: =IFERROR(I71/G71-1,"n.d.") -> n.d. | N71: =IFERROR(I71/J71-1,"n.d.") -> -0.23512172 | O71: =IFERROR(I71/K71-1,"n.d.") -> n.d. | P71: =IFERROR(I71/L71-1,"n.d.") -> n.d. | Q71: =IFERROR(F71/PIB_2016,"n.d.") -> 0.0066992837 | R71: =IFERROR(G71/PIB_2019,"n.d.") -> n.d. | S71: =IFERROR(H71/PIB_2022,"n.d.") -> n.d. | T71: =IFERROR(I71/PIB_2025,"n.d.") -> 0.0039093882 | U71: Senado (S39) – dotação aproximada | V71: Ver tentativas na aba 'Fontes e metodologia' | W71: — | X71: Casa Civil via Agência Gov (S23) | Y71: 22/09/2026 | Z71: [APROXIMAÇÃO] 2025 é dotação/empenho, não pagamento. Novo PAC (todas as fontes, inclusive privadas e estatais) somou R$ 944,8 bi executados de 2023 a ago/2025. [2016/2022] 2016: orçamento previsto do PAC ≈ R$ 42 bi (imprensa).
A72: 52 | B72: Investimentos em rodovias (empenhado) | C72: Empenhado – Rodovias – subfunção Transporte Rodoviário (782) | D72: União | E72: R$ bi | F72: ='Infraestrutura federal'!F9 -> 6.088 | G72: ='Infraestrutura federal'!G9 -> 6.31 | H72: ='Infraestrutura federal'!H9 -> 8.865 | I72: ='Infraestrutura federal'!I9 -> 12.65 | J72: =IFERROR(F72*FATOR_2016,"n.d.") -> 9.4376174 | K72: =IFERROR(G72*FATOR_2019,"n.d.") -> 8.7805573 | L72: =IFERROR(H72*FATOR_2022,"n.d.") -> 10.137358 | M72: =IFERROR(I72/G72-1,"n.d.") -> 1.0047544 | N72: =IFERROR(I72/J72-1,"n.d.") -> 0.34038067 | O72: =IFERROR(I72/K72-1,"n.d.") -> 0.44068304 | P72: =IFERROR(I72/L72-1,"n.d.") -> 0.24785969 | Q72: =IFERROR(F72/PIB_2016,"n.d.") -> 0.00097107712 | R72: =IFERROR(G72/PIB_2019,"n.d.") -> 0.00085395698 | S72: =IFERROR(H72/PIB_2022,"n.d.") -> 0.00087949256 | T72: =IFERROR(I72/PIB_2025,"n.d.") -> 0.00099304741 | U72: RREO Anexo 02 (S06) | V72: RREO Anexo 02 (S06) | W72: RREO Anexo 02 (S06) | X72: RREO Anexo 02 (S06) | Y72: 22/09/2026 | Z72: [OFICIAL] —
A73: 53 | B73: Investimentos em ferrovias (empenhado) | C73: Empenhado – Ferrovias – subfunção Transporte Ferroviário (783) | D73: União | E73: R$ bi | F73: ='Infraestrutura federal'!F13 -> 1.036 | G73: ='Infraestrutura federal'!G13 -> 0.51 | H73: ='Infraestrutura federal'!H13 -> 0.238 | I73: ='Infraestrutura federal'!I13 -> 0.06 | J73: =IFERROR(F73*FATOR_2016,"n.d.") -> 1.6060072 | K73: =IFERROR(G73*FATOR_2019,"n.d.") -> 0.70968054 | L73: =IFERROR(H73*FATOR_2022,"n.d.") -> 0.27215918 | M73: =IFERROR(I73/G73-1,"n.d.") -> -0.88235294 | N73: =IFERROR(I73/J73-1,"n.d.") -> -0.96264027 | O73: =IFERROR(I73/K73-1,"n.d.") -> -0.91545492 | P73: =IFERROR(I73/L73-1,"n.d.") -> -0.77954078 | Q73: =IFERROR(F73/PIB_2016,"n.d.") -> 0.000165249 | R73: =IFERROR(G73/PIB_2019,"n.d.") -> 6.9020295e-05 | S73: =IFERROR(H73/PIB_2022,"n.d.") -> 2.361187e-05 | T73: =IFERROR(I73/PIB_2025,"n.d.") -> 4.7101063e-06 | U73: RREO Anexo 02 (S06) | V73: RREO Anexo 02 (S06) | W73: RREO Anexo 02 (S06) | X73: RREO Anexo 02 (S06) | Y73: 22/09/2026 | Z73: [OFICIAL] —
A74: 54 | B74: Investimentos em portos (empenhado) | C74: Empenhado – Portos – subfunção Transporte Hidroviário/Aquaviário (784) | D74: União | E74: R$ bi | F74: ='Infraestrutura federal'!F17 -> 0.585 | G74: ='Infraestrutura federal'!G17 -> 0.87 | H74: ='Infraestrutura federal'!H17 -> 0.192 | I74: ='Infraestrutura federal'!I17 -> 0.45 | J74: =IFERROR(F74*FATOR_2016,"n.d.") -> 0.90686698 | K74: =IFERROR(G74*FATOR_2019,"n.d.") -> 1.2106315 | L74: =IFERROR(H74*FATOR_2022,"n.d.") -> 0.21955698 | M74: =IFERROR(I74/G74-1,"n.d.") -> -0.48275862 | N74: =IFERROR(I74/J74-1,"n.d.") -> -0.5037861 | O74: =IFERROR(I74/K74-1,"n.d.") -> -0.62829317 | P74: =IFERROR(I74/L74-1,"n.d.") -> 1.0495818 | Q74: =IFERROR(F74/PIB_2016,"n.d.") -> 9.3311451e-05 | R74: =IFERROR(G74/PIB_2019,"n.d.") -> 0.0001177405 | S74: =IFERROR(H74/PIB_2022,"n.d.") -> 1.9048231e-05 | T74: =IFERROR(I74/PIB_2025,"n.d.") -> 3.5325797e-05 | U74: RREO Anexo 02 (S06) | V74: RREO Anexo 02 (S06) | W74: RREO Anexo 02 (S06) | X74: RREO Anexo 02 (S06) | Y74: 22/09/2026 | Z74: [OFICIAL] —
A75: 55 | B75: Investimentos em aeroportos (empenhado) | C75: Empenhado – Aeroportos – subfunção Transporte Aéreo (781) | D75: União | E75: R$ bi | F75: ='Infraestrutura federal'!F21 -> 0.065 | G75: ='Infraestrutura federal'!G21 -> 0.16 | H75: ='Infraestrutura federal'!H21 -> 0.121 | I75: ='Infraestrutura federal'!I21 -> 0.19 | J75: =IFERROR(F75*FATOR_2016,"n.d.") -> 0.100763 | K75: =IFERROR(G75*FATOR_2019,"n.d.") -> 0.22264488 | L75: =IFERROR(H75*FATOR_2022,"n.d.") -> 0.13836664 | M75: =IFERROR(I75/G75-1,"n.d.") -> 0.1875 | N75: =IFERROR(I75/J75-1,"n.d.") -> 0.88561281 | O75: =IFERROR(I75/K75-1,"n.d.") -> -0.14662307 | P75: =IFERROR(I75/L75-1,"n.d.") -> 0.37316334 | Q75: =IFERROR(F75/PIB_2016,"n.d.") -> 1.0367939e-05 | R75: =IFERROR(G75/PIB_2019,"n.d.") -> 2.1653426e-05 | S75: =IFERROR(H75/PIB_2022,"n.d.") -> 1.2004354e-05 | T75: =IFERROR(I75/PIB_2025,"n.d.") -> 1.4915337e-05 | U75: RREO Anexo 02 (S06) | V75: RREO Anexo 02 (S06) | W75: RREO Anexo 02 (S06) | X75: RREO Anexo 02 (S06) | Y75: 22/09/2026 | Z75: [OFICIAL] —
A76: 56a | B76: Saneamento (empenhado) | C76: Empenhado – Saneamento (função 17) | D76: União | E76: R$ bi | F76: ='Infraestrutura federal'!F25 -> 0.564 | G76: ='Infraestrutura federal'!G25 -> 0.51 | H76: ='Infraestrutura federal'!H25 -> 0.763 | I76: ='Infraestrutura federal'!I25 -> 0.79 | J76: =IFERROR(F76*FATOR_2016,"n.d.") -> 0.87431278 | K76: =IFERROR(G76*FATOR_2019,"n.d.") -> 0.70968054 | L76: =IFERROR(H76*FATOR_2022,"n.d.") -> 0.87251031 | M76: =IFERROR(I76/G76-1,"n.d.") -> 0.54901961 | N76: =IFERROR(I76/J76-1,"n.d.") -> -0.096433205 | O76: =IFERROR(I76/K76-1,"n.d.") -> 0.11317692 | P76: =IFERROR(I76/L76-1,"n.d.") -> -0.094566573 | Q76: =IFERROR(F76/PIB_2016,"n.d.") -> 8.9961809e-05 | R76: =IFERROR(G76/PIB_2019,"n.d.") -> 6.9020295e-05 | S76: =IFERROR(H76/PIB_2022,"n.d.") -> 7.5696878e-05 | T76: =IFERROR(I76/PIB_2025,"n.d.") -> 6.20164e-05 | U76: RREO Anexo 02 (S06) | V76: RREO Anexo 02 (S06) | W76: RREO Anexo 02 (S06) | X76: RREO Anexo 02 (S06) | Y76: 22/09/2026 | Z76: [OFICIAL] —
A77: 56b | B77: Mobilidade urbana (empenhado) | C77: Empenhado – Mobilidade – subfunção Transportes Coletivos Urbanos (453) | D77: União | E77: R$ bi | F77: ='Infraestrutura federal'!F30 -> 0.834 | G77: ='Infraestrutura federal'!G30 -> 0.58 | H77: ='Infraestrutura federal'!H30 -> 0.593 | I77: ='Infraestrutura federal'!I30 -> 0.86 | J77: =IFERROR(F77*FATOR_2016,"n.d.") -> 1.2928668 | K77: =IFERROR(G77*FATOR_2019,"n.d.") -> 0.80708767 | L77: =IFERROR(H77*FATOR_2022,"n.d.") -> 0.6781109 | M77: =IFERROR(I77/G77-1,"n.d.") -> 0.48275862 | N77: =IFERROR(I77/J77-1,"n.d.") -> -0.33481159 | O77: =IFERROR(I77/K77-1,"n.d.") -> 0.065559576 | P77: =IFERROR(I77/L77-1,"n.d.") -> 0.26822914 | Q77: =IFERROR(F77/PIB_2016,"n.d.") -> 0.00013302863 | R77: =IFERROR(G77/PIB_2019,"n.d.") -> 7.8493669e-05 | S77: =IFERROR(H77/PIB_2022,"n.d.") -> 5.8831256e-05 | T77: =IFERROR(I77/PIB_2025,"n.d.") -> 6.7511524e-05 | U77: RREO Anexo 02 (S06) | V77: RREO Anexo 02 (S06) | W77: RREO Anexo 02 (S06) | X77: RREO Anexo 02 (S06) | Y77: 22/09/2026 | Z77: [OFICIAL] —
A79: Notas metodológicas
A80: 1. 'Variação nominal 2019→2025' para taxas/percentuais = diferença em p.p.
A81: 2. Linhas de LOA: 'previsto' = dotação inicial; 'empenhado' e 'pago' são estágios de execução – não somar.
A82: 3. A classificação do dado aparece entre colchetes no início das observações e na cor da linha.
A83: 4. Valores nominais do próprio ano (R$ bilhões, salvo indicação). Correção para R$ de dez/2025 pelo IPCA: fator = índice dez/2025 ÷ índice de dezembro do ano (FATOR_2016, FATOR_2019, FATOR_2022 na aba 'Resumo executivo').
A84: 5. Colunas de variação: para valores em R$ = variação REAL (IPCA); para US$ e pessoas = variação nominal; para taxas e % = diferença em pontos percentuais (p.p.).
A85: 6. % do PIB com o PIB anual do IBGE (SIDRA 1846) de cada ano; valores em US$ usam o PIB convertido pela PTAX média anual.
A86: 7. 'n.a.' = não se aplica; 'n.d.' = não disponível (algum ano 'não localizado após busca'). Azul = dado digitado da fonte; preto = fórmula; verde = vínculo com outra aba.
A87: 8. Cor da linha = classificação do dado em 2019/2025; células de 2016/2022 com cor própria quando a classificação difere (ex.: estimado, não localizado).
A88: 9. Períodos 2016→2019, 2019→2022 e 2022→2025 correspondem aproximadamente aos mandatos Temer, Bolsonaro e Lula III (até 2025); 2016 inclui o governo Dilma até maio.

Sheet PIB setorial
A1: PIB setorial – valor adicionado por atividade (valores correntes)
A2: IBGE, Contas Nacionais Trimestrais (SIDRA 1846), soma dos quatro trimestres de cada ano. Participações ao final.
A3: Código | B3: Indicador | C3: Conceito / estágio | D3: Âmbito | E3: Unidade | F3: Brasil 2016 | G3: Brasil 2019 | H3: Brasil 2022 | I3: Brasil 2025 | J3: 2016 em R$ de dez/2025 | K3: 2019 em R$ de dez/2025 | L3: 2022 em R$ de dez/2025 | M3: Variação 2016→2019 | N3: Variação 2019→2022 | O3: Variação 2022→2025 | P3: Variação 2016→2025 | Q3: Diferença absoluta 2025−2016 (nominal) | R3: Diferença absoluta 2025−2019 (nominal) | S3: 2016 % do PIB | T3: 2019 % do PIB | U3: 2022 % do PIB | V3: 2025 % do PIB | W3: Fonte 2016 | X3: Fonte 2019 | Y3: Fonte 2022 | Z3: Fonte 2025 | AA3: Classificação do dado | AB3: Observações metodológicas
A4: 1 | B4: PIB total | C4: PIB a preços de mercado, valores correntes (fluxo anual) | D4: Brasil | E4: R$ bi | F4: 6269.327 | G4: 7389.131 | H4: 10079.676 | I4: 12738.566 | J4: =IFERROR(F4*FATOR_2016,"n.d.") -> 9718.7105 | K4: =IFERROR(G4*FATOR_2019,"n.d.") -> 10282.201 | L4: =IFERROR(H4*FATOR_2022,"n.d.") -> 11526.371 | M4: =IFERROR(K4/J4-1,"n.d.") -> 0.057979958 | N4: =IFERROR(L4/K4-1,"n.d.") -> 0.12100233 | O4: =IFERROR(I4/L4-1,"n.d.") -> 0.10516708 | P4: =IFERROR(I4/J4-1,"n.d.") -> 0.31072594 | Q4: =IFERROR(I4-F4,"n.d.") -> 6469.239 | R4: =IFERROR(I4-G4,"n.d.") -> 5349.435 | S4: =IFERROR(F4/PIB_2016,"n.d.") -> 1 | T4: =IFERROR(G4/PIB_2019,"n.d.") -> 1 | U4: =IFERROR(H4/PIB_2022,"n.d.") -> 1 | V4: =IFERROR(I4/PIB_2025,"n.d.") -> 1 | W4: IBGE/SIDRA 1846 (S01) | X4: IBGE/SIDRA 1846 (S01) | Y4: IBGE/SIDRA 1846 (S01) | Z4: IBGE/SIDRA 1846 (S01) | AA4: OFICIAL | AB4: Soma dos 4 trimestres. Divulgação original de 2025: R$ 12,7 tri (S02); Tesouro usa R$ 12.733,6 bi (série anterior).
A5: 1.1 | B5: Valor adicionado bruto (VAB) a preços básicos | C5: Soma do VAB das atividades | D5: Brasil | E5: R$ bi | F5: 5419.822 | G5: 6356.683 | H5: 8736.476 | I5: 10951.982 | J5: =IFERROR(F5*FATOR_2016,"n.d.") -> 8401.8079 | K5: =IFERROR(G5*FATOR_2019,"n.d.") -> 8845.5181 | L5: =IFERROR(H5*FATOR_2022,"n.d.") -> 9990.3871 | M5: =IFERROR(K5/J5-1,"n.d.") -> 0.052811276 | N5: =IFERROR(L5/K5-1,"n.d.") -> 0.12942928 | O5: =IFERROR(I5/L5-1,"n.d.") -> 0.096252013 | P5: =IFERROR(I5/J5-1,"n.d.") -> 0.30352683 | Q5: =IFERROR(I5-F5,"n.d.") -> 5532.16 | R5: =IFERROR(I5-G5,"n.d.") -> 4595.299 | S5: =IFERROR(F5/PIB_2016,"n.d.") -> 0.86449821 | T5: =IFERROR(G5/PIB_2019,"n.d.") -> 0.86027477 | U5: =IFERROR(H5/PIB_2022,"n.d.") -> 0.86674175 | V5: =IFERROR(I5/PIB_2025,"n.d.") -> 0.85974999 | W5: IBGE/SIDRA 1846 (S01) | X5: IBGE/SIDRA 1846 (S01) | Y5: IBGE/SIDRA 1846 (S01) | Z5: IBGE/SIDRA 1846 (S01) | AA5: OFICIAL | AB5: Base para participações setoriais usadas pelo IBGE.
A6: 1.2 | B6: Impostos líquidos sobre produtos | C6: PIB − VAB | D6: Brasil | E6: R$ bi | F6: 139.32136 | G6: 1032.447 | H6: 272.61069 | I6: 1786.584 | J6: =IFERROR(F6*FATOR_2016,"n.d.") -> 215.97596 | K6: =IFERROR(G6*FATOR_2019,"n.d.") -> 1436.6815 | L6: =IFERROR(H6*FATOR_2022,"n.d.") -> 311.7374 | M6: =IFERROR(K6/J6-1,"n.d.") -> 5.6520433 | N6: =IFERROR(L6/K6-1,"n.d.") -> -0.78301565 | O6: =IFERROR(I6/L6-1,"n.d.") -> 4.7310544 | P6: =IFERROR(I6/J6-1,"n.d.") -> 7.2721427 | Q6: =IFERROR(I6-F6,"n.d.") -> 1647.2626 | R6: =IFERROR(I6-G6,"n.d.") -> 754.137 | S6: =IFERROR(F6/PIB_2016,"n.d.") -> 0.022222698 | T6: =IFERROR(G6/PIB_2019,"n.d.") -> 0.13972509 | U6: =IFERROR(H6/PIB_2022,"n.d.") -> 0.02704558 | V6: =IFERROR(I6/PIB_2025,"n.d.") -> 0.14025001 | W6: Comex Stat (S18) | X6: IBGE/SIDRA 1846 (S01) | Y6: Comex Stat (S18) | Z6: IBGE/SIDRA 1846 (S01) | AA6: OFICIAL | AB6: —
A7: 2 | B7: PIB da agropecuária (VAB) | C7: VAB – Agropecuária total | D7: Brasil | E7: R$ bi | F7: 306.654 | G7: 310.714 | H7: 581.343 | I7: 775.297 | J7: =IFERROR(F7*FATOR_2016,"n.d.") -> 475.37502 | K7: =IFERROR(G7*FATOR_2019,"n.d.") -> 432.368 | L7: =IFERROR(H7*FATOR_2022,"n.d.") -> 664.78081 | M7: =IFERROR(K7/J7-1,"n.d.") -> -0.090469672 | N7: =IFERROR(L7/K7-1,"n.d.") -> 0.53753473 | O7: =IFERROR(I7/L7-1,"n.d.") -> 0.16624455 | P7: =IFERROR(I7/J7-1,"n.d.") -> 0.63091657 | Q7: =IFERROR(I7-F7,"n.d.") -> 468.643 | R7: =IFERROR(I7-G7,"n.d.") -> 464.583 | S7: =IFERROR(F7/PIB_2016,"n.d.") -> 0.048913384 | T7: =IFERROR(G7/PIB_2019,"n.d.") -> 0.042050141 | U7: =IFERROR(H7/PIB_2022,"n.d.") -> 0.05767477 | V7: =IFERROR(I7/PIB_2025,"n.d.") -> 0.060862188 | W7: IBGE/SIDRA 1846 (S01) | X7: IBGE/SIDRA 1846 (S01) | Y7: IBGE/SIDRA 1846 (S01) | Z7: IBGE/SIDRA 1846 (S01) | AA7: OFICIAL | AB7: —
A8: 3 | B8: PIB da indústria (VAB) | C8: VAB – Indústria total | D8: Brasil | E8: R$ bi | F8: 1150.72 | G8: 1385.804 | H8: 2300.127 | I8: 2566.814 | J8: =IFERROR(F8*FATOR_2016,"n.d.") -> 1783.8461 | K8: =IFERROR(G8*FATOR_2019,"n.d.") -> 1928.3885 | L8: =IFERROR(H8*FATOR_2022,"n.d.") -> 2630.2549 | M8: =IFERROR(K8/J8-1,"n.d.") -> 0.081028506 | N8: =IFERROR(L8/K8-1,"n.d.") -> 0.36396527 | O8: =IFERROR(I8/L8-1,"n.d.") -> -0.024119693 | P8: =IFERROR(I8/J8-1,"n.d.") -> 0.43892121 | Q8: =IFERROR(I8-F8,"n.d.") -> 1416.094 | R8: =IFERROR(I8-G8,"n.d.") -> 1181.01 | S8: =IFERROR(F8/PIB_2016,"n.d.") -> 0.18354761 | T8: =IFERROR(G8/PIB_2019,"n.d.") -> 0.18754628 | U8: =IFERROR(H8/PIB_2022,"n.d.") -> 0.22819454 | V8: =IFERROR(I8/PIB_2025,"n.d.") -> 0.20149945 | W8: IBGE/SIDRA 1846 (S01) | X8: IBGE/SIDRA 1846 (S01) | Y8: IBGE/SIDRA 1846 (S01) | Z8: IBGE/SIDRA 1846 (S01) | AA8: OFICIAL | AB8: Extrativa + transformação + eletricidade/gás/água/esgoto + construção.
A9: 3.1 | B9: Indústrias extrativas | C9: VAB | D9: Brasil | E9: R$ bi | F9: 55.575 | G9: 182.817 | H9: 476.676 | I9: 403.599 | J9: =IFERROR(F9*FATOR_2016,"n.d.") -> 86.152363 | K9: =IFERROR(G9*FATOR_2019,"n.d.") -> 254.39543 | L9: =IFERROR(H9*FATOR_2022,"n.d.") -> 545.09138 | M9: =IFERROR(K9/J9-1,"n.d.") -> 1.9528549 | N9: =IFERROR(L9/K9-1,"n.d.") -> 1.1426933 | O9: =IFERROR(I9/L9-1,"n.d.") -> -0.25957553 | P9: =IFERROR(I9/J9-1,"n.d.") -> 3.6847119 | Q9: =IFERROR(I9-F9,"n.d.") -> 348.024 | R9: =IFERROR(I9-G9,"n.d.") -> 220.782 | S9: =IFERROR(F9/PIB_2016,"n.d.") -> 0.0088645879 | T9: =IFERROR(G9/PIB_2019,"n.d.") -> 0.02474134 | U9: =IFERROR(H9/PIB_2022,"n.d.") -> 0.047290806 | V9: =IFERROR(I9/PIB_2025,"n.d.") -> 0.031683237 | W9: IBGE/SIDRA 1846 (S01) | X9: IBGE/SIDRA 1846 (S01) | Y9: IBGE/SIDRA 1846 (S01) | Z9: IBGE/SIDRA 1846 (S01) | AA9: OFICIAL | AB9: —
A10: 3.2 | B10: Indústrias de transformação | C10: VAB | D10: Brasil | E10: R$ bi | F10: 676.238 | G10: 763.482 | H10: 1317.826 | I10: 1499.618 | J10: =IFERROR(F10*FATOR_2016,"n.d.") -> 1048.3041 | K10: =IFERROR(G10*FATOR_2019,"n.d.") -> 1062.4085 | L10: =IFERROR(H10*FATOR_2022,"n.d.") -> 1506.9682 | M10: =IFERROR(K10/J10-1,"n.d.") -> 0.013454436 | N10: =IFERROR(L10/K10-1,"n.d.") -> 0.41844525 | O10: =IFERROR(I10/L10-1,"n.d.") -> -0.0048775051 | P10: =IFERROR(I10/J10-1,"n.d.") -> 0.43051807 | Q10: =IFERROR(I10-F10,"n.d.") -> 823.38 | R10: =IFERROR(I10-G10,"n.d.") -> 736.136 | S10: =IFERROR(F10/PIB_2016,"n.d.") -> 0.10786453 | T10: =IFERROR(G10/PIB_2019,"n.d.") -> 0.10332501 | U10: =IFERROR(H10/PIB_2022,"n.d.") -> 0.13074091 | V10: =IFERROR(I10/PIB_2025,"n.d.") -> 0.11772267 | W10: IBGE/SIDRA 1846 (S01) | X10: IBGE/SIDRA 1846 (S01) | Y10: IBGE/SIDRA 1846 (S01) | Z10: IBGE/SIDRA 1846 (S01) | AA10: OFICIAL | AB10: —
A11: 3.3 | B11: Eletricidade e gás, água, esgoto e resíduos | C11: VAB | D11: Brasil | E11: R$ bi | F11: 143.72 | G11: 190.862 | H11: 211.586 | I11: 260.23 | J11: =IFERROR(F11*FATOR_2016,"n.d.") -> 222.79474 | K11: =IFERROR(G11*FATOR_2019,"n.d.") -> 265.59029 | L11: =IFERROR(H11*FATOR_2022,"n.d.") -> 241.95408 | M11: =IFERROR(K11/J11-1,"n.d.") -> 0.1920851 | N11: =IFERROR(L11/K11-1,"n.d.") -> -0.088994989 | O11: =IFERROR(I11/L11-1,"n.d.") -> 0.075534644 | P11: =IFERROR(I11/J11-1,"n.d.") -> 0.16802578 | Q11: =IFERROR(I11-F11,"n.d.") -> 116.51 | R11: =IFERROR(I11-G11,"n.d.") -> 69.368 | S11: =IFERROR(F11/PIB_2016,"n.d.") -> 0.022924311 | T11: =IFERROR(G11/PIB_2019,"n.d.") -> 0.025830101 | U11: =IFERROR(H11/PIB_2022,"n.d.") -> 0.020991349 | V11: =IFERROR(I11/PIB_2025,"n.d.") -> 0.020428516 | W11: IBGE/SIDRA 1846 (S01) | X11: IBGE/SIDRA 1846 (S01) | Y11: IBGE/SIDRA 1846 (S01) | Z11: IBGE/SIDRA 1846 (S01) | AA11: OFICIAL | AB11: —
A12: 3.4 | B12: Construção | C12: VAB | D12: Brasil | E12: R$ bi | F12: 275.187 | G12: 248.642 | H12: 294.04 | I12: 403.368 | J12: =IFERROR(F12*FATOR_2016,"n.d.") -> 426.59488 | K12: =IFERROR(G12*FATOR_2019,"n.d.") -> 345.99292 | L12: =IFERROR(H12*FATOR_2022,"n.d.") -> 336.24237 | M12: =IFERROR(K12/J12-1,"n.d.") -> -0.18894263 | N12: =IFERROR(L12/K12-1,"n.d.") -> -0.028181345 | O12: =IFERROR(I12/L12-1,"n.d.") -> 0.19963464 | P12: =IFERROR(I12/J12-1,"n.d.") -> -0.054447159 | Q12: =IFERROR(I12-F12,"n.d.") -> 128.181 | R12: =IFERROR(I12-G12,"n.d.") -> 154.726 | S12: =IFERROR(F12/PIB_2016,"n.d.") -> 0.043894185 | T12: =IFERROR(G12/PIB_2019,"n.d.") -> 0.033649694 | U12: =IFERROR(H12/PIB_2022,"n.d.") -> 0.029171573 | V12: =IFERROR(I12/PIB_2025,"n.d.") -> 0.031665103 | W12: IBGE/SIDRA 1846 (S01) | X12: IBGE/SIDRA 1846 (S01) | Y12: IBGE/SIDRA 1846 (S01) | Z12: IBGE/SIDRA 1846 (S01) | AA12: OFICIAL | AB12: —
A13: 4 | B13: PIB dos serviços (VAB) | C13: VAB – Serviços total | D13: Brasil | E13: R$ bi | F13: 3962.446 | G13: 4660.166 | H13: 5855.005 | I13: 7609.87 | J13: =IFERROR(F13*FATOR_2016,"n.d.") -> 6142.5837 | K13: =IFERROR(G13*FATOR_2019,"n.d.") -> 6484.763 | L13: =IFERROR(H13*FATOR_2022,"n.d.") -> 6695.3502 | M13: =IFERROR(K13/J13-1,"n.d.") -> 0.055706091 | N13: =IFERROR(L13/K13-1,"n.d.") -> 0.03247416 | O13: =IFERROR(I13/L13-1,"n.d.") -> 0.13659028 | P13: =IFERROR(I13/J13-1,"n.d.") -> 0.2388712 | Q13: =IFERROR(I13-F13,"n.d.") -> 3647.424 | R13: =IFERROR(I13-G13,"n.d.") -> 2949.704 | S13: =IFERROR(F13/PIB_2016,"n.d.") -> 0.6320369 | T13: =IFERROR(G13/PIB_2019,"n.d.") -> 0.63067849 | U13: =IFERROR(H13/PIB_2022,"n.d.") -> 0.58087234 | V13: =IFERROR(I13/PIB_2025,"n.d.") -> 0.59738828 | W13: IBGE/SIDRA 1846 (S01) | X13: IBGE/SIDRA 1846 (S01) | Y13: IBGE/SIDRA 1846 (S01) | Z13: IBGE/SIDRA 1846 (S01) | AA13: OFICIAL | AB13: —
A14: 4.1 | B14: Comércio | C14: VAB | D14: Brasil | E14: R$ bi | F14: 699.768 | G14: 822.59 | H14: 1117.748 | I14: 1271.51 | J14: =IFERROR(F14*FATOR_2016,"n.d.") -> 1084.7803 | K14: =IFERROR(G14*FATOR_2019,"n.d.") -> 1144.6591 | L14: =IFERROR(H14*FATOR_2022,"n.d.") -> 1278.1739 | M14: =IFERROR(K14/J14-1,"n.d.") -> 0.055198935 | N14: =IFERROR(L14/K14-1,"n.d.") -> 0.11664155 | O14: =IFERROR(I14/L14-1,"n.d.") -> -0.005213577 | P14: =IFERROR(I14/J14-1,"n.d.") -> 0.17213593 | Q14: =IFERROR(I14-F14,"n.d.") -> 571.742 | R14: =IFERROR(I14-G14,"n.d.") -> 448.92 | S14: =IFERROR(F14/PIB_2016,"n.d.") -> 0.11161772 | T14: =IFERROR(G14/PIB_2019,"n.d.") -> 0.11132432 | U14: =IFERROR(H14/PIB_2022,"n.d.") -> 0.11089126 | V14: =IFERROR(I14/PIB_2025,"n.d.") -> 0.099815788 | W14: IBGE/SIDRA 1846 (S01) | X14: IBGE/SIDRA 1846 (S01) | Y14: IBGE/SIDRA 1846 (S01) | Z14: IBGE/SIDRA 1846 (S01) | AA14: OFICIAL | AB14: —
A15: 4.2 | B15: Transporte, armazenagem e correio | C15: VAB | D15: Brasil | E15: R$ bi | F15: 235.979 | G15: 284.471 | H15: 279.382 | I15: 395.671 | J15: =IFERROR(F15*FATOR_2016,"n.d.") -> 365.81464 | K15: =IFERROR(G15*FATOR_2019,"n.d.") -> 395.85007 | L15: =IFERROR(H15*FATOR_2022,"n.d.") -> 319.48057 | M15: =IFERROR(K15/J15-1,"n.d.") -> 0.082105589 | N15: =IFERROR(L15/K15-1,"n.d.") -> -0.19292531 | O15: =IFERROR(I15/L15-1,"n.d.") -> 0.2384822 | P15: =IFERROR(I15/J15-1,"n.d.") -> 0.081616092 | Q15: =IFERROR(I15-F15,"n.d.") -> 159.692 | R15: =IFERROR(I15-G15,"n.d.") -> 111.2 | S15: =IFERROR(F15/PIB_2016,"n.d.") -> 0.037640244 | T15: =IFERROR(G15/PIB_2019,"n.d.") -> 0.038498573 | U15: =IFERROR(H15/PIB_2022,"n.d.") -> 0.027717359 | V15: =IFERROR(I15/PIB_2025,"n.d.") -> 0.031060875 | W15: IBGE/SIDRA 1846 (S01) | X15: IBGE/SIDRA 1846 (S01) | Y15: IBGE/SIDRA 1846 (S01) | Z15: IBGE/SIDRA 1846 (S01) | AA15: OFICIAL | AB15: —
... A20: 4.6 | B20: Administração, saúde e educação públicas e seguridade social | C20: VAB | D20: Brasil | E20: R$ bi | F20: 14700000 | G20: 1106.091 | H20: 22648395 | I20: 1747.099 | J20: =IFERROR(F20*FATOR_2016,"n.d.") -> 22787940 | K20: =IFERROR(G20*FATOR_2019,"n.d.") -> 1539.1593 | L20: =IFERROR(H20*FATOR_2022,"n.d.") -> 25899028 | M20: =IFERROR(K20/J20-1,"n.d.") -> -0.99993246 | N20: =IFERROR(L20/K20-1,"n.d.") -> 16825.736 | O20: =IFERROR(I20/L20-1,"n.d.") -> -0.99993254 | P20: =IFERROR(I20/J20-1,"n.d.") -> -0.99992333 | Q20: =IFERROR(I20-F20,"n.d.") -> -14698253 | R20: =IFERROR(I20-G20,"n.d.") -> 641.008 | S20: =IFERROR(F20/PIB_2016,"n.d.") -> 2344.7493 | T20: =IFERROR(G20/PIB_2019,"n.d.") -> 0.14969162 | U20: =IFERROR(H20/PIB_2022,"n.d.") -> 2246.9368 | V20: =IFERROR(I20/PIB_2025,"n.d.") -> 0.13715037 | W20: Caged via Agência Brasil (S33) | X20: IBGE/SIDRA 1846 (S01) | Y20: Novo Caged (S33) | Z20: IBGE/SIDRA 1846 (S01) | AA20: OFICIAL | AB20: [2016/2022] 2016 publicado arredondado (14,7 mi).
A21: 6 | B21: PIB dos serviços não financeiros | C21: Serviços totais − atividades financeiras (cálculo) | D21: Brasil | E21: R$ bi | F21: =F13-F17 -> 3536.913 | G21: =G13-G17 -> 4199.874 | H21: =H13-H17 -> 5245.629 | I21: =I13-I17 -> 6679.601 | J21: =IFERROR(F21*FATOR_2016,"n.d.") -> 5482.9224 | K21: =IFERROR(G21*FATOR_2019,"n.d.") -> 5844.2527 | L21: =IFERROR(H21*FATOR_2022,"n.d.") -> 5998.513 | M21: =IFERROR(K21/J21-1,"n.d.") -> 0.065901028 | N21: =IFERROR(L21/K21-1,"n.d.") -> 0.026395214 | O21: =IFERROR(I21/L21-1,"n.d.") -> 0.11354282 | P21: =IFERROR(I21/J21-1,"n.d.") -> 0.21825561 | Q21: =IFERROR(I21-F21,"n.d.") -> 3142.688 | R21: =IFERROR(I21-G21,"n.d.") -> 2479.727 | S21: =IFERROR(F21/PIB_2016,"n.d.") -> 0.56416151 | T21: =IFERROR(G21/PIB_2019,"n.d.") -> 0.56838538 | U21: =IFERROR(H21/PIB_2022,"n.d.") -> 0.52041643 | V21: =IFERROR(I21/PIB_2025,"n.d.") -> 0.52436051 | W21: Cálculo sobre S01 | X21: Cálculo sobre S01 | Y21: Cálculo sobre S01 | Z21: Cálculo sobre S01 | AA21: ESTIMADO | AB21: Calculado na planilha: VAB serviços − VAB financeiro (mesma fonte e conceito).
A22: 7a | B22: Participação da agropecuária no PIB | C22: VAB da atividade ÷ PIB a preços de mercado | D22: Brasil | E22: % | F22: =F7/F4 -> 0.048913384 | G22: =G7/G4 -> 0.042050141 | H22: =H7/H4 -> 0.05767477 | I22: =I7/I4 -> 0.060862188 | J22: n.a. | K22: n.a. | L22: n.a. | M22: =IFERROR((G22-F22)*100,"n.d.") -> -0.68632432 | N22: =IFERROR((H22-G22)*100,"n.d.") -> 1.562463 | O22: =IFERROR((I22-H22)*100,"n.d.") -> 0.31874176 | P22: =IFERROR((I22-F22)*100,"n.d.") -> 1.1948804 | Q22: =IFERROR((I22-F22)*100,"n.d.") -> 1.1948804 | R22: =IFERROR((I22-G22)*100,"n.d.") -> 1.8812047 | S22: n.a. | T22: n.a. | U22: n.a. | V22: n.a. | W22: Cálculo sobre S01 | X22: Cálculo sobre S01 | Y22: Cálculo sobre S01 | Z22: Cálculo sobre S01 | AA22: ESTIMADO | AB22: Participação no VAB (critério IBGE): 2016: 5,66%; 2019: 4,89%; 2022: 6,65%; 2025: 7,08%.
A23: 7b | B23: Participação da indústria no PIB | C23: VAB da atividade ÷ PIB a preços de mercado | D23: Brasil | E23: % | F23: =F8/F4 -> 0.18354761 | G23: =G8/G4 -> 0.18754628 | H23: =H8/H4 -> 0.22819454 | I23: =I8/I4 -> 0.20149945 | J23: n.a. | K23: n.a. | L23: n.a. | M23: =IFERROR((G23-F23)*100,"n.d.") -> 0.39986637 | N23: =IFERROR((H23-G23)*100,"n.d.") -> 4.0648261 | O23: =IFERROR((I23-H23)*100,"n.d.") -> -2.6695091 | P23: =IFERROR((I23-F23)*100,"n.d.") -> 1.7951835 | Q23: =IFERROR((I23-F23)*100,"n.d.") -> 1.7951835 | R23: =IFERROR((I23-G23)*100,"n.d.") -> 1.3953171 | S23: n.a. | T23: n.a. | U23: n.a. | V23: n.a. | W23: Cálculo sobre S01 | X23: Cálculo sobre S01 | Y23: Cálculo sobre S01 | Z23: Cálculo sobre S01 | AA23: ESTIMADO | AB23: Participação no VAB (critério IBGE): 2016: 21,23%; 2019: 21,80%; 2022: 26,33%; 2025: 23,44%.
A24: 7c' | B24: Participação dos serviços (total) no PIB | C24: VAB da atividade ÷ PIB a preços de mercado | D24: Brasil | E24: % | F24: =F13/F4 -> 0.6320369 | G24: =G13/G4 -> 0.63067849 | H24: =H13/H4 -> 0.58087234 | I24: =I13/I4 -> 0.59738828 | J24: n.a. | K24: n.a. | L24: n.a. | M24: =IFERROR((G24-F24)*100,"n.d.") -> -0.13584071 | N24: =IFERROR((H24-G24)*100,"n.d.") -> -4.9806151 | O24: =IFERROR((I24-H24)*100,"n.d.") -> 1.6515936 | P24: =IFERROR((I24-F24)*100,"n.d.") -> -3.4648622 | Q24: =IFERROR((I24-F24)*100,"n.d.") -> -3.4648622 | R24: =IFERROR((I24-G24)*100,"n.d.") -> -3.3290215 | S24: n.a. | T24: n.a. | U24: n.a. | V24: n.a. | W24: Cálculo sobre S01 | X24: Cálculo sobre S01 | Y24: Cálculo sobre S01 | Z24: Cálculo sobre S01 | AA24: ESTIMADO | AB24: Participação no VAB (critério IBGE): 2016: 73,11%; 2019: 73,31%; 2022: 67,02%; 2025: 69,48%.
A25: 7c | B25: Participação das atividades financeiras no PIB | C25: VAB da atividade ÷ PIB a preços de mercado | D25: Brasil | E25: % | F25: =F17/F4 -> 0.067875388 | G25: =G17/G4 -> 0.062293117 | H25: =H17/H4 -> 0.060455911 | I25: =I17/I4 -> 0.073027765 | J25: n.a. | K25: n.a. | L25: n.a. | M25: =IFERROR((G25-F25)*100,"n.d.") -> -0.55822708 | N25: =IFERROR((H25-G25)*100,"n.d.") -> -0.18372053 | O25: =IFERROR((I25-H25)*100,"n.d.") -> 1.2571853 | P25: =IFERROR((I25-F25)*100,"n.d.") -> 0.51523771 | Q25: =IFERROR((I25-F25)*100,"n.d.") -> 0.51523771 | R25: =IFERROR((I25-G25)*100,"n.d.") -> 1.0734648 | S25: n.a. | T25: n.a. | U25: n.a. | V25: n.a. | W25: Cálculo sobre S01 | X25: Cálculo sobre S01 | Y25: Cálculo sobre S01 | Z25: Cálculo sobre S01 | AA25: ESTIMADO | AB25: Participação no VAB (critério IBGE): 2016: 7,85%; 2019: 7,24%; 2022: 6,98%; 2025: 8,49%.
A26: 7d | B26: Participação dos serviços não financeiros no PIB | C26: VAB da atividade ÷ PIB a preços de mercado | D26: Brasil | E26: % | F26: =F21/F4 -> 0.56416151 | G26: =G21/G4 -> 0.56838538 | H26: =H21/H4 -> 0.52041643 | I26: =I21/I4 -> 0.52436051 | J26: n.a. | K26: n.a. | L26: n.a. | M26: =IFERROR((G26-F26)*100,"n.d.") -> 0.42238637 | N26: =IFERROR((H26-G26)*100,"n.d.") -> -4.7968946 | O26: =IFERROR((I26-H26)*100,"n.d.") -> 0.39440827 | P26: =IFERROR((I26-F26)*100,"n.d.") -> -3.9800999 | Q26: =IFERROR((I26-F26)*100,"n.d.") -> -3.9800999 | R26: =IFERROR((I26-G26)*100,"n.d.") -> -4.4024863 | S26: n.a. | T26: n.a. | U26: n.a. | V26: n.a. | W26: Cálculo sobre S01 | X26: Cálculo sobre S01 | Y26: Cálculo sobre S01 | Z26: Cálculo sobre S01 | AA26: ESTIMADO | AB26: Participação no VAB (critério IBGE): 2016: 65,26%; 2019: 66,07%; 2022: 60,04%; 2025: 60,99%.
A28: Notas metodológicas
A29: 1. Serviços não financeiros = VAB de serviços − VAB de atividades financeiras, de seguros e serviços relacionados.
A30: 2. Participações sobre o PIB a preços de mercado; a observação traz a participação sobre o VAB.
A31: 3. Série consultada em 22/09/2026; valores podem diferir das divulgações originais de cada ano.
A32: 4. Valores nominais do próprio ano (R$ bilhões, salvo indicação). Correção para R$ de dez/2025 pelo IPCA: fator = índice dez/2025 ÷ índice de dezembro do ano (FATOR_2016, FATOR_2019, FATOR_2022 na aba 'Resumo executivo').
A33: 5. Colunas de variação: para valores em R$ = variação REAL (IPCA); para US$ e pessoas = variação nominal; para taxas e % = diferença em pontos percentuais (p.p.).
A34: 6. % do PIB com o PIB anual do IBGE (SIDRA 1846) de cada ano; valores em US$ usam o PIB convertido pela PTAX média anual.
A35: 7. 'n.a.' = não se aplica; 'n.d.' = não disponível (algum ano 'não localizado após busca'). Azul = dado digitado da fonte; preto = fórmula; verde = vínculo com outra aba.
A36: 8. Cor da linha = classificação do dado em 2019/2025; células de 2016/2022 com cor própria quando a classificação difere (ex.: estimado, não localizado).
A37: 9. Períodos 2016→2019, 2019→2022 e 2022→2025 correspondem aproximadamente aos mandatos Temer, Bolsonaro e Lula III (até 2025); 2016 inclui o governo Dilma até maio.

Sheet Receitas públicas
A1: Receitas públicas – União e Governo Central
A2: Arrecadação federal (RFB), receitas do Governo Central (RTN/STN, caixa) e subsídios da União (OSU/PLOA).
A3: Código | B3: Indicador | C3: Conceito / estágio | D3: Âmbito | E3: Unidade | F3: Brasil 2016 | G3: Brasil 2019 | H3: Brasil 2022 | I3: Brasil 2025 | J3: 2016 em R$ de dez/2025 | K3: 2019 em R$ de dez/2025 | L3: 2022 em R$ de dez/2025 | M3: Variação 2016→2019 | N3: Variação 2019→2022 | O3: Variação 2022→2025 | P3: Variação 2016→2025 | Q3: Diferença absoluta 2025−2016 (nominal) | R3: Diferença absoluta 2025−2019 (nominal) | S3: 2016 % do PIB | T3: 2019 % do PIB | U3: 2022 % do PIB | V3: 2025 % do PIB | W3: Fonte 2016 | X3: Fonte 2019 | Y3: Fonte 2022 | Z3: Fonte 2025 | AA3: Classificação do dado | AB3: Observações metodológicas
A4: 8 | B4: Arrecadação da União (receitas federais) | C4: Arrecadação total das receitas federais (RFB + outros órgãos), fluxo anual | D4: União | E4: R$ bi | F4: 1289 | G4: 1537 | H4: 2218 | I4: 2886 | J4: =IFERROR(F4*FATOR_2016,"n.d.") -> 1998.2078 | K4: =IFERROR(G4*FATOR_2019,"n.d.") -> 2138.7823 | L4: =IFERROR(H4*FATOR_2022,"n.d.") -> 2536.3406 | M4: =IFERROR(K4/J4-1,"n.d.") -> 0.07035033 | N4: =IFERROR(L4/K4-1,"n.d.") -> 0.18588065 | O4: =IFERROR(I4/L4-1,"n.d.") -> 0.1378598 | P4: =IFERROR(I4/J4-1,"n.d.") -> 0.44429426 | Q4: =IFERROR(I4-F4,"n.d.") -> 1597 | R4: =IFERROR(I4-G4,"n.d.") -> 1349 | S4: =IFERROR(F4/PIB_2016,"n.d.") -> 0.20560421 | T4: =IFERROR(G4/PIB_2019,"n.d.") -> 0.20800822 | U4: =IFERROR(H4/PIB_2022,"n.d.") -> 0.22004676 | V4: =IFERROR(I4/PIB_2025,"n.d.") -> 0.22655611 | W4: Receita Federal (S29) | X4: Receita Federal (S12) | Y4: Receita Federal (S29) | Z4: Receita Federal (S12) | AA4: OFICIAL | AB4: Valores publicados como R$ 1,537 tri (2019) e R$ 2,886 tri (2025), sem mais casas decimais. Conceito distinto da 'receita total' do RTN (caixa do Tesouro). [2016/2022] 2016: R$ 1,289 tri; 2022: R$ 2,218 tri (publicados sem mais casas).
A5: 8.1 | B5: Receitas administradas pela RFB (RTN) | C5: Caixa – Tesouro Nacional | D5: Governo Central | E5: R$ bi | F5: 819.752 | G5: 946.083 | H5: 1390 | I5: 1859.844 | J5: =IFERROR(F5*FATOR_2016,"n.d.") -> 1270.7795 | K5: =IFERROR(G5*FATOR_2019,"n.d.") -> 1316.5033 | L5: =IFERROR(H5*FATOR_2022,"n.d.") -> 1589.5011 | M5: =IFERROR(K5/J5-1,"n.d.") -> 0.035980906 | N5: =IFERROR(L5/K5-1,"n.d.") -> 0.2073658 | O5: =IFERROR(I5/L5-1,"n.d.") -> 0.17008036 | P5: =IFERROR(I5/J5-1,"n.d.") -> 0.46354577 | Q5: =IFERROR(I5-F5,"n.d.") -> 1040.092 | R5: =IFERROR(I5-G5,"n.d.") -> 913.761 | S5: =IFERROR(F5/PIB_2016,"n.d.") -> 0.13075598 | T5: =IFERROR(G5/PIB_2019,"n.d.") -> 0.12803711 | U5: =IFERROR(H5/PIB_2022,"n.d.") -> 0.13790126 | V5: =IFERROR(I5/PIB_2025,"n.d.") -> 0.14600105 | W5: STN – RTN tab. 2.1 (S04) | X5: STN – RTN tab. 2.1 (S04) | Y5: STN – RTN tab. 2.1 (S04) | Z5: STN – RTN tab. 2.1 (S04) | AA5: OFICIAL | AB5: Exclui arrecadação líquida do RGPS.
A6: 8.2 | B6: Imposto de Renda | C6: Caixa | D6: Governo Central | E6: R$ bi | F6: 341.115 | G6: 398.37 | H6: 667.223 | I6: 867.31 | J6: =IFERROR(F6*FATOR_2016,"n.d.") -> 528.79646 | K6: =IFERROR(G6*FATOR_2019,"n.d.") -> 554.34399 | L6: =IFERROR(H6*FATOR_2022,"n.d.") -> 762.98682 | M6: =IFERROR(K6/J6-1,"n.d.") -> 0.048312599 | N6: =IFERROR(L6/K6-1,"n.d.") -> 0.3763779 | O6: =IFERROR(I6/L6-1,"n.d.") -> 0.13672998 | P6: =IFERROR(I6/J6-1,"n.d.") -> 0.64015847 | Q6: =IFERROR(I6-F6,"n.d.") -> 526.195 | R6: =IFERROR(I6-G6,"n.d.") -> 468.94 | S6: =IFERROR(F6/PIB_2016,"n.d.") -> 0.054410146 | T6: =IFERROR(G6/PIB_2019,"n.d.") -> 0.05391297 | U6: =IFERROR(H6/PIB_2022,"n.d.") -> 0.066194886 | V6: =IFERROR(I6/PIB_2025,"n.d.") -> 0.068085372 | W6: STN – RTN tab. 2.1 (S04) | X6: S04 | Y6: STN – RTN tab. 2.1 (S04) | Z6: S04 | AA6: OFICIAL | AB6: —
A7: 8.3 | B7: Cofins | C7: Caixa | D7: Governo Central | E7: R$ bi | F7: 204.679 | G7: 238.7 | H7: 276.748 | I7: 391.53 | J7: =IFERROR(F7*FATOR_2016,"n.d.") -> 317.29338 | K7: =IFERROR(G7*FATOR_2019,"n.d.") -> 332.15832 | L7: =IFERROR(H7*FATOR_2022,"n.d.") -> 316.46852 | M7: =IFERROR(K7/J7-1,"n.d.") -> 0.04684921 | N7: =IFERROR(L7/K7-1,"n.d.") -> -0.04723591 | O7: =IFERROR(I7/L7-1,"n.d.") -> 0.23718465 | P7: =IFERROR(I7/J7-1,"n.d.") -> 0.23396839 | Q7: =IFERROR(I7-F7,"n.d.") -> 186.851 | R7: =IFERROR(I7-G7,"n.d.") -> 152.83 | S7: =IFERROR(F7/PIB_2016,"n.d.") -> 0.032647683 | T7: =IFERROR(G7/PIB_2019,"n.d.") -> 0.032304205 | U7: =IFERROR(H7/PIB_2022,"n.d.") -> 0.027456041 | V7: =IFERROR(I7/PIB_2025,"n.d.") -> 0.030735799 | W7: STN – RTN tab. 2.1 (S04) | X7: S04 | Y7: STN – RTN tab. 2.1 (S04) | Z7: S04 | AA7: OFICIAL | AB7: —
A8: 8.4 | B8: CSLL | C8: Caixa | D8: Governo Central | E8: R$ bi | F8: 68.143 | G8: 82.02 | H8: 158.497 | I8: 177.8 | J8: =IFERROR(F8*FATOR_2016,"n.d.") -> 105.63528 | K8: =IFERROR(G8*FATOR_2019,"n.d.") -> 114.13333 | L8: =IFERROR(H8*FATOR_2022,"n.d.") -> 181.24543 | M8: =IFERROR(K8/J8-1,"n.d.") -> 0.080447111 | N8: =IFERROR(L8/K8-1,"n.d.") -> 0.58801496 | O8: =IFERROR(I8/L8-1,"n.d.") -> -0.019009773 | P8: =IFERROR(I8/J8-1,"n.d.") -> 0.68314985 | Q8: =IFERROR(I8-F8,"n.d.") -> 109.657 | R8: =IFERROR(I8-G8,"n.d.") -> 95.78 | S8: =IFERROR(F8/PIB_2016,"n.d.") -> 0.010869269 | T8: =IFERROR(G8/PIB_2019,"n.d.") -> 0.011100087 | U8: =IFERROR(H8/PIB_2022,"n.d.") -> 0.015724414 | V8: =IFERROR(I8/PIB_2025,"n.d.") -> 0.013957615 | W8: STN – RTN tab. 2.1 (S04) | X8: S04 | Y8: STN – RTN tab. 2.1 (S04) | Z8: S04 | AA8: OFICIAL | AB8: —
A9: 8.5 | B9: IOF | C9: Caixa | D9: Governo Central | E9: R$ bi | F9: 33.782 | G9: 41.04 | H9: 59.091 | I9: 86.38 | J9: =IFERROR(F9*FATOR_2016,"n.d.") -> 52.368855 | K9: =IFERROR(G9*FATOR_2019,"n.d.") -> 57.108411 | L9: =IFERROR(H9*FATOR_2022,"n.d.") -> 67.572093 | M9: =IFERROR(K9/J9-1,"n.d.") -> 0.090503319 | N9: =IFERROR(L9/K9-1,"n.d.") -> 0.18322489 | O9: =IFERROR(I9/L9-1,"n.d.") -> 0.27833839 | P9: =IFERROR(I9/J9-1,"n.d.") -> 0.64945366 | Q9: =IFERROR(I9-F9,"n.d.") -> 52.598 | R9: =IFERROR(I9-G9,"n.d.") -> 45.34 | S9: =IFERROR(F9/PIB_2016,"n.d.") -> 0.0053884572 | T9: =IFERROR(G9/PIB_2019,"n.d.") -> 0.0055541037 | U9: =IFERROR(H9/PIB_2022,"n.d.") -> 0.0058623908 | V9: =IFERROR(I9/PIB_2025,"n.d.") -> 0.006780983 | W9: STN – RTN tab. 2.1 (S04) | X9: S04 | Y9: STN – RTN tab. 2.1 (S04) | Z9: S04 | AA9: OFICIAL | AB9: Alta de alíquotas do IOF em 2025.
A10: 8.6 | B10: Arrecadação líquida para o RGPS | C10: Caixa | D10: Governo Central | E10: R$ bi | F10: 358.137 | G10: 413.331 | H10: 535.71 | I10: 709.714 | J10: =IFERROR(F10*FATOR_2016,"n.d.") -> 555.18397 | K10: =IFERROR(G10*FATOR_2019,"n.d.") -> 575.16268 | L10: =IFERROR(H10*FATOR_2022,"n.d.") -> 612.59829 | M10: =IFERROR(K10/J10-1,"n.d.") -> 0.035985757 | N10: =IFERROR(L10/K10-1,"n.d.") -> 0.065086997 | O10: =IFERROR(I10/L10-1,"n.d.") -> 0.15853081 | P10: =IFERROR(I10/J10-1,"n.d.") -> 0.27834023 | Q10: =IFERROR(I10-F10,"n.d.") -> 351.577 | R10: =IFERROR(I10-G10,"n.d.") -> 296.383 | S10: =IFERROR(F10/PIB_2016,"n.d.") -> 0.05712527 | T10: =IFERROR(G10/PIB_2019,"n.d.") -> 0.055937701 | U10: =IFERROR(H10/PIB_2022,"n.d.") -> 0.053147542 | V10: =IFERROR(I10/PIB_2025,"n.d.") -> 0.055713806 | W10: STN – RTN tab. 2.1 (S04) | X10: S04 | Y10: STN – RTN tab. 2.1 (S04) | Z10: S04 | AA10: OFICIAL | AB10: —
A11: 8.7 | B11: Concessões e permissões | C11: Caixa – receita não administrada pela RFB | D11: Governo Central | E11: R$ bi | F11: 21.908 | G11: 93.28 | H11: 46.847 | I11: 7.2 | J11: =IFERROR(F11*FATOR_2016,"n.d.") -> 33.961781 | K11: =IFERROR(G11*FATOR_2019,"n.d.") -> 129.80196 | L11: =IFERROR(H11*FATOR_2022,"n.d.") -> 53.570761 | M11: =IFERROR(K11/J11-1,"n.d.") -> 2.8220011 | N11: =IFERROR(L11/K11-1,"n.d.") -> -0.58728851 | O11: =IFERROR(I11/L11-1,"n.d.") -> -0.86559832 | P11: =IFERROR(I11/J11-1,"n.d.") -> -0.78799698 | Q11: =IFERROR(I11-F11,"n.d.") -> -14.708 | R11: =IFERROR(I11-G11,"n.d.") -> -86.08 | S11: =IFERROR(F11/PIB_2016,"n.d.") -> 0.003494474 | T11: =IFERROR(G11/PIB_2019,"n.d.") -> 0.012623947 | U11: =IFERROR(H11/PIB_2022,"n.d.") -> 0.0046476692 | V11: =IFERROR(I11/PIB_2025,"n.d.") -> 0.00056521276 | W11: STN – RTN tab. 2.1 (S04) | X11: S04 | Y11: STN – RTN tab. 2.1 (S04) | Z11: S04 | AA11: OFICIAL | AB11: 2019 inclui leilão da cessão onerosa (receita extraordinária). [2016/2022] 2022 inclui privatização da Eletrobras e leilões do pré-sal.
A12: 8.8 | B12: Dividendos e participações | C12: Caixa | D12: Governo Central | E12: R$ bi | F12: 2.848 | G12: 20.88 | H12: 87.004 | I12: 49.8 | J12: =IFERROR(F12*FATOR_2016,"n.d.") -> 4.4149695 | K12: =IFERROR(G12*FATOR_2019,"n.d.") -> 29.055156 | L12: =IFERROR(H12*FATOR_2022,"n.d.") -> 99.491333 | M12: =IFERROR(K12/J12-1,"n.d.") -> 5.5810548 | N12: =IFERROR(L12/K12-1,"n.d.") -> 2.4242229 | O12: =IFERROR(I12/L12-1,"n.d.") -> -0.49945389 | P12: =IFERROR(I12/J12-1,"n.d.") -> 10.279806 | Q12: =IFERROR(I12-F12,"n.d.") -> 46.952 | R12: =IFERROR(I12-G12,"n.d.") -> 28.92 | S12: =IFERROR(F12/PIB_2016,"n.d.") -> 0.00045427524 | T12: =IFERROR(G12/PIB_2019,"n.d.") -> 0.0028257721 | U12: =IFERROR(H12/PIB_2022,"n.d.") -> 0.0086316267 | V12: =IFERROR(I12/PIB_2025,"n.d.") -> 0.0039093882 | W12: STN – RTN tab. 2.1 (S04) | X12: S04 | Y12: STN – RTN tab. 2.1 (S04) | Z12: S04 | AA12: OFICIAL | AB12: [2016/2022] 2022: dividendos extraordinários da Petrobras.
A13: 8.9 | B13: Receitas de exploração de recursos naturais | C13: Caixa (royalties/participação especial) | D13: Governo Central | E13: R$ bi | F13: 23.275 | G13: 64.68 | H13: 132.482 | I13: 139.35 | J13: =IFERROR(F13*FATOR_2016,"n.d.") -> 36.080904 | K13: =IFERROR(G13*FATOR_2019,"n.d.") -> 90.004191 | L13: =IFERROR(H13*FATOR_2022,"n.d.") -> 151.49661 | M13: =IFERROR(K13/J13-1,"n.d.") -> 1.4945104 | N13: =IFERROR(L13/K13-1,"n.d.") -> 0.68321725 | O13: =IFERROR(I13/L13-1,"n.d.") -> -0.080177417 | P13: =IFERROR(I13/J13-1,"n.d.") -> 2.8621538 | Q13: =IFERROR(I13-F13,"n.d.") -> 116.075 | R13: =IFERROR(I13-G13,"n.d.") -> 74.67 | S13: =IFERROR(F13/PIB_2016,"n.d.") -> 0.0037125197 | T13: =IFERROR(G13/PIB_2019,"n.d.") -> 0.0087533974 | U13: =IFERROR(H13/PIB_2022,"n.d.") -> 0.013143478 | V13: =IFERROR(I13/PIB_2025,"n.d.") -> 0.010939222 | W13: STN – RTN tab. 2.1 (S04) | X13: S04 | Y13: STN – RTN tab. 2.1 (S04) | Z13: S04 | AA13: OFICIAL | AB13: —
A14: 10 | B14: Receita primária total do Governo Central | C14: Receita total (Tesouro + Previdência + BCB), caixa | D14: Governo Central | E14: R$ bi | F14: 1315.985 | G14: 1635.608 | H14: 2313.305 | I14: 2902.275 | J14: =IFERROR(F14*FATOR_2016,"n.d.") -> 2040.0399 | K14: =IFERROR(G14*FATOR_2019,"n.d.") -> 2275.9984 | L14: =IFERROR(H14*FATOR_2022,"n.d.") -> 2645.3243 | M14: =IFERROR(K14/J14-1,"n.d.") -> 0.11566365 | N14: =IFERROR(L14/K14-1,"n.d.") -> 0.16226987 | O14: =IFERROR(I14/L14-1,"n.d.") -> 0.097133902 | P14: =IFERROR(I14/J14-1,"n.d.") -> 0.42265599 | Q14: =IFERROR(I14-F14,"n.d.") -> 1586.29 | R14: =IFERROR(I14-G14,"n.d.") -> 1266.667 | S14: =IFERROR(F14/PIB_2016,"n.d.") -> 0.2099085 | T14: =IFERROR(G14/PIB_2019,"n.d.") -> 0.22135323 | U14: =IFERROR(H14/PIB_2022,"n.d.") -> 0.22950192 | V14: =IFERROR(I14/PIB_2025,"n.d.") -> 0.22783373 | W14: STN – RTN tab. 2.1 (S04) | X14: S04 | Y14: STN – RTN tab. 2.1 (S04) | Z14: S04 | AA14: OFICIAL | AB14: —
A15: 10.1 | B15: Transferências por repartição de receita | C15: FPM/FPE, royalties etc. | D15: Governo Central → subnacionais | E15: R$ bi | F15: 226.835 | G15: 288.331 | H15: 457.204 | I15: 569.716 | J15: =IFERROR(F15*FATOR_2016,"n.d.") -> 351.63961 | K15: =IFERROR(G15*FATOR_2019,"n.d.") -> 401.22137 | L15: =IFERROR(H15*FATOR_2022,"n.d.") -> 522.82464 | M15: =IFERROR(K15/J15-1,"n.d.") -> 0.14100164 | N15: =IFERROR(L15/K15-1,"n.d.") -> 0.30308274 | O15: =IFERROR(I15/L15-1,"n.d.") -> 0.089688495 | P15: =IFERROR(I15/J15-1,"n.d.") -> 0.62017015 | Q15: =IFERROR(I15-F15,"n.d.") -> 342.881 | R15: =IFERROR(I15-G15,"n.d.") -> 281.385 | S15: =IFERROR(F15/PIB_2016,"n.d.") -> 0.036181715 | T15: =IFERROR(G15/PIB_2019,"n.d.") -> 0.039020962 | U15: =IFERROR(H15/PIB_2022,"n.d.") -> 0.045358998 | V15: =IFERROR(I15/PIB_2025,"n.d.") -> 0.044723715 | W15: STN – RTN tab. 2.1 (S04) | X15: S04 | Y15: STN – RTN tab. 2.1 (S04) | Z15: S04 | AA15: OFICIAL | AB15: —
... A18: 17 | B18: Benefícios financeiros e creditícios | C18: Subsídios explícitos (financeiros) + implícitos (creditícios) | D18: União | E18: R$ bi | F18: 115 | G18: 40.05 | H18: 120.43 | I18: 172.5 | J18: =IFERROR(F18*FATOR_2016,"n.d.") -> 178.273 | K18: =IFERROR(G18*FATOR_2019,"n.d.") -> 55.730795 | L18: =IFERROR(H18*FATOR_2022,"n.d.") -> 137.71483 | M18: =IFERROR(K18/J18-1,"n.d.") -> -0.6873851 | N18: =IFERROR(L18/K18-1,"n.d.") -> 1.4710724 | O18: =IFERROR(I18/L18-1,"n.d.") -> 0.2525884 | P18: =IFERROR(I18/J18-1,"n.d.") -> -0.0323829 | Q18: =IFERROR(I18-F18,"n.d.") -> 57.5 | R18: =IFERROR(I18-G18,"n.d.") -> 132.45 | S18: =IFERROR(F18/PIB_2016,"n.d.") -> 0.018343277 | T18: =IFERROR(G18/PIB_2019,"n.d.") -> 0.0054201232 | U18: =IFERROR(H18/PIB_2022,"n.d.") -> 0.011947805 | V18: =IFERROR(I18/PIB_2025,"n.d.") -> 0.013541556 | W18: Fazenda – OSU (S36) | X18: OSU 4ª ed. (S13) – 11,5% × R$ 348,3 bi | Y18: MPO – OSU (S36) | Z18: Estimativa do Executivo – PLOA 2026 (S14) | AA18: ESTIMADO | AB18: 2019: 11,5% de R$ 348,3 bi (cálculo sobre dado oficial). 2025: estimativa do Poder Executivo, não apuração. Em 2024 (realizado, OSU 9ª ed.) financeiros+creditícios = 16,9% de R$ 678 bi ≈ R$ 114,6 bi — ordem de grandeza menor que a estimativa de 2025. [2016/2022] 2016 e 2022 apurados; 2016 inflado por subsídios implícitos do BNDES/FIES.
A19: 16.1 | B19: Subsídios da União – total (tributários + financeiros + creditícios) | C19: OSU | D19: União | E19: R$ bi | F19: 386 | G19: 348.3 | H19: 581.49 | I19: =I17+I18 -> 759.9 | J19: =IFERROR(F19*FATOR_2016,"n.d.") -> 598.37719 | K19: =IFERROR(G19*FATOR_2019,"n.d.") -> 484.67006 | L19: =IFERROR(H19*FATOR_2022,"n.d.") -> 664.94891 | M19: =IFERROR(K19/J19-1,"n.d.") -> -0.19002583 | N19: =IFERROR(L19/K19-1,"n.d.") -> 0.371962 | O19: =IFERROR(I19/L19-1,"n.d.") -> 0.14279456 | P19: =IFERROR(I19/J19-1,"n.d.") -> 0.26993477 | Q19: =IFERROR(I19-F19,"n.d.") -> 373.9 | R19: =IFERROR(I19-G19,"n.d.") -> 411.6 | S19: =IFERROR(F19/PIB_2016,"n.d.") -> 0.061569607 | T19: =IFERROR(G19/PIB_2019,"n.d.") -> 0.047136801 | U19: =IFERROR(H19/PIB_2022,"n.d.") -> 0.057689354 | V19: =IFERROR(I19/PIB_2025,"n.d.") -> 0.059653496 | W19: S36 | X19: OSU (S13) | Y19: S36 | Z19: Soma de estimativas (S14) | AA19: ESTIMADO | AB19: 2025 = soma das duas estimativas oficiais acima; não há OSU 2025 publicado.
A21: Notas metodológicas
A22: 1. Arrecadação federal (RFB) e receita total do RTN são conceitos distintos e não devem ser somados.
A23: 2. Gastos tributários: 2016, 2019 e 2022 apurados (OSU); 2025 é projeção oficial.
A24: 3. Valores nominais do próprio ano (R$ bilhões, salvo indicação). Correção para R$ de dez/2025 pelo IPCA: fator = índice dez/2025 ÷ índice de dezembro do ano (FATOR_2016, FATOR_2019, FATOR_2022 na aba 'Resumo executivo').
A25: 4. Colunas de variação: para valores em R$ = variação REAL (IPCA); para US$ e pessoas = variação nominal; para taxas e % = diferença em pontos percentuais (p.p.).
A26: 5. % do PIB com o PIB anual do IBGE (SIDRA 1846) de cada ano; valores em US$ usam o PIB convertido pela PTAX média anual.
A27: 6. 'n.a.' = não se aplica; 'n.d.' = não disponível (algum ano 'não localizado após busca'). Azul = dado digitado da fonte; preto = fórmula; verde = vínculo com outra aba.
A28: 7. Cor da linha = classificação do dado em 2019/2025; células de 2016/2022 com cor própria quando a classificação difere (ex.: estimado, não localizado).
A29: 8. Períodos 2016→2019, 2019→2022 e 2022→2025 correspondem aproximadamente aos mandatos Temer, Bolsonaro e Lula III (até 2025); 2016 inclui o governo Dilma até maio.

Sheet Despesas públicas
A1: Despesas públicas – Governo Central (RTN) e União (orçamento)
A2: Despesa primária pelo critério caixa (STN); juros e resultado nominal pelo critério competência (BCB); despesa orçamentária paga (RREO).
A3: Código | B3: Indicador | C3: Conceito / estágio | D3: Âmbito | E3: Unidade | F3: Brasil 2016 | G3: Brasil 2019 | H3: Brasil 2022 | I3: Brasil 2025 | J3: 2016 em R$ de dez/2025 | K3: 2019 em R$ de dez/2025 | L3: 2022 em R$ de dez/2025 | M3: Variação 2016→2019 | N3: Variação 2019→2022 | O3: Variação 2022→2025 | P3: Variação 2016→2025 | Q3: Diferença absoluta 2025−2016 (nominal) | R3: Diferença absoluta 2025−2019 (nominal) | S3: 2016 % do PIB | T3: 2019 % do PIB | U3: 2022 % do PIB | V3: 2025 % do PIB | W3: Fonte 2016 | X3: Fonte 2019 | Y3: Fonte 2022 | Z3: Fonte 2025 | AA3: Classificação do dado | AB3: Observações metodológicas
A4: 11 | B4: Despesa primária do Governo Central | C4: Despesa total primária (RTN), caixa | D4: Governo Central | E4: R$ bi | F4: 1250.426 | G4: 1442.34 | H4: 1809.693 | I4: 2394.25 | J4: =IFERROR(F4*FATOR_2016,"n.d.") -> 1938.4103 | K4: =IFERROR(G4*FATOR_2019,"n.d.") -> 2007.0601 | L4: =IFERROR(H4*FATOR_2022,"n.d.") -> 2069.4309 | M4: =IFERROR(K4/J4-1,"n.d.") -> 0.03541547 | N4: =IFERROR(L4/K4-1,"n.d.") -> 0.031075735 | O4: =IFERROR(I4/L4-1,"n.d.") -> 0.15696058 | P4: =IFERROR(I4/J4-1,"n.d.") -> 0.23516159 | Q4: =IFERROR(I4-F4,"n.d.") -> 1143.824 | R4: =IFERROR(I4-G4,"n.d.") -> 951.91 | S4: =IFERROR(F4/PIB_2016,"n.d.") -> 0.19945139 | T4: =IFERROR(G4/PIB_2019,"n.d.") -> 0.19519751 | U4: =IFERROR(H4/PIB_2022,"n.d.") -> 0.17953881 | V4: =IFERROR(I4/PIB_2025,"n.d.") -> 0.18795287 | W4: STN – RTN tab. 2.1 (S04) | X4: STN – RTN tab. 2.1 (S04) | Y4: STN – RTN tab. 2.1 (S04) | Z4: S04 | AA4: OFICIAL | AB4: —
A5: 11.1 | B5: Benefícios previdenciários (RGPS) | C5: RTN, caixa | D5: Governo Central | E5: R$ bi | F5: 507.871 | G5: 626.51 | H5: 796.977 | I5: 1026.87 | J5: =IFERROR(F5*FATOR_2016,"n.d.") -> 787.30161 | K5: =IFERROR(G5*FATOR_2019,"n.d.") -> 871.80776 | L5: =IFERROR(H5*FATOR_2022,"n.d.") -> 911.36389 | M5: =IFERROR(K5/J5-1,"n.d.") -> 0.10733643 | N5: =IFERROR(L5/K5-1,"n.d.") -> 0.045372542 | O5: =IFERROR(I5/L5-1,"n.d.") -> 0.12673983 | P5: =IFERROR(I5/J5-1,"n.d.") -> 0.30429049 | Q5: =IFERROR(I5-F5,"n.d.") -> 518.999 | R5: =IFERROR(I5-G5,"n.d.") -> 400.36 | S5: =IFERROR(F5/PIB_2016,"n.d.") -> 0.081008855 | T5: =IFERROR(G5/PIB_2019,"n.d.") -> 0.084788049 | U5: =IFERROR(H5/PIB_2022,"n.d.") -> 0.07906772 | V5: =IFERROR(I5/PIB_2025,"n.d.") -> 0.080611114 | W5: STN – RTN tab. 2.1 (S04) | X5: S04 | Y5: STN – RTN tab. 2.1 (S04) | Z5: S04 | AA5: OFICIAL | AB5: —
A6: 11.2 | B6: Pessoal e encargos sociais | C6: RTN, caixa | D6: Governo Central | E6: R$ bi | F6: 257.872 | G6: 313.09 | H6: 337.942 | I6: 402.55 | J6: =IFERROR(F6*FATOR_2016,"n.d.") -> 399.75317 | K6: =IFERROR(G6*FATOR_2019,"n.d.") -> 435.67428 | L6: =IFERROR(H6*FATOR_2022,"n.d.") -> 386.44545 | M6: =IFERROR(K6/J6-1,"n.d.") -> 0.089858223 | N6: =IFERROR(L6/K6-1,"n.d.") -> -0.11299456 | O6: =IFERROR(I6/L6-1,"n.d.") -> 0.041673538 | P6: =IFERROR(I6/J6-1,"n.d.") -> 0.0069964003 | Q6: =IFERROR(I6-F6,"n.d.") -> 144.678 | R6: =IFERROR(I6-G6,"n.d.") -> 89.46 | S6: =IFERROR(F6/PIB_2016,"n.d.") -> 0.041132326 | T6: =IFERROR(G6/PIB_2019,"n.d.") -> 0.042371694 | U6: =IFERROR(H6/PIB_2022,"n.d.") -> 0.03352707 | V6: =IFERROR(I6/PIB_2025,"n.d.") -> 0.031600888 | W6: STN – RTN tab. 2.1 (S04) | X6: S04 | Y6: STN – RTN tab. 2.1 (S04) | Z6: S04 | AA6: OFICIAL | AB6: —
A7: 11.3 | B7: BPC/LOAS e RMV | C7: RTN, caixa | D7: Governo Central | E7: R$ bi | F7: 48.99 | G7: 59.73 | H7: 78.827 | I7: 127.24 | J7: =IFERROR(F7*FATOR_2016,"n.d.") -> 75.944297 | K7: =IFERROR(G7*FATOR_2019,"n.d.") -> 83.116115 | L7: =IFERROR(H7*FATOR_2022,"n.d.") -> 90.140721 | M7: =IFERROR(K7/J7-1,"n.d.") -> 0.09443525 | N7: =IFERROR(L7/K7-1,"n.d.") -> 0.084515571 | O7: =IFERROR(I7/L7-1,"n.d.") -> 0.41157069 | P7: =IFERROR(I7/J7-1,"n.d.") -> 0.67543852 | Q7: =IFERROR(I7-F7,"n.d.") -> 78.25 | R7: =IFERROR(I7-G7,"n.d.") -> 67.51 | S7: =IFERROR(F7/PIB_2016,"n.d.") -> 0.0078142359 | T7: =IFERROR(G7/PIB_2019,"n.d.") -> 0.0080834945 | U7: =IFERROR(H7/PIB_2022,"n.d.") -> 0.0078203903 | V7: =IFERROR(I7/PIB_2025,"n.d.") -> 0.0099885654 | W7: STN – RTN tab. 2.1 (S04) | X7: S04 | Y7: STN – RTN tab. 2.1 (S04) | Z7: S04 | AA7: OFICIAL | AB7: —
A8: 11.4 | B8: Abono e seguro-desemprego | C8: RTN, caixa | D8: Governo Central | E8: R$ bi | F8: 56.014 | G8: 55.59 | H8: 64.271 | I8: 87.84 | J8: =IFERROR(F8*FATOR_2016,"n.d.") -> 86.832901 | K8: =IFERROR(G8*FATOR_2019,"n.d.") -> 77.355179 | L8: =IFERROR(H8*FATOR_2022,"n.d.") -> 73.495557 | M8: =IFERROR(K8/J8-1,"n.d.") -> -0.10914897 | N8: =IFERROR(L8/K8-1,"n.d.") -> -0.049894809 | O8: =IFERROR(I8/L8-1,"n.d.") -> 0.19517429 | P8: =IFERROR(I8/J8-1,"n.d.") -> 0.011598125 | Q8: =IFERROR(I8-F8,"n.d.") -> 31.826 | R8: =IFERROR(I8-G8,"n.d.") -> 32.25 | S8: =IFERROR(F8/PIB_2016,"n.d.") -> 0.0089346113 | T8: =IFERROR(G8/PIB_2019,"n.d.") -> 0.0075232121 | U8: =IFERROR(H8/PIB_2022,"n.d.") -> 0.0063762962 | V8: =IFERROR(I8/PIB_2025,"n.d.") -> 0.0068955956 | W8: STN – RTN tab. 2.1 (S04) | X8: S04 | Y8: STN – RTN tab. 2.1 (S04) | Z8: S04 | AA8: OFICIAL | AB8: —
A9: 11.5 | B9: Complementação da União ao Fundeb | C9: RTN, caixa | D9: Governo Central | E9: R$ bi | F9: 13.675 | G9: 15.6 | H9: 32.882 | I9: 59.73 | J9: =IFERROR(F9*FATOR_2016,"n.d.") -> 21.198985 | K9: =IFERROR(G9*FATOR_2019,"n.d.") -> 21.707875 | L9: =IFERROR(H9*FATOR_2022,"n.d.") -> 37.601421 | M9: =IFERROR(K9/J9-1,"n.d.") -> 0.024005432 | N9: =IFERROR(L9/K9-1,"n.d.") -> 0.73215573 | O9: =IFERROR(I9/L9-1,"n.d.") -> 0.58850381 | P9: =IFERROR(I9/J9-1,"n.d.") -> 1.8175878 | Q9: =IFERROR(I9-F9,"n.d.") -> 46.055 | R9: =IFERROR(I9-G9,"n.d.") -> 44.13 | S9: =IFERROR(F9/PIB_2016,"n.d.") -> 0.0021812549 | T9: =IFERROR(G9/PIB_2019,"n.d.") -> 0.002111209 | U9: =IFERROR(H9/PIB_2022,"n.d.") -> 0.003262208 | V9: =IFERROR(I9/PIB_2025,"n.d.") -> 0.0046889108 | W9: STN – RTN tab. 2.1 (S04) | X9: S04 | Y9: STN – RTN tab. 2.1 (S04) | Z9: S04 | AA9: OFICIAL | AB9: Novo Fundeb (EC 108/2020) ampliou a complementação.
A10: 11.6 | B10: Sentenças judiciais e precatórios (custeio e capital) | C10: RTN, caixa | D10: Governo Central | E10: R$ bi | F10: 10.163 | G10: 15.48 | H10: 17.349 | I10: 42.77 | J10: =IFERROR(F10*FATOR_2016,"n.d.") -> 15.754682 | K10: =IFERROR(G10*FATOR_2019,"n.d.") -> 21.540892 | L10: =IFERROR(H10*FATOR_2022,"n.d.") -> 19.839032 | M10: =IFERROR(K10/J10-1,"n.d.") -> 0.36726919 | N10: =IFERROR(L10/K10-1,"n.d.") -> -0.079006005 | O10: =IFERROR(I10/L10-1,"n.d.") -> 1.1558512 | P10: =IFERROR(I10/J10-1,"n.d.") -> 1.7147485 | Q10: =IFERROR(I10-F10,"n.d.") -> 32.607 | R10: =IFERROR(I10-G10,"n.d.") -> 27.29 | S10: =IFERROR(F10/PIB_2016,"n.d.") -> 0.0016210671 | T10: =IFERROR(G10/PIB_2019,"n.d.") -> 0.0020949689 | U10: =IFERROR(H10/PIB_2022,"n.d.") -> 0.0017211863 | V10: =IFERROR(I10/PIB_2025,"n.d.") -> 0.0033575208 | W10: STN – RTN tab. 2.1 (S04) | X10: S04 | Y10: STN – RTN tab. 2.1 (S04) | Z10: S04 | AA10: OFICIAL | AB10: —
A11: 11.7 | B11: Despesas discricionárias do Executivo | C11: RTN, caixa | D11: Governo Central | E11: R$ bi | F11: 141.909 | G11: 164.42 | H11: 152.143 | I11: 204.92 | J11: =IFERROR(F11*FATOR_2016,"n.d.") -> 219.98733 | K11: =IFERROR(G11*FATOR_2019,"n.d.") -> 228.79544 | L11: =IFERROR(H11*FATOR_2022,"n.d.") -> 173.97947 | M11: =IFERROR(K11/J11-1,"n.d.") -> 0.040039183 | N11: =IFERROR(L11/K11-1,"n.d.") -> -0.23958506 | O11: =IFERROR(I11/L11-1,"n.d.") -> 0.17784012 | P11: =IFERROR(I11/J11-1,"n.d.") -> -0.068491798 | Q11: =IFERROR(I11-F11,"n.d.") -> 63.011 | R11: =IFERROR(I11-G11,"n.d.") -> 40.5 | S11: =IFERROR(F11/PIB_2016,"n.d.") -> 0.022635444 | T11: =IFERROR(G11/PIB_2019,"n.d.") -> 0.022251602 | U11: =IFERROR(H11/PIB_2022,"n.d.") -> 0.015094037 | V11: =IFERROR(I11/PIB_2025,"n.d.") -> 0.016086583 | W11: STN – RTN tab. 2.1 (S04) | X11: S04 | Y11: STN – RTN tab. 2.1 (S04) | Z11: S04 | AA11: OFICIAL | AB11: —
A12: 11.8 | B12: Resultado primário do Governo Central | C12: Receita líquida − despesa primária (acima da linha) | D12: Governo Central | E12: R$ bi | F12: -161.276 | G12: -95.065 | H12: 46.408 | I12: -61.69 | J12: =IFERROR(F12*FATOR_2016,"n.d.") -> -250.01005 | K12: =IFERROR(G12*FATOR_2019,"n.d.") -> -132.28584 | L12: =IFERROR(H12*FATOR_2022,"n.d.") -> 53.068753 | M12: =IFERROR(K12/J12-1,"n.d.") -> -0.47087789 | N12: =IFERROR(L12/K12-1,"n.d.") -> -1.4011673 | O12: =IFERROR(I12/L12-1,"n.d.") -> -2.1624543 | P12: =IFERROR(I12/J12-1,"n.d.") -> -0.75324992 | Q12: =IFERROR(I12-F12,"n.d.") -> 99.586 | R12: =IFERROR(I12-G12,"n.d.") -> 33.375 | S12: =IFERROR(F12/PIB_2016,"n.d.") -> -0.025724611 | T12: =IFERROR(G12/PIB_2019,"n.d.") -> -0.012865518 | U12: =IFERROR(H12/PIB_2022,"n.d.") -> 0.0046041162 | V12: =IFERROR(I12/PIB_2025,"n.d.") -> -0.0048427743 | W12: STN – RTN tab. 2.1 (S04) | X12: S04 / S28 | Y12: STN – RTN tab. 2.1 (S04) | Z12: S04 / S28 | AA12: OFICIAL | AB12: 2025 sem as compensações autorizadas (R$ 48,68 bi); com elas o resultado para a meta foi −R$ 13 bi (0,1% PIB). [2016/2022] 2022: divulgação original = superávit de R$ 54,086 bi (S38); série atual = R$ 46,4 bi.
A13: 12.1 | B13: Juros nominais do Governo Central | C13: Apropriados por competência (BCB, abaixo da linha) | D13: Governo Central | E13: R$ bi | F13: 318.362 | G13: 310.12 | H13: 503.234 | I13: 891.88 | J13: =IFERROR(F13*FATOR_2016,"n.d.") -> 493.52476 | K13: =IFERROR(G13*FATOR_2019,"n.d.") -> 431.54143 | L13: =IFERROR(H13*FATOR_2022,"n.d.") -> 575.46114 | M13: =IFERROR(K13/J13-1,"n.d.") -> -0.12559316 | N13: =IFERROR(L13/K13-1,"n.d.") -> 0.3335015 | O13: =IFERROR(I13/L13-1,"n.d.") -> 0.54985269 | P13: =IFERROR(I13/J13-1,"n.d.") -> 0.80716363 | Q13: =IFERROR(I13-F13,"n.d.") -> 573.518 | R13: =IFERROR(I13-G13,"n.d.") -> 581.76 | S13: =IFERROR(F13/PIB_2016,"n.d.") -> 0.050780889 | T13: =IFERROR(G13/PIB_2019,"n.d.") -> 0.041969753 | U13: =IFERROR(H13/PIB_2022,"n.d.") -> 0.049925613 | V13: =IFERROR(I13/PIB_2025,"n.d.") -> 0.07001416 | W13: STN – RTN tab. 2.1 (S04) | X13: BCB via RTN tab. 2.1 linha 9 (S04) | Y13: STN – RTN tab. 2.1 (S04) | Z13: S04 | AA13: OFICIAL | AB13: —
A14: 12 | B14: Despesa total do Governo Central (primária + juros nominais) | C14: Soma: despesa primária (caixa, STN) + juros nominais (competência, BCB) | D14: Governo Central | E14: R$ bi | F14: =F4+F13 -> 1568.788 | G14: =G4+G13 -> 1752.46 | H14: =H4+H13 -> 2312.927 | I14: =I4+I13 -> 3286.13 | J14: =IFERROR(F14*FATOR_2016,"n.d.") -> 2431.9351 | K14: =IFERROR(G14*FATOR_2019,"n.d.") -> 2438.6015 | L14: =IFERROR(H14*FATOR_2022,"n.d.") -> 2644.8921 | M14: =IFERROR(K14/J14-1,"n.d.") -> 0.0027411839 | N14: =IFERROR(L14/K14-1,"n.d.") -> 0.084593806 | O14: =IFERROR(I14/L14-1,"n.d.") -> 0.24244389 | P14: =IFERROR(I14/J14-1,"n.d.") -> 0.35124082 | Q14: =IFERROR(I14-F14,"n.d.") -> 1717.342 | R14: =IFERROR(I14-G14,"n.d.") -> 1533.67 | S14: =IFERROR(F14/PIB_2016,"n.d.") -> 0.25023228 | T14: =IFERROR(G14/PIB_2019,"n.d.") -> 0.23716727 | U14: =IFERROR(H14/PIB_2022,"n.d.") -> 0.22946442 | V14: =IFERROR(I14/PIB_2025,"n.d.") -> 0.25796703 | W14: Cálculo S04 | X14: Cálculo S04 | Y14: Cálculo S04 | Z14: Cálculo S04 | AA14: APROXIMAÇÃO | AB14: Indicador sem publicação oficial única. Soma critérios diferentes (caixa × competência); usar apenas como ordem de grandeza. Ver também o déficit nominal oficial na linha seguinte.
A15: 12.2 | B15: Resultado nominal do Governo Central | C15: BCB, abaixo da linha | D15: Governo Central | E15: R$ bi | F15: -477.835 | G15: -399.01 | H15: -448.288 | I15: -950.57 | J15: =IFERROR(F15*FATOR_2016,"n.d.") -> -740.7398 | K15: =IFERROR(G15*FATOR_2019,"n.d.") -> -555.23457 | L15: =IFERROR(H15*FATOR_2022,"n.d.") -> -512.62897 | M15: =IFERROR(K15/J15-1,"n.d.") -> -0.25043238 | N15: =IFERROR(L15/K15-1,"n.d.") -> -0.076734428 | O15: =IFERROR(I15/L15-1,"n.d.") -> 0.85430411 | P15: =IFERROR(I15/J15-1,"n.d.") -> 0.28327112 | Q15: =IFERROR(I15-F15,"n.d.") -> -472.735 | R15: =IFERROR(I15-G15,"n.d.") -> -551.56 | S15: =IFERROR(F15/PIB_2016,"n.d.") -> -0.07621791 | T15: =IFERROR(G15/PIB_2019,"n.d.") -> -0.053999584 | U15: =IFERROR(H15/PIB_2022,"n.d.") -> -0.044474445 | V15: =IFERROR(I15/PIB_2025,"n.d.") -> -0.074621429 | W15: STN – RTN tab. 2.1 (S04) | X15: S04 | Y15: STN – RTN tab. 2.1 (S04) | Z15: S04 | AA15: OFICIAL | AB15: —
A16: 9 | B16: Gastos da União – despesa paga (OFSS), sem refinanciamento | C16: Despesas pagas no exercício, exceto intra-orçamentárias; inclui juros e amortização | D16: União | E16: R$ bi | F16: 1875.18 | G16: 2198.25 | H16: 2603.83 | I16: 3606.51 | J16: =IFERROR(F16*FATOR_2016,"n.d.") -> 2906.904 | K16: =IFERROR(G16*FATOR_2019,"n.d.") -> 3058.9319 | L16: =IFERROR(H16*FATOR_2022,"n.d.") -> 2977.5472 | M16: =IFERROR(K16/J16-1,"n.d.") -> 0.0522989 | N16: =IFERROR(L16/K16-1,"n.d.") -> -0.02660558 | O16: =IFERROR(I16/L16-1,"n.d.") -> 0.2112352 | P16: =IFERROR(I16/J16-1,"n.d.") -> 0.24067049 | Q16: =IFERROR(I16-F16,"n.d.") -> 1731.33 | R16: =IFERROR(I16-G16,"n.d.") -> 1408.26 | S16: =IFERROR(F16/PIB_2016,"n.d.") -> 0.29910388 | T16: =IFERROR(G16/PIB_2019,"n.d.") -> 0.29749777 | U16: =IFERROR(H16/PIB_2022,"n.d.") -> 0.25832477 | V16: =IFERROR(I16/PIB_2025,"n.d.") -> 0.28311742 | W16: RREO Anexo 01 (S05) | X16: RREO Anexo 01 (S05) | Y16: RREO Anexo 01 (S05) | Z16: S05 | AA16: OFICIAL | AB16: Não inclui restos a pagar pagos nem refinanciamento da dívida.
A17: 9.1 | B17: Gastos da União – despesa paga com refinanciamento | C17: Total pago (inclui intra-orçamentárias e refinanciamento) | D17: União | E17: R$ bi | F17: 2572.18 | G17: 2710.91 | H17: 4059.5 | I17: 5054.25 | J17: =IFERROR(F17*FATOR_2016,"n.d.") -> 3987.3934 | K17: =IFERROR(G17*FATOR_2019,"n.d.") -> 3772.3139 | L17: =IFERROR(H17*FATOR_2022,"n.d.") -> 4642.1436 | M17: =IFERROR(K17/J17-1,"n.d.") -> -0.053939872 | N17: =IFERROR(L17/K17-1,"n.d.") -> 0.23058255 | O17: =IFERROR(I17/L17-1,"n.d.") -> 0.088775011 | P17: =IFERROR(I17/J17-1,"n.d.") -> 0.26755741 | Q17: =IFERROR(I17-F17,"n.d.") -> 2482.07 | R17: =IFERROR(I17-G17,"n.d.") -> 2343.34 | S17: =IFERROR(F17/PIB_2016,"n.d.") -> 0.41028008 | T17: =IFERROR(G17/PIB_2019,"n.d.") -> 0.36687805 | U17: =IFERROR(H17/PIB_2022,"n.d.") -> 0.40274112 | V17: =IFERROR(I17/PIB_2025,"n.d.") -> 0.39676758 | W17: RREO Anexo 01 (S05) | X17: S05 | Y17: RREO Anexo 01 (S05) | Z17: S05 | AA17: OFICIAL | AB17: —
A18: 9.2 | B18: LOA – dotação inicial total (com refinanciamento) | C18: Orçamentos Fiscal e da Seguridade Social | D18: União | E18: R$ bi | F18: 2953.55 | G18: 3262.2 | H18: 4726.93 | I18: 5719.39 | J18: =IFERROR(F18*FATOR_2016,"n.d.") -> 4578.5931 | K18: =IFERROR(G18*FATOR_2019,"n.d.") -> 4539.4507 | L18: =IFERROR(H18*FATOR_2022,"n.d.") -> 5405.3672 | M18: =IFERROR(K18/J18-1,"n.d.") -> -0.0085490046 | N18: =IFERROR(L18/K18-1,"n.d.") -> 0.19075358 | O18: =IFERROR(I18/L18-1,"n.d.") -> 0.058094633 | P18: =IFERROR(I18/J18-1,"n.d.") -> 0.24915882 | Q18: =IFERROR(I18-F18,"n.d.") -> 2765.84 | R18: =IFERROR(I18-G18,"n.d.") -> 2457.19 | S18: =IFERROR(F18/PIB_2016,"n.d.") -> 0.47111117 | T18: =IFERROR(G18/PIB_2019,"n.d.") -> 0.44148629 | U18: =IFERROR(H18/PIB_2022,"n.d.") -> 0.46895654 | V18: =IFERROR(I18/PIB_2025,"n.d.") -> 0.44898225 | W18: RREO Anexo 01 (S05) | X18: S05 | Y18: RREO Anexo 01 (S05) | Z18: S05 | AA18: OFICIAL | AB18: Previsão ≠ execução.
A20: Notas metodológicas
A21: 1. Despesa primária (RTN, caixa) ≠ despesa orçamentária paga (RREO).
A22: 2. A 'despesa total do Governo Central' é aproximação (soma de critérios distintos).
A23: 3. Valores nominais do próprio ano (R$ bilhões, salvo indicação). Correção para R$ de dez/2025 pelo IPCA: fator = índice dez/2025 ÷ índice de dezembro do ano (FATOR_2016, FATOR_2019, FATOR_2022 na aba 'Resumo executivo').
A24: 4. Colunas de variação: para valores em R$ = variação REAL (IPCA); para US$ e pessoas = variação nominal; para taxas e % = diferença em pontos percentuais (p.p.).
A25: 5. % do PIB com o PIB anual do IBGE (SIDRA 1846) de cada ano; valores em US$ usam o PIB convertido pela PTAX média anual.
A26: 6. 'n.a.' = não se aplica; 'n.d.' = não disponível (algum ano 'não localizado após busca'). Azul = dado digitado da fonte; preto = fórmula; verde = vínculo com outra aba.
A27: 7. Cor da linha = classificação do dado em 2019/2025; células de 2016/2022 com cor própria quando a classificação difere (ex.: estimado, não localizado).
A28: 8. Períodos 2016→2019, 2019→2022 e 2022→2025 correspondem aproximadamente aos mandatos Temer, Bolsonaro e Lula III (até 2025); 2016 inclui o governo Dilma até maio.

Sheet Dívida e juros
A1: Dívida pública, juros, amortização e refinanciamento
A2: Estoques em 31 de dezembro (dívida) e fluxos anuais (juros, amortização, refinanciamento).
A3: Código | B3: Indicador | C3: Conceito / estágio | D3: Âmbito | E3: Unidade | F3: Brasil 2016 | G3: Brasil 2019 | H3: Brasil 2022 | I3: Brasil 2025 | J3: 2016 em R$ de dez/2025 | K3: 2019 em R$ de dez/2025 | L3: 2022 em R$ de dez/2025 | M3: Variação 2016→2019 | N3: Variação 2019→2022 | O3: Variação 2022→2025 | P3: Variação 2016→2025 | Q3: Diferença absoluta 2025−2016 (nominal) | R3: Diferença absoluta 2025−2019 (nominal) | S3: 2016 % do PIB | T3: 2019 % do PIB | U3: 2022 % do PIB | V3: 2025 % do PIB | W3: Fonte 2016 | X3: Fonte 2019 | Y3: Fonte 2022 | Z3: Fonte 2025 | AA3: Classificação do dado | AB3: Observações metodológicas
A4: 13 | B4: Dívida Pública Federal (DPF) | C4: Estoque em 31/dez (interna + externa) | D4: União | E4: R$ bi | F4: 3113 | G4: 4248 | H4: 5951 | I4: 8635 | J4: =IFERROR(F4*FATOR_2016,"n.d.") -> 4825.7725 | K4: =IFERROR(G4*FATOR_2019,"n.d.") -> 5911.2215 | L4: =IFERROR(H4*FATOR_2022,"n.d.") -> 6805.123 | M4: =IFERROR(K4/J4-1,"n.d.") -> 0.2249275 | N4: =IFERROR(L4/K4-1,"n.d.") -> 0.15122112 | O4: =IFERROR(I4/L4-1,"n.d.") -> 0.26889698 | P4: =IFERROR(I4/J4-1,"n.d.") -> 0.78935082 | Q4: =IFERROR(I4-F4,"n.d.") -> 5522 | R4: =IFERROR(I4-G4,"n.d.") -> 4387 | S4: =IFERROR(F4/PIB_2016,"n.d.") -> 0.49654453 | T4: =IFERROR(G4/PIB_2019,"n.d.") -> 0.57489846 | U4: =IFERROR(H4/PIB_2022,"n.d.") -> 0.59039596 | V4: =IFERROR(I4/PIB_2025,"n.d.") -> 0.6778628 | W4: Tesouro – RMD (S30) | X4: Tesouro – RMD (S11) | Y4: Tesouro – RMD (S30) | Z4: S11 | AA4: OFICIAL | AB4: Estoque; não somar com fluxos.
A5: 13.1 | B5: Dívida Pública Mobiliária Federal interna (DPMFi) | C5: Estoque em 31/dez | D5: União | E5: R$ bi | F5: 2986 | G5: 4083 | H5: 5698 | I5: 8309 | J5: =IFERROR(F5*FATOR_2016,"n.d.") -> 4628.8971 | K5: =IFERROR(G5*FATOR_2019,"n.d.") -> 5681.6189 | L5: =IFERROR(H5*FATOR_2022,"n.d.") -> 6515.8109 | M5: =IFERROR(K5/J5-1,"n.d.") -> 0.22742389 | N5: =IFERROR(L5/K5-1,"n.d.") -> 0.14682294 | O5: =IFERROR(I5/L5-1,"n.d.") -> 0.27520582 | P5: =IFERROR(I5/J5-1,"n.d.") -> 0.79502802 | Q5: =IFERROR(I5-F5,"n.d.") -> 5323 | R5: =IFERROR(I5-G5,"n.d.") -> 4226 | S5: =IFERROR(F5/PIB_2016,"n.d.") -> 0.47628717 | T5: =IFERROR(G5/PIB_2019,"n.d.") -> 0.55256836 | U5: =IFERROR(H5/PIB_2022,"n.d.") -> 0.56529595 | V5: =IFERROR(I5/PIB_2025,"n.d.") -> 0.65227122 | W5: S30 | X5: S11 | Y5: S30 | Z5: S11 | AA5: OFICIAL | AB5: —
A6: 14 | B6: Dívida Bruta do Governo Geral (DBGG) | C6: Estoque em dez (União + estados + municípios; exclui BCB e estatais) | D6: Governo Geral | E6: R$ bi | F6: 4378.4864 | G6: 5500.1042 | H6: 7224.8822 | I6: 10017.919 | J6: =IFERROR(F6*FATOR_2016,"n.d.") -> 6787.5295 | K6: =IFERROR(G6*FATOR_2019,"n.d.") -> 7653.5625 | L6: =IFERROR(H6*FATOR_2022,"n.d.") -> 8261.8404 | M6: =IFERROR(K6/J6-1,"n.d.") -> 0.1275918 | N6: =IFERROR(L6/K6-1,"n.d.") -> 0.079476435 | O6: =IFERROR(I6/L6-1,"n.d.") -> 0.21255297 | P6: =IFERROR(I6/J6-1,"n.d.") -> 0.47593011 | Q6: =IFERROR(I6-F6,"n.d.") -> 5639.4327 | R6: =IFERROR(I6-G6,"n.d.") -> 4517.815 | S6: =IFERROR(F6/PIB_2016,"n.d.") -> 0.69839815 | T6: =IFERROR(G6/PIB_2019,"n.d.") -> 0.74435061 | U6: =IFERROR(H6/PIB_2022,"n.d.") -> 0.71677723 | V6: =IFERROR(I6/PIB_2025,"n.d.") -> 0.7864244 | W6: BCB SGS (S08) | X6: BCB SGS 13761 (S08) | Y6: BCB SGS (S08) | Z6: S08 | AA6: OFICIAL | AB6: DBGG ≠ DPF: inclui dívida de estados/municípios e operações compromissadas do BCB; exclui títulos na carteira do BCB.
A7: 14.1 | B7: DBGG em % do PIB (BCB) | C7: Estoque/PIB 12 meses (BCB) | D7: Governo Geral | E7: % do PIB | F7: 0.6984 | G7: 0.7444 | H7: 0.7168 | I7: 0.7864 | J7: n.a. | K7: n.a. | L7: n.a. | M7: =IFERROR((G7-F7)*100,"n.d.") -> 4.6 | N7: =IFERROR((H7-G7)*100,"n.d.") -> -2.76 | O7: =IFERROR((I7-H7)*100,"n.d.") -> 6.96 | P7: =IFERROR((I7-F7)*100,"n.d.") -> 8.8 | Q7: =IFERROR((I7-F7)*100,"n.d.") -> 8.8 | R7: =IFERROR((I7-G7)*100,"n.d.") -> 4.2 | S7: =IF(ISNUMBER(F7),F7,"n.d.") -> 0.6984 | T7: =IF(ISNUMBER(G7),G7,"n.d.") -> 0.7444 | U7: =IF(ISNUMBER(H7),H7,"n.d.") -> 0.7168 | V7: =IF(ISNUMBER(I7),I7,"n.d.") -> 0.7864 | W7: BCB SGS (S08) | X7: BCB SGS 13762 (S08) | Y7: BCB SGS (S08) | Z7: S08 | AA7: OFICIAL | AB7: Imprensa arredondou 2025 para 78,7%.
A8: 15 | B8: Dívida Líquida do Setor Público (DLSP) | C8: Estoque em dez (setor público consolidado, inclui BCB e estatais não financeiras) | D8: Setor público consolidado | E8: R$ bi | F8: 2892.9135 | G8: 4041.7688 | H8: 5658.0169 | I8: 8311.0858 | J8: =IFERROR(F8*FATOR_2016,"n.d.") -> 4484.5944 | K8: =IFERROR(G8*FATOR_2019,"n.d.") -> 5624.2444 | L8: =IFERROR(H8*FATOR_2022,"n.d.") -> 6470.0892 | M8: =IFERROR(K8/J8-1,"n.d.") -> 0.25412556 | N8: =IFERROR(L8/K8-1,"n.d.") -> 0.1503926 | O8: =IFERROR(I8/L8-1,"n.d.") -> 0.2845396 | P8: =IFERROR(I8/J8-1,"n.d.") -> 0.85325251 | Q8: =IFERROR(I8-F8,"n.d.") -> 5418.1723 | R8: =IFERROR(I8-G8,"n.d.") -> 4269.317 | S8: =IFERROR(F8/PIB_2016,"n.d.") -> 0.46143924 | T8: =IFERROR(G8/PIB_2019,"n.d.") -> 0.54698838 | U8: =IFERROR(H8/PIB_2022,"n.d.") -> 0.56132924 | V8: =IFERROR(I8/PIB_2025,"n.d.") -> 0.65243496 | W8: BCB SGS (S08) | X8: BCB SGS 4478 (S08) | Y8: BCB SGS (S08) | Z8: S08 | AA8: OFICIAL | AB8: —
A9: 15.1 | B9: DLSP em % do PIB (BCB) | C9: Estoque/PIB 12 meses (BCB) | D9: Setor público consolidado | E9: % do PIB | F9: 0.4614 | G9: 0.547 | H9: 0.5613 | I9: 0.6524 | J9: n.a. | K9: n.a. | L9: n.a. | M9: =IFERROR((G9-F9)*100,"n.d.") -> 8.56 | N9: =IFERROR((H9-G9)*100,"n.d.") -> 1.43 | O9: =IFERROR((I9-H9)*100,"n.d.") -> 9.11 | P9: =IFERROR((I9-F9)*100,"n.d.") -> 19.1 | Q9: =IFERROR((I9-F9)*100,"n.d.") -> 19.1 | R9: =IFERROR((I9-G9)*100,"n.d.") -> 10.54 | S9: =IF(ISNUMBER(F9),F9,"n.d.") -> 0.4614 | T9: =IF(ISNUMBER(G9),G9,"n.d.") -> 0.547 | U9: =IF(ISNUMBER(H9),H9,"n.d.") -> 0.5613 | V9: =IF(ISNUMBER(I9),I9,"n.d.") -> 0.6524 | W9: BCB SGS (S08) | X9: BCB SGS 4513 (S08) | Y9: BCB SGS (S08) | Z9: S08 | AA9: OFICIAL | AB9: Imprensa arredondou 2025 para 65,3%.
A10: 18 | B10: Juros nominais pagos – juros e encargos da dívida (orçamento) | C10: GND 2, valor pago no exercício (caixa) | D10: União | E10: R$ bi | F10: 204.89 | G10: 285.09 | H10: 247.31 | I10: 363.47 | J10: =IFERROR(F10*FATOR_2016,"n.d.") -> 317.62047 | K10: =IFERROR(G10*FATOR_2019,"n.d.") -> 396.71142 | L10: =IFERROR(H10*FATOR_2022,"n.d.") -> 282.80541 | M10: =IFERROR(K10/J10-1,"n.d.") -> 0.24901087 | N10: =IFERROR(L10/K10-1,"n.d.") -> -0.28712563 | O10: =IFERROR(I10/L10-1,"n.d.") -> 0.28523003 | P10: =IFERROR(I10/J10-1,"n.d.") -> 0.14435319 | Q10: =IFERROR(I10-F10,"n.d.") -> 158.58 | R10: =IFERROR(I10-G10,"n.d.") -> 78.38 | S10: =IFERROR(F10/PIB_2016,"n.d.") -> 0.032681339 | T10: =IFERROR(G10/PIB_2019,"n.d.") -> 0.038582345 | U10: =IFERROR(H10/PIB_2022,"n.d.") -> 0.024535511 | V10: =IFERROR(I10/PIB_2025,"n.d.") -> 0.028533039 | W10: RREO Anexo 01 (S05) | X10: RREO Anexo 01 (S05) | Y10: RREO Anexo 01 (S05) | Z10: S05 | AA10: OFICIAL | AB10: Pagamento orçamentário; difere dos juros apropriados (competência) do BCB. Não há estatística oficial de juros 'pagos' do setor público consolidado.
A11: 19 | B11: Juros nominais líquidos apropriados – setor público consolidado | C11: Competência, líquidos de juros ativos (BCB/NFSP) | D11: Setor público consolidado | E11: R$ bi | F11: 407.024 | G11: 367.282 | H11: 586.4 | I11: 1007.6 | J11: =IFERROR(F11*FATOR_2016,"n.d.") -> 630.96859 | K11: =IFERROR(G11*FATOR_2019,"n.d.") -> 511.0841 | L11: =IFERROR(H11*FATOR_2022,"n.d.") -> 670.56362 | M11: =IFERROR(K11/J11-1,"n.d.") -> -0.19000074 | N11: =IFERROR(L11/K11-1,"n.d.") -> 0.31204166 | O11: =IFERROR(I11/L11-1,"n.d.") -> 0.50261655 | P11: =IFERROR(I11/J11-1,"n.d.") -> 0.59690991 | Q11: =IFERROR(I11-F11,"n.d.") -> 600.576 | R11: =IFERROR(I11-G11,"n.d.") -> 640.318 | S11: =IFERROR(F11/PIB_2016,"n.d.") -> 0.064923077 | T11: =IFERROR(G11/PIB_2019,"n.d.") -> 0.04970571 | U11: =IFERROR(H11/PIB_2022,"n.d.") -> 0.058176473 | V11: =IFERROR(I11/PIB_2025,"n.d.") -> 0.079098385 | W11: BCB (S31) | X11: BCB via Agência Brasil (S09) | Y11: BCB (S31) | Z11: BCB via Poder360 (S10) | AA11: OFICIAL | AB11: Governo Central (juros nominais BCB): 310,1 (2019) e 891,9 (2025) – ver aba Despesas. 2025 inclui ganho de R$ 105,9 bi com swaps cambiais (redutor).
A12: 19.1 | B12: Juros nominais do setor público em % do PIB (publicado) | C12: BCB | D12: Setor público consolidado | E12: % do PIB | F12: 0.0646 | G12: 0.0506 | H12: 0.0596 | I12: 0.0791 | J12: n.a. | K12: n.a. | L12: n.a. | M12: =IFERROR((G12-F12)*100,"n.d.") -> -1.4 | N12: =IFERROR((H12-G12)*100,"n.d.") -> 0.9 | O12: =IFERROR((I12-H12)*100,"n.d.") -> 1.95 | P12: =IFERROR((I12-F12)*100,"n.d.") -> 1.45 | Q12: =IFERROR((I12-F12)*100,"n.d.") -> 1.45 | R12: =IFERROR((I12-G12)*100,"n.d.") -> 2.85 | S12: =IF(ISNUMBER(F12),F12,"n.d.") -> 0.0646 | T12: =IF(ISNUMBER(G12),G12,"n.d.") -> 0.0506 | U12: =IF(ISNUMBER(H12),H12,"n.d.") -> 0.0596 | V12: =IF(ISNUMBER(I12),I12,"n.d.") -> 0.0791 | W12: S31 | X12: S09 | Y12: S31 | Z12: S10 | AA12: OFICIAL | AB12: 2019 publicado com PIB anterior à revisão; com PIB atual equivale a 4,97%. [2016/2022] Percentuais publicados com a série de PIB da época.
A13: 19.2 | B13: Resultado primário do setor público consolidado | C13: BCB, abaixo da linha | D13: Setor público consolidado | E13: R$ bi | F13: -155.791 | G13: -61.872 | H13: 126 | I13: -55.021 | J13: =IFERROR(F13*FATOR_2016,"n.d.") -> -241.5072 | K13: =IFERROR(G13*FATOR_2019,"n.d.") -> -86.096773 | L13: =IFERROR(H13*FATOR_2022,"n.d.") -> 144.08427 | M13: =IFERROR(K13/J13-1,"n.d.") -> -0.64350226 | N13: =IFERROR(L13/K13-1,"n.d.") -> -2.6735153 | O13: =IFERROR(I13/L13-1,"n.d.") -> -1.3818668 | P13: =IFERROR(I13/J13-1,"n.d.") -> -0.77217657 | Q13: =IFERROR(I13-F13,"n.d.") -> 100.77 | R13: =IFERROR(I13-G13,"n.d.") -> 6.851 | S13: =IFERROR(F13/PIB_2016,"n.d.") -> -0.024849717 | T13: =IFERROR(G13/PIB_2019,"n.d.") -> -0.0083733798 | U13: =IFERROR(H13/PIB_2022,"n.d.") -> 0.012500402 | V13: =IFERROR(I13/PIB_2025,"n.d.") -> -0.004319246 | W13: S31 | X13: S09 | Y13: S31 | Z13: S10 | AA13: OFICIAL | AB13: —
A14: 19.3 | B14: Resultado nominal do setor público consolidado | C14: Primário − juros nominais | D14: Setor público consolidado | E14: R$ bi | F14: =F13-F11 -> -562.815 | G14: =G13-G11 -> -429.154 | H14: =H13-H11 -> -460.4 | I14: -1062.6 | J14: =IFERROR(F14*FATOR_2016,"n.d.") -> -872.4758 | K14: =IFERROR(G14*FATOR_2019,"n.d.") -> -597.18087 | L14: =IFERROR(H14*FATOR_2022,"n.d.") -> -526.47935 | M14: =IFERROR(K14/J14-1,"n.d.") -> -0.31553303 | N14: =IFERROR(L14/K14-1,"n.d.") -> -0.11839213 | O14: =IFERROR(I14/L14-1,"n.d.") -> 1.0183128 | P14: =IFERROR(I14/J14-1,"n.d.") -> 0.21791344 | Q14: =IFERROR(I14-F14,"n.d.") -> -499.785 | R14: =IFERROR(I14-G14,"n.d.") -> -633.446 | S14: =IFERROR(F14/PIB_2016,"n.d.") -> -0.089772794 | T14: =IFERROR(G14/PIB_2019,"n.d.") -> -0.058079089 | U14: =IFERROR(H14/PIB_2022,"n.d.") -> -0.045676071 | V14: =IFERROR(I14/PIB_2025,"n.d.") -> -0.083415983 | W14: Cálculo sobre S31 | X14: Cálculo sobre S09 | Y14: Cálculo sobre S31 | Z14: S10 | AA14: OFICIAL | AB14: 2019 calculado (primário + juros, mesmos conceitos BCB); 2025 publicado. [2016/2022] 2022 publicado: déficit nominal de R$ 460 bi.
A15: 19.4 | B15: NFSP nominal em % do PIB (BCB) | C15: Déficit nominal acumulado 12 meses | D15: Setor público consolidado | E15: % do PIB | F15: 0.0898 | G15: 0.0581 | H15: 0.0457 | I15: 0.0834 | J15: n.a. | K15: n.a. | L15: n.a. | M15: =IFERROR((G15-F15)*100,"n.d.") -> -3.17 | N15: =IFERROR((H15-G15)*100,"n.d.") -> -1.24 | O15: =IFERROR((I15-H15)*100,"n.d.") -> 3.77 | P15: =IFERROR((I15-F15)*100,"n.d.") -> -0.64 | Q15: =IFERROR((I15-F15)*100,"n.d.") -> -0.64 | R15: =IFERROR((I15-G15)*100,"n.d.") -> 2.53 | S15: =IF(ISNUMBER(F15),F15,"n.d.") -> 0.0898 | T15: =IF(ISNUMBER(G15),G15,"n.d.") -> 0.0581 | U15: =IF(ISNUMBER(H15),H15,"n.d.") -> 0.0457 | V15: =IF(ISNUMBER(I15),I15,"n.d.") -> 0.0834 | W15: BCB SGS (S08) | X15: BCB SGS 5727 (S08) | Y15: BCB SGS (S08) | Z15: S08 | AA15: OFICIAL | AB15: —
A16: 20 | B16: Amortizações da dívida (exceto refinanciamento) | C16: GND 6, pago no exercício | D16: União | E16: R$ bi | F16: 271.44 | G16: 275.69 | H16: 207.09 | I16: 353.98 | J16: =IFERROR(F16*FATOR_2016,"n.d.") -> 420.78628 | K16: =IFERROR(G16*FATOR_2019,"n.d.") -> 383.63104 | L16: =IFERROR(H16*FATOR_2022,"n.d.") -> 236.81279 | M16: =IFERROR(K16/J16-1,"n.d.") -> -0.088299561 | N16: =IFERROR(L16/K16-1,"n.d.") -> -0.3827069 | O16: =IFERROR(I16/L16-1,"n.d.") -> 0.49476723 | P16: =IFERROR(I16/J16-1,"n.d.") -> -0.15876535 | Q16: =IFERROR(I16-F16,"n.d.") -> 82.54 | R16: =IFERROR(I16-G16,"n.d.") -> 78.29 | S16: =IFERROR(F16/PIB_2016,"n.d.") -> 0.043296513 | T16: =IFERROR(G16/PIB_2019,"n.d.") -> 0.037310206 | U16: =IFERROR(H16/PIB_2022,"n.d.") -> 0.020545303 | V16: =IFERROR(I16/PIB_2025,"n.d.") -> 0.027788057 | W16: RREO Anexo 01 (S05) | X16: RREO Anexo 01 (S05) | Y16: RREO Anexo 01 (S05) | Z16: S05 | AA16: OFICIAL | AB16: Fluxo; não confundir com refinanciamento (rolagem com emissão de títulos).
A17: 21 | B17: Refinanciamento da dívida | C17: Amortização paga com recursos de emissão de títulos (rolagem) | D17: União | E17: R$ bi | F17: 653.82 | G17: 476.78 | H17: 1425.07 | I17: 1417.64 | J17: =IFERROR(F17*FATOR_2016,"n.d.") -> 1013.5517 | K17: =IFERROR(G17*FATOR_2019,"n.d.") -> 663.4539 | L17: =IFERROR(H17*FATOR_2022,"n.d.") -> 1629.6045 | M17: =IFERROR(K17/J17-1,"n.d.") -> -0.34541684 | N17: =IFERROR(L17/K17-1,"n.d.") -> 1.4562438 | O17: =IFERROR(I17/L17-1,"n.d.") -> -0.13007115 | P17: =IFERROR(I17/J17-1,"n.d.") -> 0.39868537 | Q17: =IFERROR(I17-F17,"n.d.") -> 763.82 | R17: =IFERROR(I17-G17,"n.d.") -> 940.86 | S17: =IFERROR(F17/PIB_2016,"n.d.") -> 0.10428871 | T17: =IFERROR(G17/PIB_2019,"n.d.") -> 0.064524502 | U17: =IFERROR(H17/PIB_2022,"n.d.") -> 0.14138054 | V17: =IFERROR(I17/PIB_2025,"n.d.") -> 0.11128725 | W17: RREO Anexo 01 (S05) | X17: RREO Anexo 01 (S05) | Y17: RREO Anexo 01 (S05) | Z17: S05 | AA17: OFICIAL | AB17: Dotação inicial: 714,09 (2019) e 1.655,91 (2025).
A18: 21.1 | B18: Refinanciamento – dotação inicial na LOA | C18: Previsão orçamentária | D18: União | E18: R$ bi | F18: 766.75 | G18: 714.09 | H18: 1838.02 | I18: 1655.91 | J18: =IFERROR(F18*FATOR_2016,"n.d.") -> 1188.6158 | K18: =IFERROR(G18*FATOR_2019,"n.d.") -> 993.678 | L18: =IFERROR(H18*FATOR_2022,"n.d.") -> 2101.8236 | M18: =IFERROR(K18/J18-1,"n.d.") -> -0.16400407 | N18: =IFERROR(L18/K18-1,"n.d.") -> 1.1151959 | O18: =IFERROR(I18/L18-1,"n.d.") -> -0.21215557 | P18: =IFERROR(I18/J18-1,"n.d.") -> 0.39314147 | Q18: =IFERROR(I18-F18,"n.d.") -> 889.16 | R18: =IFERROR(I18-G18,"n.d.") -> 941.82 | S18: =IFERROR(F18/PIB_2016,"n.d.") -> 0.1223018 | T18: =IFERROR(G18/PIB_2019,"n.d.") -> 0.096640593 | U18: =IFERROR(H18/PIB_2022,"n.d.") -> 0.18234912 | V18: =IFERROR(I18/PIB_2025,"n.d.") -> 0.12999187 | W18: RREO Anexo 01 (S05) | X18: S05 | Y18: RREO Anexo 01 (S05) | Z18: S05 | AA18: OFICIAL | AB18: Previsão ≠ execução.
A19: 18.1 | B19: Juros e encargos – dotação inicial na LOA | C19: Previsão orçamentária | D19: União | E19: R$ bi | F19: 304.1 | G19: 378.9 | H19: 351.42 | I19: 480.01 | J19: =IFERROR(F19*FATOR_2016,"n.d.") -> 471.41581 | K19: =IFERROR(G19*FATOR_2019,"n.d.") -> 527.2509 | L19: =IFERROR(H19*FATOR_2022,"n.d.") -> 401.85789 | M19: =IFERROR(K19/J19-1,"n.d.") -> 0.11844127 | N19: =IFERROR(L19/K19-1,"n.d.") -> -0.23782416 | O19: =IFERROR(I19/L19-1,"n.d.") -> 0.19447697 | P19: =IFERROR(I19/J19-1,"n.d.") -> 0.018230591 | Q19: =IFERROR(I19-F19,"n.d.") -> 175.91 | R19: =IFERROR(I19-G19,"n.d.") -> 101.11 | S19: =IFERROR(F19/PIB_2016,"n.d.") -> 0.048506004 | T19: =IFERROR(G19/PIB_2019,"n.d.") -> 0.051278019 | U19: =IFERROR(H19/PIB_2022,"n.d.") -> 0.034864216 | V19: =IFERROR(I19/PIB_2025,"n.d.") -> 0.037681635 | W19: RREO Anexo 01 (S05) | X19: S05 | Y19: RREO Anexo 01 (S05) | Z19: S05 | AA19: OFICIAL | AB19: —
A21: Notas metodológicas
A22: 1. Estoques não são somados a fluxos.
A23: 2. DPF (Tesouro) ≠ DBGG (BCB) ≠ DLSP (BCB).
A24: 3. Juros pagos (orçamento, caixa) ≠ juros apropriados (BCB, competência). Refinanciamento = rolagem.
A25: 4. Valores nominais do próprio ano (R$ bilhões, salvo indicação). Correção para R$ de dez/2025 pelo IPCA: fator = índice dez/2025 ÷ índice de dezembro do ano (FATOR_2016, FATOR_2019, FATOR_2022 na aba 'Resumo executivo').
A26: 5. Colunas de variação: para valores em R$ = variação REAL (IPCA); para US$ e pessoas = variação nominal; para taxas e % = diferença em pontos percentuais (p.p.).
A27: 6. % do PIB com o PIB anual do IBGE (SIDRA 1846) de cada ano; valores em US$ usam o PIB convertido pela PTAX média anual.
A28: 7. 'n.a.' = não se aplica; 'n.d.' = não disponível (algum ano 'não localizado após busca'). Azul = dado digitado da fonte; preto = fórmula; verde = vínculo com outra aba.
A29: 8. Cor da linha = classificação do dado em 2019/2025; células de 2016/2022 com cor própria quando a classificação difere (ex.: estimado, não localizado).
A30: 9. Períodos 2016→2019, 2019→2022 e 2022→2025 correspondem aproximadamente aos mandatos Temer, Bolsonaro e Lula III (até 2025); 2016 inclui o governo Dilma até maio.

Sheet LOA e execução orçamentária
A1: LOA e execução orçamentária da União – despesa total e investimentos
A2: Estágios: dotação inicial → dotação atualizada → empenho → liquidação → pagamento (RREO, 6º bimestre).
A3: Código | B3: Indicador | C3: Conceito / estágio | D3: Âmbito | E3: Unidade | F3: Brasil 2016 | G3: Brasil 2019 | H3: Brasil 2022 | I3: Brasil 2025 | J3: 2016 em R$ de dez/2025 | K3: 2019 em R$ de dez/2025 | L3: 2022 em R$ de dez/2025 | M3: Variação 2016→2019 | N3: Variação 2019→2022 | O3: Variação 2022→2025 | P3: Variação 2016→2025 | Q3: Diferença absoluta 2025−2016 (nominal) | R3: Diferença absoluta 2025−2019 (nominal) | S3: 2016 % do PIB | T3: 2019 % do PIB | U3: 2022 % do PIB | V3: 2025 % do PIB | W3: Fonte 2016 | X3: Fonte 2019 | Y3: Fonte 2022 | Z3: Fonte 2025 | AA3: Classificação do dado | AB3: Observações metodológicas
A4: 9.3 | B4: Despesa total da União (exceto intra-orçamentárias) | C4: Dotação inicial (LOA) | D4: União | E4: R$ bi | F4: 2141.17 | G4: 2504.68 | H4: 2854.31 | I4: 4028.7 | J4: =IFERROR(F4*FATOR_2016,"n.d.") -> 3319.2417 | K4: =IFERROR(G4*FATOR_2019,"n.d.") -> 3485.3385 | L4: =IFERROR(H4*FATOR_2022,"n.d.") -> 3263.9776 | M4: =IFERROR(K4/J4-1,"n.d.") -> 0.050040609 | N4: =IFERROR(L4/K4-1,"n.d.") -> -0.063512038 | O4: =IFERROR(I4/L4-1,"n.d.") -> 0.23429156 | P4: =IFERROR(I4/J4-1,"n.d.") -> 0.21374109 | Q4: =IFERROR(I4-F4,"n.d.") -> 1887.53 | R4: =IFERROR(I4-G4,"n.d.") -> 1524.02 | S4: =IFERROR(F4/PIB_2016,"n.d.") -> 0.34153108 | T4: =IFERROR(G4/PIB_2019,"n.d.") -> 0.33896814 | U4: =IFERROR(H4/PIB_2022,"n.d.") -> 0.28317478 | V4: =IFERROR(I4/PIB_2025,"n.d.") -> 0.31626009 | W4: RREO Anexo 01 (S05) | X4: RREO Anexo 01 (S05) | Y4: RREO Anexo 01 (S05) | Z4: RREO Anexo 01 (S05) | AA4: OFICIAL | AB4: Exclui intra-orçamentárias.
A5: 9.3 | B5: Despesa total da União (exceto intra-orçamentárias) | C5: Dotação atualizada | D5: União | E5: R$ bi | F5: 2188.92 | G5: 2556.5 | H5: 3067.02 | I5: 4144.73 | J5: =IFERROR(F5*FATOR_2016,"n.d.") -> 3393.2637 | K5: =IFERROR(G5*FATOR_2019,"n.d.") -> 3557.4477 | L5: =IFERROR(H5*FATOR_2022,"n.d.") -> 3507.217 | M5: =IFERROR(K5/J5-1,"n.d.") -> 0.048385256 | N5: =IFERROR(L5/K5-1,"n.d.") -> -0.014119858 | O5: =IFERROR(I5/L5-1,"n.d.") -> 0.18177176 | P5: =IFERROR(I5/J5-1,"n.d.") -> 0.22145826 | Q5: =IFERROR(I5-F5,"n.d.") -> 1955.81 | R5: =IFERROR(I5-G5,"n.d.") -> 1588.23 | S5: =IFERROR(F5/PIB_2016,"n.d.") -> 0.34914752 | T5: =IFERROR(G5/PIB_2019,"n.d.") -> 0.34598114 | U5: =IFERROR(H5/PIB_2022,"n.d.") -> 0.30427764 | V5: =IFERROR(I5/PIB_2025,"n.d.") -> 0.32536865 | W5: RREO Anexo 01 (S05) | X5: RREO Anexo 01 (S05) | Y5: RREO Anexo 01 (S05) | Z5: RREO Anexo 01 (S05) | AA5: OFICIAL | AB5: —
A6: 9.3 | B6: Despesa total da União (exceto intra-orçamentárias) | C6: Empenhado | D6: União | E6: R$ bi | F6: 1961.59 | G6: 2331.13 | H6: 2793.73 | I6: 3901.65 | J6: =IFERROR(F6*FATOR_2016,"n.d.") -> 3040.8568 | K6: =IFERROR(G6*FATOR_2019,"n.d.") -> 3243.8384 | L6: =IFERROR(H6*FATOR_2022,"n.d.") -> 3194.7028 | M6: =IFERROR(K6/J6-1,"n.d.") -> 0.066751474 | N6: =IFERROR(L6/K6-1,"n.d.") -> -0.015147377 | O6: =IFERROR(I6/L6-1,"n.d.") -> 0.22128732 | P6: =IFERROR(I6/J6-1,"n.d.") -> 0.28307589 | Q6: =IFERROR(I6-F6,"n.d.") -> 1940.06 | R6: =IFERROR(I6-G6,"n.d.") -> 1570.52 | S6: =IFERROR(F6/PIB_2016,"n.d.") -> 0.31288685 | T6: =IFERROR(G6/PIB_2019,"n.d.") -> 0.31548094 | U6: =IFERROR(H6/PIB_2022,"n.d.") -> 0.27716466 | V6: =IFERROR(I6/PIB_2025,"n.d.") -> 0.30628644 | W6: RREO Anexo 01 (S05) | X6: RREO Anexo 01 (S05) | Y6: RREO Anexo 01 (S05) | Z6: RREO Anexo 01 (S05) | AA6: OFICIAL | AB6: —
A7: 9.3 | B7: Despesa total da União (exceto intra-orçamentárias) | C7: Liquidado | D7: União | E7: R$ bi | F7: 1892.46 | G7: 2255.45 | H7: 2675.76 | I7: 3705.42 | J7: =IFERROR(F7*FATOR_2016,"n.d.") -> 2933.6914 | K7: =IFERROR(G7*FATOR_2019,"n.d.") -> 3138.5274 | L7: =IFERROR(H7*FATOR_2022,"n.d.") -> 3059.801 | M7: =IFERROR(K7/J7-1,"n.d.") -> 0.06982192 | N7: =IFERROR(L7/K7-1,"n.d.") -> -0.025083858 | O7: =IFERROR(I7/L7-1,"n.d.") -> 0.21100031 | P7: =IFERROR(I7/J7-1,"n.d.") -> 0.26305717 | Q7: =IFERROR(I7-F7,"n.d.") -> 1812.96 | R7: =IFERROR(I7-G7,"n.d.") -> 1449.97 | S7: =IFERROR(F7/PIB_2016,"n.d.") -> 0.30186015 | T7: =IFERROR(G7/PIB_2019,"n.d.") -> 0.30523887 | U7: =IFERROR(H7/PIB_2022,"n.d.") -> 0.26546091 | V7: =IFERROR(I7/PIB_2025,"n.d.") -> 0.29088203 | W7: RREO Anexo 01 (S05) | X7: RREO Anexo 01 (S05) | Y7: RREO Anexo 01 (S05) | Z7: RREO Anexo 01 (S05) | AA7: OFICIAL | AB7: —
A8: 9.3 | B8: Despesa total da União (exceto intra-orçamentárias) | C8: Pago | D8: União | E8: R$ bi | F8: 1875.18 | G8: 2198.25 | H8: 2603.83 | I8: 3606.51 | J8: =IFERROR(F8*FATOR_2016,"n.d.") -> 2906.904 | K8: =IFERROR(G8*FATOR_2019,"n.d.") -> 3058.9319 | L8: =IFERROR(H8*FATOR_2022,"n.d.") -> 2977.5472 | M8: =IFERROR(K8/J8-1,"n.d.") -> 0.0522989 | N8: =IFERROR(L8/K8-1,"n.d.") -> -0.02660558 | O8: =IFERROR(I8/L8-1,"n.d.") -> 0.2112352 | P8: =IFERROR(I8/J8-1,"n.d.") -> 0.24067049 | Q8: =IFERROR(I8-F8,"n.d.") -> 1731.33 | R8: =IFERROR(I8-G8,"n.d.") -> 1408.26 | S8: =IFERROR(F8/PIB_2016,"n.d.") -> 0.29910388 | T8: =IFERROR(G8/PIB_2019,"n.d.") -> 0.29749777 | U8: =IFERROR(H8/PIB_2022,"n.d.") -> 0.25832477 | V8: =IFERROR(I8/PIB_2025,"n.d.") -> 0.28311742 | W8: RREO Anexo 01 (S05) | X8: RREO Anexo 01 (S05) | Y8: RREO Anexo 01 (S05) | Z8: RREO Anexo 01 (S05) | AA8: OFICIAL | AB8: Pago no exercício; não inclui refinanciamento.
A9: 22–24 | B9: Investimentos (GND 4) | C9: Dotação inicial (LOA) | D9: União | E9: R$ bi | F9: 45.31 | G9: 36.12 | H9: 42.36 | I9: 80.28 | J9: =IFERROR(F9*FATOR_2016,"n.d.") -> 70.239561 | K9: =IFERROR(G9*FATOR_2019,"n.d.") -> 50.262081 | L9: =IFERROR(H9*FATOR_2022,"n.d.") -> 48.43976 | M9: =IFERROR(K9/J9-1,"n.d.") -> -0.2844192 | N9: =IFERROR(L9/K9-1,"n.d.") -> -0.036256376 | O9: =IFERROR(I9/L9-1,"n.d.") -> 0.65731623 | P9: =IFERROR(I9/J9-1,"n.d.") -> 0.14294565 | Q9: =IFERROR(I9-F9,"n.d.") -> 34.97 | R9: =IFERROR(I9-G9,"n.d.") -> 44.16 | S9: =IFERROR(F9/PIB_2016,"n.d.") -> 0.007227251 | T9: =IFERROR(G9/PIB_2019,"n.d.") -> 0.0048882609 | U9: =IFERROR(H9/PIB_2022,"n.d.") -> 0.004202516 | V9: =IFERROR(I9/PIB_2025,"n.d.") -> 0.0063021222 | W9: RREO Anexo 01 (S05) | X9: RREO Anexo 01 (S05) | Y9: RREO Anexo 01 (S05) | Z9: RREO Anexo 01 (S05) | AA9: OFICIAL | AB9: Exclui intra-orçamentárias.
A10: 22–24 | B10: Investimentos (GND 4) | C10: Dotação atualizada | D10: União | E10: R$ bi | F10: 47.21 | G10: 45.44 | H10: 52.07 | I10: 74.36 | J10: =IFERROR(F10*FATOR_2016,"n.d.") -> 73.184941 | K10: =IFERROR(G10*FATOR_2019,"n.d.") -> 63.231145 | L10: =IFERROR(H10*FATOR_2022,"n.d.") -> 59.543397 | M10: =IFERROR(K10/J10-1,"n.d.") -> -0.1360088 | N10: =IFERROR(L10/K10-1,"n.d.") -> -0.0583217 | O10: =IFERROR(I10/L10-1,"n.d.") -> 0.24883705 | P10: =IFERROR(I10/J10-1,"n.d.") -> 0.016056027 | Q10: =IFERROR(I10-F10,"n.d.") -> 27.15 | R10: =IFERROR(I10-G10,"n.d.") -> 28.92 | S10: =IFERROR(F10/PIB_2016,"n.d.") -> 0.0075303139 | T10: =IFERROR(G10/PIB_2019,"n.d.") -> 0.0061495729 | U10: =IFERROR(H10/PIB_2022,"n.d.") -> 0.0051658406 | V10: =IFERROR(I10/PIB_2025,"n.d.") -> 0.0058373917 | W10: RREO Anexo 01 (S05) | X10: RREO Anexo 01 (S05) | Y10: RREO Anexo 01 (S05) | Z10: RREO Anexo 01 (S05) | AA10: OFICIAL | AB10: —
A11: 22–24 | B11: Investimentos (GND 4) | C11: Empenhado | D11: União | E11: R$ bi | F11: 38.08 | G11: 42.44 | H11: 51.19 | I11: 72.11 | J11: =IFERROR(F11*FATOR_2016,"n.d.") -> 59.031615 | K11: =IFERROR(G11*FATOR_2019,"n.d.") -> 59.056553 | L11: =IFERROR(H11*FATOR_2022,"n.d.") -> 58.537094 | M11: =IFERROR(K11/J11-1,"n.d.") -> 0.00042245835 | N11: =IFERROR(L11/K11-1,"n.d.") -> -0.0087959629 | O11: =IFERROR(I11/L11-1,"n.d.") -> 0.23186846 | P11: =IFERROR(I11/J11-1,"n.d.") -> 0.22154883 | Q11: =IFERROR(I11-F11,"n.d.") -> 34.03 | R11: =IFERROR(I11-G11,"n.d.") -> 29.67 | S11: =IFERROR(F11/PIB_2016,"n.d.") -> 0.0060740172 | T11: =IFERROR(G11/PIB_2019,"n.d.") -> 0.0057435712 | U11: =IFERROR(H11/PIB_2022,"n.d.") -> 0.0050785363 | V11: =IFERROR(I11/PIB_2025,"n.d.") -> 0.0056607628 | W11: RREO Anexo 01 (S05) | X11: RREO Anexo 01 (S05) | Y11: RREO Anexo 01 (S05) | Z11: RREO Anexo 01 (S05) | AA11: OFICIAL | AB11: —
A12: 22–24 | B12: Investimentos (GND 4) | C12: Liquidado | D12: União | E12: R$ bi | F12: 17.28 | G12: 16.61 | H12: 19.99 | I12: 38.62 | J12: =IFERROR(F12*FATOR_2016,"n.d.") -> 26.787455 | K12: =IFERROR(G12*FATOR_2019,"n.d.") -> 23.113321 | L12: =IFERROR(H12*FATOR_2022,"n.d.") -> 22.859084 | M12: =IFERROR(K12/J12-1,"n.d.") -> -0.13715877 | N12: =IFERROR(L12/K12-1,"n.d.") -> -0.010999595 | O12: =IFERROR(I12/L12-1,"n.d.") -> 0.68948152 | P12: =IFERROR(I12/J12-1,"n.d.") -> 0.44171961 | Q12: =IFERROR(I12-F12,"n.d.") -> 21.34 | R12: =IFERROR(I12-G12,"n.d.") -> 22.01 | S12: =IFERROR(F12/PIB_2016,"n.d.") -> 0.0027562767 | T12: =IFERROR(G12/PIB_2019,"n.d.") -> 0.0022478963 | U12: =IFERROR(H12/PIB_2022,"n.d.") -> 0.0019831987 | V12: =IFERROR(I12/PIB_2025,"n.d.") -> 0.0030317384 | W12: RREO Anexo 01 (S05) | X12: RREO Anexo 01 (S05) | Y12: RREO Anexo 01 (S05) | Z12: RREO Anexo 01 (S05) | AA12: OFICIAL | AB12: —
A13: 22–24 | B13: Investimentos (GND 4) | C13: Pago | D13: União | E13: R$ bi | F13: 16.8 | G13: 16.37 | H13: 19.59 | I13: 37.81 | J13: =IFERROR(F13*FATOR_2016,"n.d.") -> 26.04336 | K13: =IFERROR(G13*FATOR_2019,"n.d.") -> 22.779354 | L13: =IFERROR(H13*FATOR_2022,"n.d.") -> 22.401674 | M13: =IFERROR(K13/J13-1,"n.d.") -> -0.12532967 | N13: =IFERROR(L13/K13-1,"n.d.") -> -0.016579936 | O13: =IFERROR(I13/L13-1,"n.d.") -> 0.68782032 | P13: =IFERROR(I13/J13-1,"n.d.") -> 0.45180962 | Q13: =IFERROR(I13-F13,"n.d.") -> 21.01 | R13: =IFERROR(I13-G13,"n.d.") -> 21.44 | S13: =IFERROR(F13/PIB_2016,"n.d.") -> 0.0026797135 | T13: =IFERROR(G13/PIB_2019,"n.d.") -> 0.0022154161 | U13: =IFERROR(H13/PIB_2022,"n.d.") -> 0.0019435149 | V13: =IFERROR(I13/PIB_2025,"n.d.") -> 0.002968152 | W13: RREO Anexo 01 (S05) | X13: RREO Anexo 01 (S05) | Y13: RREO Anexo 01 (S05) | Z13: RREO Anexo 01 (S05) | AA13: OFICIAL | AB13: Pago do exercício (sem RAP).
A14: 24.1 | B14: Investimentos (GND 4) | C14: Pago total no ano, inclui restos a pagar (RTN) | D14: Governo Central | E14: R$ bi | F14: 48.051 | G14: 37.82 | H14: 40.639 | I14: 69.923 | J14: =IFERROR(F14*FATOR_2016,"n.d.") -> 74.488659 | K14: =IFERROR(G14*FATOR_2019,"n.d.") -> 52.627682 | L14: =IFERROR(H14*FATOR_2022,"n.d.") -> 46.471752 | M14: =IFERROR(K14/J14-1,"n.d.") -> -0.2934806 | N14: =IFERROR(L14/K14-1,"n.d.") -> -0.11697135 | O14: =IFERROR(I14/L14-1,"n.d.") -> 0.50463448 | P14: =IFERROR(I14/J14-1,"n.d.") -> -0.061293341 | Q14: =IFERROR(I14-F14,"n.d.") -> 21.872 | R14: =IFERROR(I14-G14,"n.d.") -> 32.103 | S14: =IFERROR(F14/PIB_2016,"n.d.") -> 0.007664459 | T14: =IFERROR(G14/PIB_2019,"n.d.") -> 0.0051183285 | U14: =IFERROR(H14/PIB_2022,"n.d.") -> 0.0040317764 | V14: =IFERROR(I14/PIB_2025,"n.d.") -> 0.0054890794 | W14: STN – RTN tab. 2.3 (S04) | X14: STN – RTN tab. 2.3 (S04) | Y14: S04 | Z14: S04 | AA14: OFICIAL | AB14: Conceito mais usado no debate fiscal: inclui pagamentos de RAP de anos anteriores.
A15: 24.2 | B15: Investimento total (GND 4 + inversões financeiras) | C15: Pago total no ano (RTN) | D15: Governo Central | E15: R$ bi | F15: 64.813 | G15: 56.593 | H15: 45.055 | I15: 83.406 | J15: =IFERROR(F15*FATOR_2016,"n.d.") -> 100.47311 | K15: =IFERROR(G15*FATOR_2019,"n.d.") -> 78.750884 | L15: =IFERROR(H15*FATOR_2022,"n.d.") -> 51.521562 | M15: =IFERROR(K15/J15-1,"n.d.") -> -0.2161994 | N15: =IFERROR(L15/K15-1,"n.d.") -> -0.34576528 | O15: =IFERROR(I15/L15-1,"n.d.") -> 0.61885619 | P15: =IFERROR(I15/J15-1,"n.d.") -> -0.16986745 | Q15: =IFERROR(I15-F15,"n.d.") -> 18.593 | R15: =IFERROR(I15-G15,"n.d.") -> 26.813 | S15: =IFERROR(F15/PIB_2016,"n.d.") -> 0.010338111 | T15: =IFERROR(G15/PIB_2019,"n.d.") -> 0.007658952 | U15: =IFERROR(H15/PIB_2022,"n.d.") -> 0.0044698857 | V15: =IFERROR(I15/PIB_2025,"n.d.") -> 0.0065475188 | W15: S04 | X15: S04 | Y15: S04 | Z15: S04 | AA15: OFICIAL | AB15: —
A17: Notas metodológicas
A18: 1. Previsão e execução nunca são somadas.
A19: 2. 'Pago' do RREO = pagamentos do exercício; o RTN soma restos a pagar pagos (linhas 24.1 e 24.2).
A20: 3. Valores nominais do próprio ano (R$ bilhões, salvo indicação). Correção para R$ de dez/2025 pelo IPCA: fator = índice dez/2025 ÷ índice de dezembro do ano (FATOR_2016, FATOR_2019, FATOR_2022 na aba 'Resumo executivo').
A21: 4. Colunas de variação: para valores em R$ = variação REAL (IPCA); para US$ e pessoas = variação nominal; para taxas e % = diferença em pontos percentuais (p.p.).
A22: 5. % do PIB com o PIB anual do IBGE (SIDRA 1846) de cada ano; valores em US$ usam o PIB convertido pela PTAX média anual.
A23: 6. 'n.a.' = não se aplica; 'n.d.' = não disponível (algum ano 'não localizado após busca'). Azul = dado digitado da fonte; preto = fórmula; verde = vínculo com outra aba.
A24: 7. Cor da linha = classificação do dado em 2019/2025; células de 2016/2022 com cor própria quando a classificação difere (ex.: estimado, não localizado).
A25: 8. Períodos 2016→2019, 2019→2022 e 2022→2025 correspondem aproximadamente aos mandatos Temer, Bolsonaro e Lula III (até 2025); 2016 inclui o governo Dilma até maio.

Sheet Saúde, educação e previdência
A1: Saúde, educação e previdência – LOA e execução (União)
A2: RREO Anexo 02 (funções/subfunções) para dotação, empenho e liquidação; Portal da Transparência para valor pago.
A3: Código | B3: Indicador | C3: Conceito / estágio | D3: Âmbito | E3: Unidade | F3: Brasil 2016 | G3: Brasil 2019 | H3: Brasil 2022 | I3: Brasil 2025 | J3: 2016 em R$ de dez/2025 | K3: 2019 em R$ de dez/2025 | L3: 2022 em R$ de dez/2025 | M3: Variação 2016→2019 | N3: Variação 2019→2022 | O3: Variação 2022→2025 | P3: Variação 2016→2025 | Q3: Diferença absoluta 2025−2016 (nominal) | R3: Diferença absoluta 2025−2019 (nominal) | S3: 2016 % do PIB | T3: 2019 % do PIB | U3: 2022 % do PIB | V3: 2025 % do PIB | W3: Fonte 2016 | X3: Fonte 2019 | Y3: Fonte 2022 | Z3: Fonte 2025 | AA3: Classificação do dado | AB3: Observações metodológicas
A4: 25–26 | B4: Saúde (função 10) | C4: Dotação inicial (LOA) | D4: União | E4: R$ bi | F4: 108.006 | G4: 120.56 | H4: 147.204 | I4: 232.87 | J4: =IFERROR(F4*FATOR_2016,"n.d.") -> 167.4309 | K4: =IFERROR(G4*FATOR_2019,"n.d.") -> 167.76291 | L4: =IFERROR(H4*FATOR_2022,"n.d.") -> 168.3316 | M4: =IFERROR(K4/J4-1,"n.d.") -> 0.0019830021 | N4: =IFERROR(L4/K4-1,"n.d.") -> 0.0033897955 | O4: =IFERROR(I4/L4-1,"n.d.") -> 0.38340042 | P4: =IFERROR(I4/J4-1,"n.d.") -> 0.39084245 | Q4: =IFERROR(I4-F4,"n.d.") -> 124.864 | R4: =IFERROR(I4-G4,"n.d.") -> 112.31 | S4: =IFERROR(F4/PIB_2016,"n.d.") -> 0.017227686 | T4: =IFERROR(G4/PIB_2019,"n.d.") -> 0.016315856 | U4: =IFERROR(H4/PIB_2022,"n.d.") -> 0.014604041 | V4: =IFERROR(I4/PIB_2025,"n.d.") -> 0.018280708 | W4: RREO Anexo 02 (S06) | X4: RREO Anexo 02 (S06) | Y4: RREO Anexo 02 (S06) | Z4: RREO Anexo 02 (S06) | AA4: OFICIAL | AB4: Exclui intra-orçamentárias.
A5: 25–26 | B5: Saúde (função 10) | C5: Dotação atualizada | D5: União | E5: R$ bi | F5: 110.456 | G5: 125.01 | H5: 153.698 | I5: 239.62 | J5: =IFERROR(F5*FATOR_2016,"n.d.") -> 171.22889 | K5: =IFERROR(G5*FATOR_2019,"n.d.") -> 173.95522 | L5: =IFERROR(H5*FATOR_2022,"n.d.") -> 175.75765 | M5: =IFERROR(K5/J5-1,"n.d.") -> 0.015922176 | N5: =IFERROR(L5/K5-1,"n.d.") -> 0.010361453 | O5: =IFERROR(I5/L5-1,"n.d.") -> 0.36335457 | P5: =IFERROR(I5/J5-1,"n.d.") -> 0.3994134 | Q5: =IFERROR(I5-F5,"n.d.") -> 129.164 | R5: =IFERROR(I5-G5,"n.d.") -> 114.61 | S5: =IFERROR(F5/PIB_2016,"n.d.") -> 0.017618478 | T5: =IFERROR(G5/PIB_2019,"n.d.") -> 0.016918092 | U5: =IFERROR(H5/PIB_2022,"n.d.") -> 0.015248308 | V5: =IFERROR(I5/PIB_2025,"n.d.") -> 0.018810595 | W5: RREO Anexo 02 (S06) | X5: RREO Anexo 02 (S06) | Y5: RREO Anexo 02 (S06) | Z5: RREO Anexo 02 (S06) | AA5: OFICIAL | AB5: —
A6: 25–26 | B6: Saúde (função 10) | C6: Empenhado | D6: União | E6: R$ bi | F6: 106.487 | G6: 124.11 | H6: 153.231 | I6: 238.64 | J6: =IFERROR(F6*FATOR_2016,"n.d.") -> 165.07614 | K6: =IFERROR(G6*FATOR_2019,"n.d.") -> 172.70285 | L6: =IFERROR(H6*FATOR_2022,"n.d.") -> 175.22363 | M6: =IFERROR(K6/J6-1,"n.d.") -> 0.04620112 | N6: =IFERROR(L6/K6-1,"n.d.") -> 0.014596052 | O6: =IFERROR(I6/L6-1,"n.d.") -> 0.36191679 | P6: =IFERROR(I6/J6-1,"n.d.") -> 0.4456359 | Q6: =IFERROR(I6-F6,"n.d.") -> 132.153 | R6: =IFERROR(I6-G6,"n.d.") -> 114.53 | S6: =IFERROR(F6/PIB_2016,"n.d.") -> 0.016985396 | T6: =IFERROR(G6/PIB_2019,"n.d.") -> 0.016796292 | U6: =IFERROR(H6/PIB_2022,"n.d.") -> 0.015201977 | V6: =IFERROR(I6/PIB_2025,"n.d.") -> 0.018733663 | W6: RREO Anexo 02 (S06) | X6: RREO Anexo 02 (S06) | Y6: RREO Anexo 02 (S06) | Z6: RREO Anexo 02 (S06) | AA6: OFICIAL | AB6: —
A7: 25–26 | B7: Saúde (função 10) | C7: Liquidado | D7: União | E7: R$ bi | F7: 98.773 | G7: 113.91 | H7: 136.174 | I7: 217.07 | J7: =IFERROR(F7*FATOR_2016,"n.d.") -> 153.1179 | K7: =IFERROR(G7*FATOR_2019,"n.d.") -> 158.50924 | L7: =IFERROR(H7*FATOR_2022,"n.d.") -> 155.7185 | M7: =IFERROR(K7/J7-1,"n.d.") -> 0.035210347 | N7: =IFERROR(L7/K7-1,"n.d.") -> -0.017606114 | O7: =IFERROR(I7/L7-1,"n.d.") -> 0.39398976 | P7: =IFERROR(I7/J7-1,"n.d.") -> 0.41766572 | Q7: =IFERROR(I7-F7,"n.d.") -> 118.297 | R7: =IFERROR(I7-G7,"n.d.") -> 103.16 | S7: =IFERROR(F7/PIB_2016,"n.d.") -> 0.015754961 | T7: =IFERROR(G7/PIB_2019,"n.d.") -> 0.015415886 | U7: =IFERROR(H7/PIB_2022,"n.d.") -> 0.01350976 | V7: =IFERROR(I7/PIB_2025,"n.d.") -> 0.01704038 | W7: RREO Anexo 02 (S06) | X7: RREO Anexo 02 (S06) | Y7: RREO Anexo 02 (S06) | Z7: RREO Anexo 02 (S06) | AA7: OFICIAL | AB7: —
A8: 25–26 | B8: Saúde (função 10) | C8: Pago | D8: União | E8: R$ bi | F8: 100.191 | G8: 114.182 | H8: 136.85 | I8: 234.28 | J8: =IFERROR(F8*FATOR_2016,"n.d.") -> 155.31609 | K8: =IFERROR(G8*FATOR_2019,"n.d.") -> 158.88773 | L8: =IFERROR(H8*FATOR_2022,"n.d.") -> 156.49153 | M8: =IFERROR(K8/J8-1,"n.d.") -> 0.022995991 | N8: =IFERROR(L8/K8-1,"n.d.") -> -0.015081117 | O8: =IFERROR(I8/L8-1,"n.d.") -> 0.49707785 | P8: =IFERROR(I8/J8-1,"n.d.") -> 0.50840784 | Q8: =IFERROR(I8-F8,"n.d.") -> 134.089 | R8: =IFERROR(I8-G8,"n.d.") -> 120.098 | S8: =IFERROR(F8/PIB_2016,"n.d.") -> 0.015981141 | T8: =IFERROR(G8/PIB_2019,"n.d.") -> 0.015452697 | U8: =IFERROR(H8/PIB_2022,"n.d.") -> 0.013576825 | V8: =IFERROR(I8/PIB_2025,"n.d.") -> 0.018391395 | W8: Portal da Transparência (S07) | X8: Portal da Transparência (S07) | Y8: Portal da Transparência (S07) | Z8: Portal da Transparência (S07) | AA8: OFICIAL | AB8: Pago segundo o Portal da Transparência: inclui restos a pagar pagos no ano e classificação por função do Portal; pode divergir do RREO (critérios distintos).
A9: 27–28 | B9: Educação (função 12) | C9: Dotação inicial (LOA) | D9: União | E9: R$ bi | F9: 91.627 | G9: 103.03 | H9: 112.505 | I9: 163.1 | J9: =IFERROR(F9*FATOR_2016,"n.d.") -> 142.04017 | K9: =IFERROR(G9*FATOR_2019,"n.d.") -> 143.36938 | L9: =IFERROR(H9*FATOR_2022,"n.d.") -> 128.65239 | M9: =IFERROR(K9/J9-1,"n.d.") -> 0.009358 | N9: =IFERROR(L9/K9-1,"n.d.") -> -0.1026509 | O9: =IFERROR(I9/L9-1,"n.d.") -> 0.26775726 | P9: =IFERROR(I9/J9-1,"n.d.") -> 0.1482667 | Q9: =IFERROR(I9-F9,"n.d.") -> 71.473 | R9: =IFERROR(I9-G9,"n.d.") -> 60.07 | S9: =IFERROR(F9/PIB_2016,"n.d.") -> 0.014615125 | T9: =IFERROR(G9/PIB_2019,"n.d.") -> 0.013943453 | U9: =IFERROR(H9/PIB_2022,"n.d.") -> 0.011161569 | V9: =IFERROR(I9/PIB_2025,"n.d.") -> 0.012803639 | W9: RREO Anexo 02 (S06) | X9: RREO Anexo 02 (S06) | Y9: RREO Anexo 02 (S06) | Z9: RREO Anexo 02 (S06) | AA9: OFICIAL | AB9: Exclui intra-orçamentárias.
A10: 27–28 | B10: Educação (função 12) | C10: Dotação atualizada | D10: União | E10: R$ bi | F10: 97.41 | G10: 104.57 | H10: 118.572 | I10: 176.86 | J10: =IFERROR(F10*FATOR_2016,"n.d.") -> 151.00498 | K10: =IFERROR(G10*FATOR_2019,"n.d.") -> 145.51234 | L10: =IFERROR(H10*FATOR_2022,"n.d.") -> 135.59016 | M10: =IFERROR(K10/J10-1,"n.d.") -> -0.036373884 | N10: =IFERROR(L10/K10-1,"n.d.") -> -0.068187901 | O10: =IFERROR(I10/L10-1,"n.d.") -> 0.30437194 | P10: =IFERROR(I10/J10-1,"n.d.") -> 0.17121966 | Q10: =IFERROR(I10-F10,"n.d.") -> 79.45 | R10: =IFERROR(I10-G10,"n.d.") -> 72.29 | S10: =IFERROR(F10/PIB_2016,"n.d.") -> 0.015537553 | T10: =IFERROR(G10/PIB_2019,"n.d.") -> 0.014151867 | U10: =IFERROR(H10/PIB_2022,"n.d.") -> 0.011763473 | V10: =IFERROR(I10/PIB_2025,"n.d.") -> 0.013883823 | W10: RREO Anexo 02 (S06) | X10: RREO Anexo 02 (S06) | Y10: RREO Anexo 02 (S06) | Z10: RREO Anexo 02 (S06) | AA10: OFICIAL | AB10: —
A11: 27–28 | B11: Educação (função 12) | C11: Empenhado | D11: União | E11: R$ bi | F11: 94.546 | G11: 101.3 | H11: 117.753 | I11: 176.01 | J11: =IFERROR(F11*FATOR_2016,"n.d.") -> 146.56521 | K11: =IFERROR(G11*FATOR_2019,"n.d.") -> 140.96204 | L11: =IFERROR(H11*FATOR_2022,"n.d.") -> 134.65361 | M11: =IFERROR(K11/J11-1,"n.d.") -> -0.038229875 | N11: =IFERROR(L11/K11-1,"n.d.") -> -0.044752647 | O11: =IFERROR(I11/L11-1,"n.d.") -> 0.30713166 | P11: =IFERROR(I11/J11-1,"n.d.") -> 0.20089893 | Q11: =IFERROR(I11-F11,"n.d.") -> 81.464 | R11: =IFERROR(I11-G11,"n.d.") -> 74.71 | S11: =IFERROR(F11/PIB_2016,"n.d.") -> 0.015080726 | T11: =IFERROR(G11/PIB_2019,"n.d.") -> 0.013709325 | U11: =IFERROR(H11/PIB_2022,"n.d.") -> 0.011682221 | V11: =IFERROR(I11/PIB_2025,"n.d.") -> 0.013817097 | W11: RREO Anexo 02 (S06) | X11: RREO Anexo 02 (S06) | Y11: RREO Anexo 02 (S06) | Z11: RREO Anexo 02 (S06) | AA11: OFICIAL | AB11: —
A12: 27–28 | B12: Educação (função 12) | C12: Liquidado | D12: União | E12: R$ bi | F12: 84.949 | G12: 88.22 | H12: 104.467 | I12: 156.97 | J12: =IFERROR(F12*FATOR_2016,"n.d.") -> 131.68794 | K12: =IFERROR(G12*FATOR_2019,"n.d.") -> 122.76082 | L12: =IFERROR(H12*FATOR_2022,"n.d.") -> 119.46073 | M12: =IFERROR(K12/J12-1,"n.d.") -> -0.067789952 | N12: =IFERROR(L12/K12-1,"n.d.") -> -0.026882287 | O12: =IFERROR(I12/L12-1,"n.d.") -> 0.31398832 | P12: =IFERROR(I12/J12-1,"n.d.") -> 0.19198465 | Q12: =IFERROR(I12-F12,"n.d.") -> 72.021 | R12: =IFERROR(I12-G12,"n.d.") -> 68.75 | S12: =IFERROR(F12/PIB_2016,"n.d.") -> 0.013549939 | T12: =IFERROR(G12/PIB_2019,"n.d.") -> 0.011939158 | U12: =IFERROR(H12/PIB_2022,"n.d.") -> 0.010364123 | V12: =IFERROR(I12/PIB_2025,"n.d.") -> 0.012322423 | W12: RREO Anexo 02 (S06) | X12: RREO Anexo 02 (S06) | Y12: RREO Anexo 02 (S06) | Z12: RREO Anexo 02 (S06) | AA12: OFICIAL | AB12: —
A13: 27–28 | B13: Educação (função 12) | C13: Pago | D13: União | E13: R$ bi | F13: 95.184 | G13: 94.474 | H13: 109.778 | I13: 174.587 | J13: =IFERROR(F13*FATOR_2016,"n.d.") -> 147.55423 | K13: =IFERROR(G13*FATOR_2019,"n.d.") -> 131.46345 | L13: =IFERROR(H13*FATOR_2022,"n.d.") -> 125.53399 | M13: =IFERROR(K13/J13-1,"n.d.") -> -0.10904997 | N13: =IFERROR(L13/K13-1,"n.d.") -> -0.045103463 | O13: =IFERROR(I13/L13-1,"n.d.") -> 0.39075477 | P13: =IFERROR(I13/J13-1,"n.d.") -> 0.18320563 | Q13: =IFERROR(I13-F13,"n.d.") -> 79.403 | R13: =IFERROR(I13-G13,"n.d.") -> 80.113 | S13: =IFERROR(F13/PIB_2016,"n.d.") -> 0.015182491 | T13: =IFERROR(G13/PIB_2019,"n.d.") -> 0.012785536 | U13: =IFERROR(H13/PIB_2022,"n.d.") -> 0.010891025 | V13: =IFERROR(I13/PIB_2025,"n.d.") -> 0.013705389 | W13: Portal da Transparência (S07) | X13: Portal da Transparência (S07) | Y13: Portal da Transparência (S07) | Z13: Portal da Transparência (S07) | AA13: OFICIAL | AB13: Pago segundo o Portal da Transparência: inclui restos a pagar pagos no ano e classificação por função do Portal; pode divergir do RREO (critérios distintos).
A14: 31–32 | B14: Previdência Social (função 09) | C14: Dotação inicial (LOA) | D14: União | E14: R$ bi | F14: 570.877 | G14: 733.92 | H14: 882.003 | I14: 1085.59 | J14: =IFERROR(F14*FATOR_2016,"n.d.") -> 884.97351 | K14: =IFERROR(G14*FATOR_2019,"n.d.") -> 1021.272 | L14: =IFERROR(H14*FATOR_2022,"n.d.") -> 1008.5933 | M14: =IFERROR(K14/J14-1,"n.d.") -> 0.15401426 | N14: =IFERROR(L14/K14-1,"n.d.") -> -0.012414631 | O14: =IFERROR(I14/L14-1,"n.d.") -> 0.07634065 | P14: =IFERROR(I14/J14-1,"n.d.") -> 0.22669209 | Q14: =IFERROR(I14-F14,"n.d.") -> 514.713 | R14: =IFERROR(I14-G14,"n.d.") -> 351.67 | S14: =IFERROR(F14/PIB_2016,"n.d.") -> 0.091058737 | T14: =IFERROR(G14/PIB_2019,"n.d.") -> 0.099324264 | U14: =IFERROR(H14/PIB_2022,"n.d.") -> 0.08750311 | V14: =IFERROR(I14/PIB_2025,"n.d.") -> 0.085220738 | W14: RREO Anexo 02 (S06) | X14: RREO Anexo 02 (S06) | Y14: RREO Anexo 02 (S06) | Z14: RREO Anexo 02 (S06) | AA14: OFICIAL | AB14: Exclui intra-orçamentárias.
A15: 31–32 | B15: Previdência Social (função 09) | C15: Dotação atualizada | D15: União | E15: R$ bi | F15: 595.214 | G15: 727.78 | H15: 897.749 | I15: 1103.83 | J15: =IFERROR(F15*FATOR_2016,"n.d.") -> 922.70073 | K15: =IFERROR(G15*FATOR_2019,"n.d.") -> 1012.728 | L15: =IFERROR(H15*FATOR_2022,"n.d.") -> 1026.5993 | M15: =IFERROR(K15/J15-1,"n.d.") -> 0.097569363 | N15: =IFERROR(L15/K15-1,"n.d.") -> 0.013696907 | O15: =IFERROR(I15/L15-1,"n.d.") -> 0.075229655 | P15: =IFERROR(I15/J15-1,"n.d.") -> 0.19630338 | Q15: =IFERROR(I15-F15,"n.d.") -> 508.616 | R15: =IFERROR(I15-G15,"n.d.") -> 376.05 | S15: =IFERROR(F15/PIB_2016,"n.d.") -> 0.094940653 | T15: =IFERROR(G15/PIB_2019,"n.d.") -> 0.098493314 | U15: =IFERROR(H15/PIB_2022,"n.d.") -> 0.089065264 | V15: =IFERROR(I15/PIB_2025,"n.d.") -> 0.086652611 | W15: RREO Anexo 02 (S06) | X15: RREO Anexo 02 (S06) | Y15: RREO Anexo 02 (S06) | Z15: RREO Anexo 02 (S06) | AA15: OFICIAL | AB15: —
... A26: 31.2 | B26: Previdência do regime estatutário – RPPS (subfunção 272) | C26: Liquidado | D26: União | E26: R$ bi | F26: 86.044 | G26: 108.46 | H26: 114.131 | I26: 104.5 | J26: =IFERROR(F26*FATOR_2016,"n.d.") -> 133.38541 | K26: =IFERROR(G26*FATOR_2019,"n.d.") -> 150.9254 | L26: =IFERROR(H26*FATOR_2022,"n.d.") -> 130.51176 | M26: =IFERROR(K26/J26-1,"n.d.") -> 0.13149856 | N26: =IFERROR(L26/K26-1,"n.d.") -> -0.13525645 | O26: =IFERROR(I26/L26-1,"n.d.") -> -0.19930588 | P26: =IFERROR(I26/J26-1,"n.d.") -> -0.21655597 | Q26: =IFERROR(I26-F26,"n.d.") -> 18.456 | R26: =IFERROR(I26-G26,"n.d.") -> -3.96 | S26: =IFERROR(F26/PIB_2016,"n.d.") -> 0.013724599 | T26: =IFERROR(G26/PIB_2019,"n.d.") -> 0.014678316 | U26: =IFERROR(H26/PIB_2022,"n.d.") -> 0.011322884 | V26: =IFERROR(I26/PIB_2025,"n.d.") -> 0.0082034351 | W26: RREO Anexo 02 (S06) | X26: RREO Anexo 02 (S06) | Y26: RREO Anexo 02 (S06) | Z26: RREO Anexo 02 (S06) | AA26: OFICIAL | AB26: —
A28: Notas metodológicas
A29: 1. Função orçamentária ≠ mínimos constitucionais (ASPS/MDE).
A30: 2. 2016: vigência do teto de gastos a partir de 2017 (EC 95/2016); 2019–2022 sob teto; 2025 sob o Regime Fiscal Sustentável (LC 200/2023).
A31: 3. Valores nominais do próprio ano (R$ bilhões, salvo indicação). Correção para R$ de dez/2025 pelo IPCA: fator = índice dez/2025 ÷ índice de dezembro do ano (FATOR_2016, FATOR_2019, FATOR_2022 na aba 'Resumo executivo').
A32: 4. Colunas de variação: para valores em R$ = variação REAL (IPCA); para US$ e pessoas = variação nominal; para taxas e % = diferença em pontos percentuais (p.p.).
A33: 5. % do PIB com o PIB anual do IBGE (SIDRA 1846) de cada ano; valores em US$ usam o PIB convertido pela PTAX média anual.
A34: 6. 'n.a.' = não se aplica; 'n.d.' = não disponível (algum ano 'não localizado após busca'). Azul = dado digitado da fonte; preto = fórmula; verde = vínculo com outra aba.
A35: 7. Cor da linha = classificação do dado em 2019/2025; células de 2016/2022 com cor própria quando a classificação difere (ex.: estimado, não localizado).
A36: 8. Períodos 2016→2019, 2019→2022 e 2022→2025 correspondem aproximadamente aos mandatos Temer, Bolsonaro e Lula III (até 2025); 2016 inclui o governo Dilma até maio.

Sheet Segurança e polít. afirmativas
A1: Segurança pública e políticas afirmativas – LOA e execução
A2: Função 06 pelo RREO; políticas afirmativas pelos programas de igualdade racial (Portal da Transparência) e dados do MIR.
A3: Código | B3: Indicador | C3: Conceito / estágio | D3: Âmbito | E3: Unidade | F3: Brasil 2016 | G3: Brasil 2019 | H3: Brasil 2022 | I3: Brasil 2025 | J3: 2016 em R$ de dez/2025 | K3: 2019 em R$ de dez/2025 | L3: 2022 em R$ de dez/2025 | M3: Variação 2016→2019 | N3: Variação 2019→2022 | O3: Variação 2022→2025 | P3: Variação 2016→2025 | Q3: Diferença absoluta 2025−2016 (nominal) | R3: Diferença absoluta 2025−2019 (nominal) | S3: 2016 % do PIB | T3: 2019 % do PIB | U3: 2022 % do PIB | V3: 2025 % do PIB | W3: Fonte 2016 | X3: Fonte 2019 | Y3: Fonte 2022 | Z3: Fonte 2025 | AA3: Classificação do dado | AB3: Observações metodológicas
A4: 29–30 | B4: Segurança pública (função 06) | C4: Dotação inicial (LOA) | D4: União | E4: R$ bi | F4: 7.032 | G4: 10.37 | H4: 11.607 | I4: 15.62 | J4: =IFERROR(F4*FATOR_2016,"n.d.") -> 10.901006 | K4: =IFERROR(G4*FATOR_2019,"n.d.") -> 14.430171 | L4: =IFERROR(H4*FATOR_2022,"n.d.") -> 13.272906 | M4: =IFERROR(K4/J4-1,"n.d.") -> 0.3237467 | N4: =IFERROR(L4/K4-1,"n.d.") -> -0.080197605 | O4: =IFERROR(I4/L4-1,"n.d.") -> 0.17683348 | P4: =IFERROR(I4/J4-1,"n.d.") -> 0.43289525 | Q4: =IFERROR(I4-F4,"n.d.") -> 8.588 | R4: =IFERROR(I4-G4,"n.d.") -> 5.25 | S4: =IFERROR(F4/PIB_2016,"n.d.") -> 0.0011216515 | T4: =IFERROR(G4/PIB_2019,"n.d.") -> 0.0014034127 | U4: =IFERROR(H4/PIB_2022,"n.d.") -> 0.0011515251 | V4: =IFERROR(I4/PIB_2025,"n.d.") -> 0.0012261977 | W4: RREO Anexo 02 (S06) | X4: RREO Anexo 02 (S06) | Y4: RREO Anexo 02 (S06) | Z4: RREO Anexo 02 (S06) | AA4: OFICIAL | AB4: Exclui intra-orçamentárias.
A5: 29–30 | B5: Segurança pública (função 06) | C5: Dotação atualizada | D5: União | E5: R$ bi | F5: 9.425 | G5: 10.51 | H5: 13.489 | I5: 16.88 | J5: =IFERROR(F5*FATOR_2016,"n.d.") -> 14.610635 | K5: =IFERROR(G5*FATOR_2019,"n.d.") -> 14.624985 | L5: =IFERROR(H5*FATOR_2022,"n.d.") -> 15.425022 | M5: =IFERROR(K5/J5-1,"n.d.") -> 0.00098219891 | N5: =IFERROR(L5/K5-1,"n.d.") -> 0.054703401 | O5: =IFERROR(I5/L5-1,"n.d.") -> 0.09432585 | P5: =IFERROR(I5/J5-1,"n.d.") -> 0.15532284 | Q5: =IFERROR(I5-F5,"n.d.") -> 7.455 | R5: =IFERROR(I5-G5,"n.d.") -> 6.37 | S5: =IFERROR(F5/PIB_2016,"n.d.") -> 0.0015033512 | T5: =IFERROR(G5/PIB_2019,"n.d.") -> 0.0014223594 | U5: =IFERROR(H5/PIB_2022,"n.d.") -> 0.0013382375 | V5: =IFERROR(I5/PIB_2025,"n.d.") -> 0.0013251099 | W5: RREO Anexo 02 (S06) | X5: RREO Anexo 02 (S06) | Y5: RREO Anexo 02 (S06) | Z5: RREO Anexo 02 (S06) | AA5: OFICIAL | AB5: —
A6: 29–30 | B6: Segurança pública (função 06) | C6: Empenhado | D6: União | E6: R$ bi | F6: 8.816 | G6: 10.23 | H6: 13.057 | I6: 16.58 | J6: =IFERROR(F6*FATOR_2016,"n.d.") -> 13.666563 | K6: =IFERROR(G6*FATOR_2019,"n.d.") -> 14.235357 | L6: =IFERROR(H6*FATOR_2022,"n.d.") -> 14.931018 | M6: =IFERROR(K6/J6-1,"n.d.") -> 0.041619374 | N6: =IFERROR(L6/K6-1,"n.d.") -> 0.048868586 | O6: =IFERROR(I6/L6-1,"n.d.") -> 0.11043999 | P6: =IFERROR(I6/J6-1,"n.d.") -> 0.21317994 | Q6: =IFERROR(I6-F6,"n.d.") -> 7.764 | R6: =IFERROR(I6-G6,"n.d.") -> 6.35 | S6: =IFERROR(F6/PIB_2016,"n.d.") -> 0.0014062115 | T6: =IFERROR(G6/PIB_2019,"n.d.") -> 0.0013844659 | U6: =IFERROR(H6/PIB_2022,"n.d.") -> 0.0012953789 | V6: =IFERROR(I6/PIB_2025,"n.d.") -> 0.0013015594 | W6: RREO Anexo 02 (S06) | X6: RREO Anexo 02 (S06) | Y6: RREO Anexo 02 (S06) | Z6: RREO Anexo 02 (S06) | AA6: OFICIAL | AB6: —
A7: 29–30 | B7: Segurança pública (função 06) | C7: Liquidado | D7: União | E7: R$ bi | F7: 7.553 | G7: 8.45 | H7: 10.982 | I7: 13.89 | J7: =IFERROR(F7*FATOR_2016,"n.d.") -> 11.70866 | K7: =IFERROR(G7*FATOR_2019,"n.d.") -> 11.758432 | L7: =IFERROR(H7*FATOR_2022,"n.d.") -> 12.558202 | M7: =IFERROR(K7/J7-1,"n.d.") -> 0.0042508808 | N7: =IFERROR(L7/K7-1,"n.d.") -> 0.068016687 | O7: =IFERROR(I7/L7-1,"n.d.") -> 0.10605004 | P7: =IFERROR(I7/J7-1,"n.d.") -> 0.18630138 | Q7: =IFERROR(I7-F7,"n.d.") -> 6.337 | R7: =IFERROR(I7-G7,"n.d.") -> 5.44 | S7: =IFERROR(F7/PIB_2016,"n.d.") -> 0.0012047545 | T7: =IFERROR(G7/PIB_2019,"n.d.") -> 0.0011435716 | U7: =IFERROR(H7/PIB_2022,"n.d.") -> 0.0010895191 | V7: =IFERROR(I7/PIB_2025,"n.d.") -> 0.0010903896 | W7: RREO Anexo 02 (S06) | X7: RREO Anexo 02 (S06) | Y7: RREO Anexo 02 (S06) | Z7: RREO Anexo 02 (S06) | AA7: OFICIAL | AB7: —
A8: 29–30 | B8: Segurança pública (função 06) | C8: Pago | D8: União | E8: R$ bi | F8: 8.423 | G8: 9.018 | H8: 11.729 | I8: 15.41 | J8: =IFERROR(F8*FATOR_2016,"n.d.") -> 13.057334 | K8: =IFERROR(G8*FATOR_2019,"n.d.") -> 12.548822 | L8: =IFERROR(H8*FATOR_2022,"n.d.") -> 13.412416 | M8: =IFERROR(K8/J8-1,"n.d.") -> -0.038944591 | N8: =IFERROR(L8/K8-1,"n.d.") -> 0.068818748 | O8: =IFERROR(I8/L8-1,"n.d.") -> 0.14893543 | P8: =IFERROR(I8/J8-1,"n.d.") -> 0.18017963 | Q8: =IFERROR(I8-F8,"n.d.") -> 6.987 | R8: =IFERROR(I8-G8,"n.d.") -> 6.392 | S8: =IFERROR(F8/PIB_2016,"n.d.") -> 0.0013435254 | T8: =IFERROR(G8/PIB_2019,"n.d.") -> 0.0012204412 | U8: =IFERROR(H8/PIB_2022,"n.d.") -> 0.0011636287 | V8: =IFERROR(I8/PIB_2025,"n.d.") -> 0.0012097123 | W8: Portal da Transparência (S07) | X8: Portal da Transparência (S07) | Y8: Portal da Transparência (S07) | Z8: Portal da Transparência (S07) | AA8: OFICIAL | AB8: Pago segundo o Portal da Transparência: inclui restos a pagar pagos no ano e classificação por função do Portal; pode divergir do RREO (critérios distintos).
A9: 33 | B9: Políticas afirmativas – programa de igualdade racial | C9: Orçamento atualizado (proxy de 'previsto') | D9: União | E9: R$ mi | F9: 39.609 | G9: 12.908 | H9: não localizado após busca | I9: 78.02 | J9: =IFERROR(F9*FATOR_2016,"n.d.") -> 61.401871 | K9: =IFERROR(G9*FATOR_2019,"n.d.") -> 17.961875 | L9: =IFERROR(H9*FATOR_2022,"n.d.") -> n.d. | M9: =IFERROR(K9/J9-1,"n.d.") -> -0.70747023 | N9: =IFERROR(L9/K9-1,"n.d.") -> n.d. | O9: =IFERROR(I9/L9-1,"n.d.") -> n.d. | P9: =IFERROR(I9/J9-1,"n.d.") -> 0.27064533 | Q9: =IFERROR(I9-F9,"n.d.") -> 38.411 | R9: =IFERROR(I9-G9,"n.d.") -> 65.112 | S9: =IFERROR(F9/1000/PIB_2016,"n.d.") -> 6.317903e-06 | T9: =IFERROR(G9/1000/PIB_2019,"n.d.") -> 1.7468901e-06 | U9: =IFERROR(H9/1000/PIB_2022,"n.d.") -> n.d. | V9: =IFERROR(I9/1000/PIB_2025,"n.d.") -> 6.1247082e-06 | W9: Portal – Programa 2034 (S07) | X9: Portal – Programa 2034 (S07) | Y9: Sem programa específico no PPA 2020–23 | Z9: Portal – Programa 5804 (S07) | AA9: APROXIMAÇÃO | AB9: Programa 2034 'Promoção da Igualdade Racial e Superação do Racismo' (PPA 2016–19) × 5804 'Promoção da Igualdade Étnico-Racial, Combate e Superação do Racismo' (PPA 2024–27). Programas diferentes; dotação inicial não localizada.
A10: 34a | B10: Políticas afirmativas – programa de igualdade racial | C10: Empenhado | D10: União | E10: R$ mi | F10: 20.269 | G10: 12.458 | H10: não localizado após busca | I10: 77.486 | J10: =IFERROR(F10*FATOR_2016,"n.d.") -> 31.421003 | K10: =IFERROR(G10*FATOR_2019,"n.d.") -> 17.335687 | L10: =IFERROR(H10*FATOR_2022,"n.d.") -> n.d. | M10: =IFERROR(K10/J10-1,"n.d.") -> -0.44827711 | N10: =IFERROR(L10/K10-1,"n.d.") -> n.d. | O10: =IFERROR(I10/L10-1,"n.d.") -> n.d. | P10: =IFERROR(I10/J10-1,"n.d.") -> 1.4660575 | Q10: =IFERROR(I10-F10,"n.d.") -> 57.217 | R10: =IFERROR(I10-G10,"n.d.") -> 65.028 | S10: =IFERROR(F10/1000/PIB_2016,"n.d.") -> 3.2330424e-06 | T10: =IFERROR(G10/1000/PIB_2019,"n.d.") -> 1.6859899e-06 | U10: =IFERROR(H10/1000/PIB_2022,"n.d.") -> n.d. | V10: =IFERROR(I10/1000/PIB_2025,"n.d.") -> 6.0827883e-06 | W10: S07 | X10: S07 | Y10: Sem programa específico no PPA 2020–23 | Z10: S07 | AA10: APROXIMAÇÃO | AB10: Mesmo recorte da linha acima.
A11: 34b | B11: Políticas afirmativas – programa de igualdade racial | C11: Liquidado | D11: União | E11: R$ mi | F11: 9.406 | G11: 5.937 | H11: não localizado após busca | I11: 60.634 | J11: =IFERROR(F11*FATOR_2016,"n.d.") -> 14.581181 | K11: =IFERROR(G11*FATOR_2019,"n.d.") -> 8.2615164 | L11: =IFERROR(H11*FATOR_2022,"n.d.") -> n.d. | M11: =IFERROR(K11/J11-1,"n.d.") -> -0.43341239 | N11: =IFERROR(L11/K11-1,"n.d.") -> n.d. | O11: =IFERROR(I11/L11-1,"n.d.") -> n.d. | P11: =IFERROR(I11/J11-1,"n.d.") -> 3.1583738 | Q11: =IFERROR(I11-F11,"n.d.") -> 51.228 | R11: =IFERROR(I11-G11,"n.d.") -> 54.697 | S11: =IFERROR(F11/1000/PIB_2016,"n.d.") -> 1.5003205e-06 | T11: =IFERROR(G11/1000/PIB_2019,"n.d.") -> 8.0347743e-07 | U11: =IFERROR(H11/1000/PIB_2022,"n.d.") -> n.d. | V11: =IFERROR(I11/1000/PIB_2025,"n.d.") -> 4.7598764e-06 | W11: S07 | X11: S07 | Y11: Sem programa específico no PPA 2020–23 | Z11: S07 | AA11: APROXIMAÇÃO | AB11: —
